Workbook

Sheet COMISION STAFF
E2: Fecha | F2: =NOW() -> 46324.461 | G2: Grupo | H2: S1 CASHMAX | J2: TLJ | L2: MATEO | M2: % DEVOLUCIÓN | N2: %FALTA META | O2: POR ASESOR
E3: PRODUCTIVIDAD | G3: ASIGNACIÓN | H3: =SUM(F5:F15) -> #N/A | J3: RECAUDO | L3: =SUM(H5:H15) -> #N/A | M3: =L3/H3 -> #N/A | N3: =(H3*9.5%)-L3 -> #N/A | O3: =N3/11 -> #N/A
B4: META | C4: CUMPLIMIENTO | D4: PERCENTIL | E4: Asesor | F4: Asignacion | G4: Cuentas | H4: Recaudo | I4: %_Meta | J4: $_Meta | K4: # GESTIONES | L4: Falta | M4: %_Aporte | N4: DOMINGO 1 | O4: DOMINGO 2 | P4: DOMINGO 3 | Q4: FESTIVO 1 | R4: R DOMINGO 1 | S4: R DOMINGO 2 | T4: R DOMINGO 3 | U4: FESTIVO | V4: FESTIVO 2
B5: 0.12 | C5: =M5/B5 -> #N/A | D5: =IF(C5>=0.95,"S",IF(C5>=0.9,"A",IF(C5>=0.8,"B",IF(C5>=0.7,"C",IF(C5>=0.6,"D","F"))))) -> #N/A | F5: =VLOOKUP(E5,'ASIGNACION RANKING'!D:AB,7,0)-N5-O5 -> #N/A | G5: =VLOOKUP(E5,'ASIGNACION RANKING'!D:AB,6,0) -> #N/A | H5: =VLOOKUP(E5,'ASIGNACION RANKING'!D:AB,11,0)-R5-S5 -> #N/A | I5: 0.15 | J5: =F5*I5 -> #N/A | K5: =VLOOKUP(E5,[1]ASIGNACION!AA1:AM55,13,0) -> #N/A | L5: =J5-H5 -> #N/A | M5: =H5/F5 -> #N/A | N5: =VLOOKUP(E5,'DOMINGO 1'!D:AB,7,0) -> #N/A | O5: =VLOOKUP(E5,'DOMINGO 2'!D:AB,7,0) -> #N/A | P5: 0 | Q5: =VLOOKUP(E5,'FESTIVO 1'!D:AB,7,0) -> #N/A | R5: =VLOOKUP(E5,'DOMINGO 1'!D:AB,11,0) -> #N/A | S5: =VLOOKUP(E5,'DOMINGO 2'!D:AB,11,0) -> #N/A | T5: 0
B6: 0.12 | C6: =M6/B6 -> #N/A | D6: =IF(C6>=0.95,"S",IF(C6>=0.9,"A",IF(C6>=0.8,"B",IF(C6>=0.7,"C",IF(C6>=0.6,"D","F"))))) -> #N/A | F6: =VLOOKUP(E6,'ASIGNACION RANKING'!D:AB,7,0)-N6-O6 -> #N/A | G6: =VLOOKUP(E6,'ASIGNACION RANKING'!D:AB,6,0) -> #N/A | H6: =VLOOKUP(E6,'ASIGNACION RANKING'!D:AB,11,0)-R6-S6 -> #N/A | I6: 0.15 | J6: =F6*I6 -> #N/A | K6: =VLOOKUP(E6,[1]ASIGNACION!AA2:AM56,13,0) -> #N/A | L6: =J6-H6 -> #N/A | M6: =H6/F6 -> #N/A | N6: =VLOOKUP(E6,'DOMINGO 1'!D:AB,7,0) -> #N/A | O6: =VLOOKUP(E6,'DOMINGO 2'!D:AB,7,0) -> #N/A | P6: =VLOOKUP(E6,'DOMINGO 3'!D:AB,7,0) -> #N/A | Q6: 0 | R6: =VLOOKUP(E6,'DOMINGO 1'!D:AB,11,0) -> #N/A | S6: =VLOOKUP(E6,'DOMINGO 2'!D:AB,11,0) -> #N/A | T6: =VLOOKUP(E6,'DOMINGO 3'!D:AB,11,0) -> #N/A
B7: 0.12 | C7: =M7/B7 -> #N/A | D7: =IF(C7>=0.95,"S",IF(C7>=0.9,"A",IF(C7>=0.8,"B",IF(C7>=0.7,"C",IF(C7>=0.6,"D","F"))))) -> #N/A | F7: =VLOOKUP(E7,'ASIGNACION RANKING'!D:AB,7,0)-N7-O7 -> #N/A | G7: =VLOOKUP(E7,'ASIGNACION RANKING'!D:AB,6,0) -> #N/A | H7: =VLOOKUP(E7,'ASIGNACION RANKING'!D:AB,11,0)-R7-S7 -> #N/A | I7: 0.15 | J7: =F7*I7 -> #N/A | K7: =VLOOKUP(E7,[1]ASIGNACION!AA3:AM57,13,0) -> #N/A | L7: =J7-H7 -> #N/A | M7: =H7/F7 -> #N/A | N7: =VLOOKUP(E7,'DOMINGO 1'!D:AB,7,0) -> #N/A | O7: =VLOOKUP(E7,'DOMINGO 2'!D:AB,7,0) -> #N/A | P7: =VLOOKUP(E7,'DOMINGO 3'!D:AB,7,0) -> #N/A | Q7: =VLOOKUP(E7,'FESTIVO 1'!D:AB,7,0) -> #N/A | R7: =VLOOKUP(E7,'DOMINGO 1'!D:AB,11,0) -> #N/A | S7: =VLOOKUP(E7,'DOMINGO 2'!D:AB,11,0) -> #N/A | T7: =VLOOKUP(E7,'DOMINGO 3'!D:AB,11,0) -> #N/A
B8: 0.12 | C8: =M8/B8 -> #N/A | D8: =IF(C8>=0.95,"S",IF(C8>=0.9,"A",IF(C8>=0.8,"B",IF(C8>=0.7,"C",IF(C8>=0.6,"D","F"))))) -> #N/A | F8: =VLOOKUP(E8,'ASIGNACION RANKING'!D:AB,7,0)-N8-O8 -> #N/A | G8: =VLOOKUP(E8,'ASIGNACION RANKING'!D:AB,6,0) -> #N/A | H8: =VLOOKUP(E8,'ASIGNACION RANKING'!D:AB,11,0)-R8-S8 -> #N/A | I8: 0.15 | J8: =F8*I8 -> #N/A | K8: =VLOOKUP(E8,[1]ASIGNACION!AA4:AM58,13,0) -> #N/A | L8: =J8-H8 -> #N/A | M8: =H8/F8 -> #N/A | N8: =VLOOKUP(E8,'DOMINGO 1'!D:AB,7,0) -> #N/A | O8: =VLOOKUP(E8,'DOMINGO 2'!D:AB,7,0) -> #N/A | P8: =VLOOKUP(E8,'DOMINGO 3'!D:AB,7,0) -> #N/A | Q8: =VLOOKUP(E8,'FESTIVO 1'!D:AB,7,0) -> #N/A | R8: =VLOOKUP(E8,'DOMINGO 1'!D:AB,11,0) -> #N/A | S8: =VLOOKUP(E8,'DOMINGO 2'!D:AB,11,0) -> #N/A | T8: =VLOOKUP(E8,'DOMINGO 3'!D:AB,11,0) -> #N/A
B9: 0.12 | C9: =M9/B9 -> #N/A | D9: =IF(C9>=0.95,"S",IF(C9>=0.9,"A",IF(C9>=0.8,"B",IF(C9>=0.7,"C",IF(C9>=0.6,"D","F"))))) -> #N/A | F9: =VLOOKUP(E9,'ASIGNACION RANKING'!D:AB,7,0)-N9-O9 -> #N/A | G9: =VLOOKUP(E9,'ASIGNACION RANKING'!D:AB,6,0) -> #N/A | H9: =VLOOKUP(E9,'ASIGNACION RANKING'!D:AB,11,0)-R9-S9 -> #N/A | I9: 0.15 | J9: =F9*I9 -> #N/A | K9: =VLOOKUP(E9,[1]ASIGNACION!AA5:AM59,13,0) -> #N/A | L9: =J9-H9 -> #N/A | M9: =H9/F9 -> #N/A | N9: =VLOOKUP(E9,'DOMINGO 1'!D:AB,7,0) -> #N/A | O9: =VLOOKUP(E9,'DOMINGO 2'!D:AB,7,0) -> #N/A | P9: =VLOOKUP(E9,'DOMINGO 3'!D:AB,7,0) -> #N/A | Q9: =VLOOKUP(E9,'FESTIVO 1'!D:AB,7,0) -> #N/A | R9: =VLOOKUP(E9,'DOMINGO 1'!D:AB,11,0) -> #N/A | S9: =VLOOKUP(E9,'DOMINGO 2'!D:AB,11,0) -> #N/A | T9: =VLOOKUP(E9,'DOMINGO 3'!D:AB,11,0) -> #N/A
B10: 0.12 | C10: =M10/B10 -> #N/A | D10: =IF(C10>=0.95,"S",IF(C10>=0.9,"A",IF(C10>=0.8,"B",IF(C10>=0.7,"C",IF(C10>=0.6,"D","F"))))) -> #N/A | F10: =VLOOKUP(E10,'ASIGNACION RANKING'!D:AB,7,0)-N10-O10 -> #N/A | G10: =VLOOKUP(E10,'ASIGNACION RANKING'!D:AB,6,0) -> #N/A | H10: =VLOOKUP(E10,'ASIGNACION RANKING'!D:AB,11,0)-R10-S10 -> #N/A | I10: 0.15 | J10: =F10*I10 -> #N/A | K10: =VLOOKUP(E10,[1]ASIGNACION!AA1:AM60,13,0) -> #N/A | L10: =J10-H10 -> #N/A | M10: =H10/F10 -> #N/A | N10: =VLOOKUP(E10,'DOMINGO 1'!D:AB,7,0) -> #N/A | O10: =VLOOKUP(E10,'DOMINGO 2'!D:AB,7,0) -> #N/A | P10: =VLOOKUP(E10,'DOMINGO 3'!D:AB,7,0) -> #N/A | Q10: =VLOOKUP(E10,'FESTIVO 1'!D:AB,7,0) -> #N/A | R10: =VLOOKUP(E10,'DOMINGO 1'!D:AB,11,0) -> #N/A | S10: =VLOOKUP(E10,'DOMINGO 2'!D:AB,11,0) -> #N/A | T10: =VLOOKUP(E10,'DOMINGO 3'!D:AB,11,0) -> #N/A
B11: 0.12 | C11: =M11/B11 -> #N/A | D11: =IF(C11>=0.95,"S",IF(C11>=0.9,"A",IF(C11>=0.8,"B",IF(C11>=0.7,"C",IF(C11>=0.6,"D","F"))))) -> #N/A | F11: =VLOOKUP(E11,'ASIGNACION RANKING'!D:AB,7,0)-N11-O11 -> #N/A | G11: =VLOOKUP(E11,'ASIGNACION RANKING'!D:AB,6,0) -> #N/A | H11: =VLOOKUP(E11,'ASIGNACION RANKING'!D:AB,11,0)-R11-S11 -> #N/A | I11: 0.15 | J11: =F11*I11 -> #N/A | K11: =VLOOKUP(E11,[1]ASIGNACION!AA7:AM61,13,0) -> #N/A | L11: =J11-H11 -> #N/A | M11: =H11/F11 -> #N/A | N11: =VLOOKUP(E11,'DOMINGO 1'!D:AB,7,0) -> #N/A | O11: =VLOOKUP(E11,'DOMINGO 2'!D:AB,7,0) -> #N/A | P11: 0 | Q11: =VLOOKUP(E11,'FESTIVO 1'!D:AB,7,0) -> #N/A | R11: =VLOOKUP(E11,'DOMINGO 1'!D:AB,11,0) -> #N/A | S11: =VLOOKUP(E11,'DOMINGO 2'!D:AB,11,0) -> #N/A | T11: 0
B12: 0.12 | C12: =M12/B12 -> #N/A | D12: =IF(C12>=0.95,"S",IF(C12>=0.9,"A",IF(C12>=0.8,"B",IF(C12>=0.7,"C",IF(C12>=0.6,"D","F"))))) -> #N/A | F12: =VLOOKUP(E12,'ASIGNACION RANKING'!D:AB,7,0)-N12-O12 -> #N/A | G12: =VLOOKUP(E12,'ASIGNACION RANKING'!D:AB,6,0) -> #N/A | H12: =VLOOKUP(E12,'ASIGNACION RANKING'!D:AB,11,0)-R12-S12 -> #N/A | I12: 0.15 | J12: =F12*I12 -> #N/A | K12: =VLOOKUP(E12,[1]ASIGNACION!AA8:AM62,13,0) -> #N/A | L12: =J12-H12 -> #N/A | M12: =H12/F12 -> #N/A | N12: =VLOOKUP(E12,'DOMINGO 1'!D:AB,7,0) -> #N/A | O12: =VLOOKUP(E12,'DOMINGO 2'!D:AB,7,0) -> #N/A | P12: =VLOOKUP(E12,'DOMINGO 3'!D:AB,7,0) -> #N/A | Q12: =VLOOKUP(E12,'FESTIVO 1'!D:AB,7,0) -> #N/A | R12: =VLOOKUP(E12,'DOMINGO 1'!D:AB,11,0) -> #N/A | S12: =VLOOKUP(E12,'DOMINGO 2'!D:AB,11,0) -> #N/A | T12: =VLOOKUP(E12,'DOMINGO 3'!D:AB,11,0) -> #N/A
B13: 0.12 | C13: =M13/B13 -> #N/A | D13: =IF(C13>=0.95,"S",IF(C13>=0.9,"A",IF(C13>=0.8,"B",IF(C13>=0.7,"C",IF(C13>=0.6,"D","F"))))) -> #N/A | F13: =VLOOKUP(E13,'ASIGNACION RANKING'!D:AB,7,0)-N13-O13 -> #N/A | G13: =VLOOKUP(E13,'ASIGNACION RANKING'!D:AB,6,0) -> #N/A | H13: =VLOOKUP(E13,'ASIGNACION RANKING'!D:AB,11,0)-R13-S13 -> #N/A | I13: 0.15 | J13: =F13*I13 -> #N/A | K13: =VLOOKUP(E13,[1]ASIGNACION!AA9:AM63,13,0) -> #N/A | L13: =J13-H13 -> #N/A | M13: =H13/F13 -> #N/A | N13: =VLOOKUP(E13,'DOMINGO 1'!D:AB,7,0) -> #N/A | O13: =VLOOKUP(E13,'DOMINGO 2'!D:AB,7,0) -> #N/A | P13: =VLOOKUP(E13,'DOMINGO 3'!D:AB,7,0) -> #N/A | Q13: 0 | R13: =VLOOKUP(E13,'DOMINGO 1'!D:AB,11,0) -> #N/A | S13: =VLOOKUP(E13,'DOMINGO 2'!D:AB,11,0) -> #N/A | T13: =VLOOKUP(E13,'DOMINGO 3'!D:AB,11,0) -> #N/A
B14: 0.12 | C14: =M14/B14 -> #N/A | D14: =IF(C14>=0.95,"S",IF(C14>=0.9,"A",IF(C14>=0.8,"B",IF(C14>=0.7,"C",IF(C14>=0.6,"D","F"))))) -> #N/A | F14: =VLOOKUP(E14,'ASIGNACION RANKING'!D:AB,7,0)-N14-O14 -> #N/A | G14: =VLOOKUP(E14,'ASIGNACION RANKING'!D:AB,6,0) -> #N/A | H14: =VLOOKUP(E14,'ASIGNACION RANKING'!D:AB,11,0)-R14-S14 -> #N/A | I14: 0.15 | J14: =F14*I14 -> #N/A | K14: =VLOOKUP(E14,[1]ASIGNACION!AA10:AM64,13,0) -> #N/A | L14: =J14-H14 -> #N/A | M14: =H14/F14 -> #N/A | N14: =VLOOKUP(E14,'DOMINGO 1'!D:AB,7,0) -> #N/A | O14: =VLOOKUP(E14,'DOMINGO 2'!D:AB,7,0) -> #N/A | P14: =VLOOKUP(E14,'DOMINGO 3'!D:AB,7,0) -> #N/A | Q14: =VLOOKUP(E14,'FESTIVO 1'!D:AB,7,0) -> #N/A | R14: =VLOOKUP(E14,'DOMINGO 1'!D:AB,11,0) -> #N/A | S14: =VLOOKUP(E14,'DOMINGO 2'!D:AB,11,0) -> #N/A | T14: =VLOOKUP(E14,'DOMINGO 3'!D:AB,11,0) -> #N/A
B15: 0.12 | C15: =M15/B15 -> #N/A | D15: =IF(C15>=0.95,"S",IF(C15>=0.9,"A",IF(C15>=0.8,"B",IF(C15>=0.7,"C",IF(C15>=0.6,"D","F"))))) -> #N/A | F15: =VLOOKUP(E15,'ASIGNACION RANKING'!D:AB,7,0)-N15-O15 -> #N/A | G15: =VLOOKUP(E15,'ASIGNACION RANKING'!D:AB,6,0) -> #N/A | H15: =VLOOKUP(E15,'ASIGNACION RANKING'!D:AB,11,0)-R15-S15 -> #N/A | I15: 0.15 | J15: =F15*I15 -> #N/A | L15: =J15-H15 -> #N/A | M15: =H15/F15 -> #N/A | N15: =VLOOKUP(E15,'DOMINGO 1'!D:AB,7,0) -> #N/A | O15: =VLOOKUP(E15,'DOMINGO 2'!D:AB,7,0) -> #N/A | P15: =VLOOKUP(E15,'DOMINGO 3'!D:AB,7,0) -> #N/A | Q15: =VLOOKUP(E15,'FESTIVO 1'!D:AB,7,0) -> #N/A | R15: =VLOOKUP(E15,'DOMINGO 1'!D:AB,11,0) -> #N/A | S15: =VLOOKUP(E15,'DOMINGO 2'!D:AB,11,0) -> #N/A | T15: =VLOOKUP(E15,'DOMINGO 3'!D:AB,11,0) -> #N/A
E17: Fecha | F17: =NOW() -> 46324.461 | G17: Grupo | H17: S2 CASHMAX | J17: TLJ | L17: MATEO | M17: % DEVOLUCIÓN | N17: %FALTA META | O17: POR ASESOR
E18: PRODUCTIVIDAD | G18: ASIGNACIÓN | H18: =SUM(F20:F29) -> #N/A | J18: RECUADO | L18: =SUM(H20:H29) -> #N/A | M18: =L18/H18 -> #N/A | N18: =(H18*1.2%)-L18 -> #N/A | O18: =N18/10 -> #N/A
B19: META | C19: CUMPLIMIENTO | D19: PERCENTIL | E19: Asesor | F19: Asignacion | G19: Cuentas | H19: Recaudo | I19: %_Meta | J19: $_Meta | K19: # GESTIONES | L19: Falta | M19: %_Aporte | N19: DOMINGO 1 | O19: DOMINGO 2 | P19: DOMINGO 3 | Q19: FESTIVO 1 | R19: FESTIVO 2
B20: 0.012 | C20: =M20/B20 -> #N/A | D20: =IF(C20>=0.95,"S",IF(C20>=0.9,"A",IF(C20>=0.8,"B",IF(C20>=0.7,"C",IF(C20>=0.6,"D","F"))))) -> #N/A | E20: A0120(CRISTIAN RODRIGUEZ ) | F20: =VLOOKUP(E20,'ASIGNACION RANKING'!D:AB,7,0)-N20-O20 -> #N/A | G20: =VLOOKUP(E20,'ASIGNACION RANKING'!D:AB,6,0) -> #N/A | H20: =VLOOKUP(E20,'ASIGNACION RANKING'!D:AB,11,0) -> #N/A | I20: 0.018 | J20: =F20*I20 -> #N/A | K20: =VLOOKUP(E20,[1]ASIGNACION!AA1:AM75,13,0) -> #N/A | L20: =J20-H20 -> #N/A | M20: =H20/F20 -> #N/A | N20: =VLOOKUP(E20,'DOMINGO 1'!D:AB,7,0) -> #N/A | O20: =VLOOKUP(E20,'DOMINGO 2'!D:AB,7,0) -> #N/A | P20: =VLOOKUP(E20,'DOMINGO 3'!D:AB,7,0) -> #N/A | Q20: =VLOOKUP(E20,'FESTIVO 1'!D:AB,7,0) -> #N/A
B21: 0.012 | C21: =M21/B21 -> #N/A | D21: =IF(C21>=0.95,"S",IF(C21>=0.9,"A",IF(C21>=0.8,"B",IF(C21>=0.7,"C",IF(C21>=0.6,"D","F"))))) -> #N/A | E21: A0068(JENNY MENDIETA) | F21: =VLOOKUP(E21,'ASIGNACION RANKING'!D:AB,7,0)-N21-O21 -> #N/A | G21: =VLOOKUP(E21,'ASIGNACION RANKING'!D:AB,6,0) -> #N/A | H21: =VLOOKUP(E21,'ASIGNACION RANKING'!D:AB,11,0) -> #N/A | I21: 0.018 | J21: =F21*I21 -> #N/A | K21: =VLOOKUP(E21,[1]ASIGNACION!AA2:AM76,13,0) -> #N/A | L21: =J21-H21 -> #N/A | M21: =H21/F21 -> #N/A | N21: =VLOOKUP(E21,'DOMINGO 1'!D:AB,7,0) -> #N/A | O21: =VLOOKUP(E21,'DOMINGO 2'!D:AB,7,0) -> #N/A | P21: =VLOOKUP(E21,'DOMINGO 3'!D:AB,7,0) -> #N/A | Q21: =VLOOKUP(E21,'FESTIVO 1'!D:AB,7,0) -> #N/A
B22: 0.012 | C22: =M22/B22 -> #N/A | D22: =IF(C22>=0.95,"S",IF(C22>=0.9,"A",IF(C22>=0.8,"B",IF(C22>=0.7,"C",IF(C22>=0.6,"D","F"))))) -> #N/A | E22: A03290(JOHAN OJEDA) | F22: =VLOOKUP(E22,'ASIGNACION RANKING'!D:AB,7,0)-N22-O22 -> #N/A | G22: =VLOOKUP(E22,'ASIGNACION RANKING'!D:AB,6,0) -> #N/A | H22: =VLOOKUP(E22,'ASIGNACION RANKING'!D:AB,11,0) -> #N/A | I22: 0.018 | J22: =F22*I22 -> #N/A | K22: =VLOOKUP(E22,[1]ASIGNACION!AA3:AM77,13,0) -> #N/A | L22: =J22-H22 -> #N/A | M22: =H22/F22 -> #N/A | N22: =VLOOKUP(E22,'DOMINGO 1'!D:AB,7,0) -> #N/A | O22: =VLOOKUP(E22,'DOMINGO 2'!D:AB,7,0) -> #N/A | P22: =VLOOKUP(E22,'DOMINGO 3'!D:AB,7,0) -> #N/A | Q22: =VLOOKUP(E22,'FESTIVO 1'!D:AB,7,0) -> #N/A
B23: 0.012 | C23: =M23/B23 -> #N/A | D23: =IF(C23>=0.95,"S",IF(C23>=0.9,"A",IF(C23>=0.8,"B",IF(C23>=0.7,"C",IF(C23>=0.6,"D","F"))))) -> #N/A | E23: A0364(JOSE VERA) | F23: =VLOOKUP(E23,'ASIGNACION RANKING'!D:AB,7,0)-N23-O23 -> #N/A | G23: =VLOOKUP(E23,'ASIGNACION RANKING'!D:AB,6,0) -> #N/A | H23: =VLOOKUP(E23,'ASIGNACION RANKING'!D:AB,11,0) -> #N/A | I23: 0.018 | J23: =F23*I23 -> #N/A | K23: =VLOOKUP(E23,[1]ASIGNACION!AA4:AM78,13,0) -> #N/A | L23: =J23-H23 -> #N/A | M23: =H23/F23 -> #N/A | N23: =VLOOKUP(E23,'DOMINGO 1'!D:AB,7,0) -> #N/A | O23: =VLOOKUP(E23,'DOMINGO 2'!D:AB,7,0) -> #N/A | P23: =VLOOKUP(E23,'DOMINGO 3'!D:AB,7,0) -> #N/A | Q23: =VLOOKUP(E23,'FESTIVO 1'!D:AB,7,0) -> #N/A
B24: 0.012 | C24: =M24/B24 -> #N/A | D24: =IF(C24>=0.95,"S",IF(C24>=0.9,"A",IF(C24>=0.8,"B",IF(C24>=0.7,"C",IF(C24>=0.6,"D","F"))))) -> #N/A | E24: A0340(KAFFYR PUERTAS) | F24: =VLOOKUP(E24,'ASIGNACION RANKING'!D:AB,7,0)-N24-O24 -> #N/A | G24: =VLOOKUP(E24,'ASIGNACION RANKING'!D:AB,6,0) -> #N/A | H24: =VLOOKUP(E24,'ASIGNACION RANKING'!D:AB,11,0) -> #N/A | I24: 0.018 | J24: =F24*I24 -> #N/A | K24: =VLOOKUP(E24,[1]ASIGNACION!AA5:AM79,13,0) -> #N/A | L24: =J24-H24 -> #N/A | M24: =H24/F24 -> #N/A | N24: =VLOOKUP(E24,'DOMINGO 1'!D:AB,7,0) -> #N/A | O24: =VLOOKUP(E24,'DOMINGO 2'!D:AB,7,0) -> #N/A | P24: =VLOOKUP(E24,'DOMINGO 3'!D:AB,7,0) -> #N/A | Q24: =VLOOKUP(E24,'FESTIVO 1'!D:AB,7,0) -> #N/A
B25: 0.012 | C25: =M25/B25 -> #N/A | D25: =IF(C25>=0.95,"S",IF(C25>=0.9,"A",IF(C25>=0.8,"B",IF(C25>=0.7,"C",IF(C25>=0.6,"D","F"))))) -> #N/A | E25: A0053(LAURA RUBIANO) | F25: =VLOOKUP(E25,'ASIGNACION RANKING'!D:AB,7,0)-N25-O25 -> #N/A | G25: =VLOOKUP(E25,'ASIGNACION RANKING'!D:AB,6,0) -> #N/A | H25: =VLOOKUP(E25,'ASIGNACION RANKING'!D:AB,11,0) -> #N/A | I25: 0.018 | J25: =F25*I25 -> #N/A | K25: =VLOOKUP(E25,[1]ASIGNACION!AA6:AM80,13,0) -> #N/A | L25: =J25-H25 -> #N/A | M25: =H25/F25 -> #N/A | N25: =VLOOKUP(E25,'DOMINGO 1'!D:AB,7,0) -> #N/A | O25: =VLOOKUP(E25,'DOMINGO 2'!D:AB,7,0) -> #N/A | P25: =VLOOKUP(E25,'DOMINGO 3'!D:AB,7,0) -> #N/A | Q25: =VLOOKUP(E25,'FESTIVO 1'!D:AB,7,0) -> #N/A
B26: 0.012 | C26: =M26/B26 -> #N/A | D26: =IF(C26>=0.95,"S",IF(C26>=0.9,"A",IF(C26>=0.8,"B",IF(C26>=0.7,"C",IF(C26>=0.6,"D","F"))))) -> #N/A | E26: A0360(MARCELA VALDERRAMA) | F26: =VLOOKUP(E26,'ASIGNACION RANKING'!D:AB,7,0)-N26-O26 -> #N/A | G26: =VLOOKUP(E26,'ASIGNACION RANKING'!D:AB,6,0) -> #N/A | H26: =VLOOKUP(E26,'ASIGNACION RANKING'!D:AB,11,0) -> #N/A | I26: 0.018 | J26: =F26*I26 -> #N/A | K26: =VLOOKUP(E26,[1]ASIGNACION!AA7:AM81,13,0) -> #N/A | L26: =J26-H26 -> #N/A | M26: =H26/F26 -> #N/A | N26: =VLOOKUP(E26,'DOMINGO 1'!D:AB,7,0) -> #N/A | O26: =VLOOKUP(E26,'DOMINGO 2'!D:AB,7,0) -> #N/A | P26: =VLOOKUP(E26,'DOMINGO 3'!D:AB,7,0) -> #N/A | Q26: =VLOOKUP(E26,'FESTIVO 1'!D:AB,7,0) -> #N/A
B27: 0.012 | C27: =M27/B27 -> #N/A | D27: =IF(C27>=0.95,"S",IF(C27>=0.9,"A",IF(C27>=0.8,"B",IF(C27>=0.7,"C",IF(C27>=0.6,"D","F"))))) -> #N/A | E27: A0315(MATEO PINTO) | F27: =VLOOKUP(E27,'ASIGNACION RANKING'!D:AB,7,0)-N27-O27 -> #N/A | G27: =VLOOKUP(E27,'ASIGNACION RANKING'!D:AB,6,0) -> #N/A | H27: =VLOOKUP(E27,'ASIGNACION RANKING'!D:AB,11,0) -> #N/A | I27: 0.018 | J27: =F27*I27 -> #N/A | K27: =VLOOKUP(E27,[1]ASIGNACION!AA8:AM82,13,0) -> #N/A | L27: =J27-H27 -> #N/A | M27: =H27/F27 -> #N/A | N27: =VLOOKUP(E27,'DOMINGO 1'!D:AB,7,0) -> #N/A | O27: =VLOOKUP(E27,'DOMINGO 2'!D:AB,7,0) -> #N/A | P27: =VLOOKUP(E27,'DOMINGO 3'!D:AB,7,0) -> #N/A | Q27: =VLOOKUP(E27,'FESTIVO 1'!D:AB,7,0) -> #N/A
B28: 0.012 | C28: =M28/B28 -> #N/A | D28: =IF(C28>=0.95,"S",IF(C28>=0.9,"A",IF(C28>=0.8,"B",IF(C28>=0.7,"C",IF(C28>=0.6,"D","F"))))) -> #N/A | E28: A0135(PAULA RODRIGUEZ ) | F28: =VLOOKUP(E28,'ASIGNACION RANKING'!D:AB,7,0)-N28-O28 -> #N/A | G28: =VLOOKUP(E28,'ASIGNACION RANKING'!D:AB,6,0) -> #N/A | H28: =VLOOKUP(E28,'ASIGNACION RANKING'!D:AB,11,0) -> #N/A | I28: 0.018 | J28: =F28*I28 -> #N/A | K28: =VLOOKUP(E28,[1]ASIGNACION!AA9:AM83,13,0) -> #N/A | L28: =J28-H28 -> #N/A | M28: =H28/F28 -> #N/A | N28: =VLOOKUP(E28,'DOMINGO 1'!D:AB,7,0) -> #N/A | O28: =VLOOKUP(E28,'DOMINGO 2'!D:AB,7,0) -> #N/A | P28: =VLOOKUP(E28,'DOMINGO 3'!D:AB,7,0) -> #N/A | Q28: =VLOOKUP(E28,'FESTIVO 1'!D:AB,7,0) -> #N/A
B29: 0.012 | C29: =M29/B29 -> #N/A | D29: =IF(C29>=0.95,"S",IF(C29>=0.9,"A",IF(C29>=0.8,"B",IF(C29>=0.7,"C",IF(C29>=0.6,"D","F"))))) -> #N/A | E29: A0217(SEBASTIAN BARRIOS) | F29: =VLOOKUP(E29,'ASIGNACION RANKING'!D:AB,7,0)-N29-O29 -> #N/A | G29: =VLOOKUP(E29,'ASIGNACION RANKING'!D:AB,6,0) -> #N/A | H29: =VLOOKUP(E29,'ASIGNACION RANKING'!D:AB,11,0) -> #N/A | I29: 0.018 | J29: =F29*I29 -> #N/A | K29: =VLOOKUP(E29,[1]ASIGNACION!AA9:AM82,13,0) -> #N/A | L29: =J29-H29 -> #N/A | M29: =H29/F29 -> #N/A | N29: =VLOOKUP(E29,'DOMINGO 1'!D:AB,7,0) -> #N/A | O29: =VLOOKUP(E29,'DOMINGO 2'!D:AB,7,0) -> #N/A | P29: =VLOOKUP(E29,'DOMINGO 3'!D:AB,7,0) -> #N/A | Q29: =VLOOKUP(E29,'FESTIVO 1'!D:AB,7,0) -> #N/A
E31: Fecha | F31: =NOW() -> 46324.461 | G31: Grupo | H31: M1 CASHMAX | J31: TLJ | L31: MATEO | M31: % DEVOLUCIÓN | N31: %FALTA META | O31: POR ASESOR
E32: PRODUCTIVIDAD | G32: ASIGNACIÓN | H32: =SUM(F34:F41) -> #N/A | J32: RECUADO | L32: =SUM(H34:H41) -> #N/A | M32: =L32/H32 -> #N/A | N32: =(H32*0.11%)-L32 -> #N/A | O32: =N32/7 -> #N/A
B33: META | C33: CUMPLIMIENTO | D33: PERCENTIL | E33: Asesor | F33: Asignacion | G33: Cuentas | H33: Recaudo | I33: %_Meta | J33: $_Meta | K33: # GESTIONES | L33: Falta | M33: %_Aporte | N33: DOMINGO 1 | O33: DOMINGO 2 | P33: DOMINGO 3 | Q33: FESTIVO 1 | R33: FESTIVO 2
B34: 0.0015 | C34: =M34/B34 -> #N/A | D34: =IF(C34>=0.95,"S",IF(C34>=0.9,"A",IF(C34>=0.8,"B",IF(C34>=0.7,"C",IF(C34>=0.6,"D","F"))))) -> #N/A | F34: =VLOOKUP(E34,'ASIGNACION RANKING'!D:AB,7,0)-N34-O34 -> #N/A | G34: =VLOOKUP(E34,'ASIGNACION RANKING'!D:AB,6,0) -> #N/A | H34: =VLOOKUP(E34,'ASIGNACION RANKING'!D:AB,11,0) -> #N/A | I34: 0.002 | J34: =F34*I34 -> #N/A | K34: =VLOOKUP(E34,[1]ASIGNACION!AA1:AM85,13,0) -> #N/A | L34: =J34-H34 -> #N/A | M34: =H34/F34 -> #N/A | N34: =VLOOKUP(E34,'DOMINGO 1'!D:AB,7,0) -> #N/A | O34: =VLOOKUP(E34,'DOMINGO 2'!D:AB,7,0) -> #N/A | P34: =VLOOKUP(E34,'DOMINGO 3'!D:AB,7,0) -> #N/A | Q34: =VLOOKUP(E34,'FESTIVO 1'!D:AB,7,0) -> #N/A
B35: 0.0015 | C35: =M35/B35 -> #N/A | D35: =IF(C35>=0.95,"S",IF(C35>=0.9,"A",IF(C35>=0.8,"B",IF(C35>=0.7,"C",IF(C35>=0.6,"D","F"))))) -> #N/A | F35: =VLOOKUP(E35,'ASIGNACION RANKING'!D:AB,7,0)-N35-O35 -> #N/A | G35: =VLOOKUP(E35,'ASIGNACION RANKING'!D:AB,6,0) -> #N/A | H35: =VLOOKUP(E35,'ASIGNACION RANKING'!D:AB,11,0) -> #N/A | I35: 0.002 | J35: =F35*I35 -> #N/A | K35: =VLOOKUP(E35,[1]ASIGNACION!AA2:AM86,13,0) -> #N/A | L35: =J35-H35 -> #N/A | M35: =H35/F35 -> #N/A | N35: =VLOOKUP(E35,'DOMINGO 1'!D:AB,7,0) -> #N/A | O35: =VLOOKUP(E35,'DOMINGO 2'!D:AB,7,0) -> #N/A | P35: 0 | Q35: =VLOOKUP(E35,'FESTIVO 1'!D:AB,7,0) -> #N/A
B36: 0.0015 | C36: =M36/B36 -> #N/A | D36: =IF(C36>=0.95,"S",IF(C36>=0.9,"A",IF(C36>=0.8,"B",IF(C36>=0.7,"C",IF(C36>=0.6,"D","F"))))) -> #N/A | F36: =VLOOKUP(E36,'ASIGNACION RANKING'!D:AB,7,0)-N36-O36 -> #N/A | G36: =VLOOKUP(E36,'ASIGNACION RANKING'!D:AB,6,0) -> #N/A | H36: =VLOOKUP(E36,'ASIGNACION RANKING'!D:AB,11,0) -> #N/A | I36: 0.002 | J36: =F36*I36 -> #N/A | K36: =VLOOKUP(E36,[1]ASIGNACION!AA3:AM86,13,0) -> #N/A | L36: =J36-H36 -> #N/A | M36: =H36/F36 -> #N/A | N36: =VLOOKUP(E36,'DOMINGO 1'!D:AB,7,0) -> #N/A | O36: =VLOOKUP(E36,'DOMINGO 2'!D:AB,7,0) -> #N/A | P36: =VLOOKUP(E36,'DOMINGO 3'!D:AB,7,0) -> #N/A | Q36: =VLOOKUP(E36,'FESTIVO 1'!D:AB,7,0) -> #N/A
B37: 0.0015 | C37: =M37/B37 -> #N/A | D37: =IF(C37>=0.95,"S",IF(C37>=0.9,"A",IF(C37>=0.8,"B",IF(C37>=0.7,"C",IF(C37>=0.6,"D","F"))))) -> #N/A | F37: =VLOOKUP(E37,'ASIGNACION RANKING'!D:AB,7,0)-N37-O37 -> #N/A | G37: =VLOOKUP(E37,'ASIGNACION RANKING'!D:AB,6,0) -> #N/A | H37: =VLOOKUP(E37,'ASIGNACION RANKING'!D:AB,11,0) -> #N/A | I37: 0.002 | J37: =F37*I37 -> #N/A | K37: =VLOOKUP(E37,[1]ASIGNACION!AA4:AM86,13,0) -> #N/A | L37: =J37-H37 -> #N/A | M37: =H37/F37 -> #N/A | N37: =VLOOKUP(E37,'DOMINGO 1'!D:AB,7,0) -> #N/A | O37: =VLOOKUP(E37,'DOMINGO 2'!D:AB,7,0) -> #N/A | P37: =VLOOKUP(E37,'DOMINGO 3'!D:AB,7,0) -> #N/A | Q37: 0
B38: 0.0015 | C38: =M38/B38 -> #N/A | D38: =IF(C38>=0.95,"S",IF(C38>=0.9,"A",IF(C38>=0.8,"B",IF(C38>=0.7,"C",IF(C38>=0.6,"D","F"))))) -> #N/A | F38: =VLOOKUP(E38,'ASIGNACION RANKING'!D:AB,7,0)-N38-O38 -> #N/A | G38: =VLOOKUP(E38,'ASIGNACION RANKING'!D:AB,6,0) -> #N/A | H38: =VLOOKUP(E38,'ASIGNACION RANKING'!D:AB,11,0) -> #N/A | I38: 0.002 | J38: =F38*I38 -> #N/A | K38: =VLOOKUP(E38,[1]ASIGNACION!AA5:AM86,13,0) -> #N/A | L38: =J38-H38 -> #N/A | M38: =H38/F38 -> #N/A | N38: =VLOOKUP(E38,'DOMINGO 1'!D:AB,7,0) -> #N/A | O38: =VLOOKUP(E38,'DOMINGO 2'!D:AB,7,0) -> #N/A | P38: 0 | Q38: =VLOOKUP(E38,'FESTIVO 1'!D:AB,7,0) -> #N/A
B39: 0.0015 | C39: =M39/B39 -> #DIV/0! | D39: =IF(C39>=0.95,"S",IF(C39>=0.9,"A",IF(C39>=0.8,"B",IF(C39>=0.7,"C",IF(C39>=0.6,"D","F"))))) -> #DIV/0! | K39: =VLOOKUP(E39,[1]ASIGNACION!AA6:AM86,13,0) -> #N/A | L39: =J39-H39 -> 0 | M39: =H39/F39 -> #DIV/0! | N39: =VLOOKUP(E39,'DOMINGO 1'!D:AB,7,0) -> #N/A | O39: =VLOOKUP(E39,'DOMINGO 2'!D:AB,7,0) -> #N/A | P39: =VLOOKUP(E39,'DOMINGO 3'!D:AB,7,0) -> #N/A | Q39: =VLOOKUP(E39,'FESTIVO 1'!D:AB,7,0) -> #N/A
B40: 0.0015 | C40: =M40/B40 -> #DIV/0! | D40: =IF(C40>=0.95,"S",IF(C40>=0.9,"A",IF(C40>=0.8,"B",IF(C40>=0.7,"C",IF(C40>=0.6,"D","F"))))) -> #DIV/0! | L40: =J40-H40 -> 0 | M40: =H40/F40 -> #DIV/0! | N40: =VLOOKUP(E40,'DOMINGO 1'!D:AB,7,0) -> #N/A | O40: =VLOOKUP(E40,'DOMINGO 2'!D:AB,7,0) -> #N/A | P40: =VLOOKUP(E40,'DOMINGO 3'!D:AB,7,0) -> #N/A | Q40: 0
B41: 0.0015 | C41: =M41/B41 -> #DIV/0! | D41: =IF(C41>=0.95,"S",IF(C41>=0.9,"A",IF(C41>=0.8,"B",IF(C41>=0.7,"C",IF(C41>=0.6,"D","F"))))) -> #DIV/0! | K41: =VLOOKUP(E41,[1]ASIGNACION!AA7:AM86,13,0) -> #N/A | L41: =J41-H41 -> 0 | M41: =H41/F41 -> #DIV/0! | N41: =VLOOKUP(E41,'DOMINGO 1'!D:AB,7,0) -> #N/A | O41: =VLOOKUP(E41,'DOMINGO 2'!D:AB,7,0) -> #N/A | P41: =VLOOKUP(E41,'DOMINGO 3'!D:AB,7,0) -> #N/A | Q41: =VLOOKUP(E41,'FESTIVO 1'!D:AB,7,0) -> #N/A
D43: PORCENTAJE | E43: PERCENTILES | F43: SIGNIFICA | Q43: S1
D44: 0.95 | E44: S | F44: PILAR, ARRASTRA LA CIFRA DE MANERA POSITIVA | Q44: % DE RECUPERACION | R44: COMISION | S44: PISO
D45: 0.9 | E45: A | F45: CUMPLE, ESTA DENTRO DE LA MEDIA ALTA | Q45: 0.055 | R45: 100000 | S45: PISO 1
D46: 0.8 | E46: B | F46: MEDIA, TIENE PUNTOS A MEJORAR | Q46: 0.06 | R46: 160000 | S46: PISO 2
D47: 0.7 | E47: C | F47: RESULTADOS BAJOS, SE DEBE HACER SEGUIMIENTO | Q47: 0.07 | R47: 240000 | S47: PISO 3
D48: 0.6 | E48: D | F48: RESULTADOS DEFICIENTES, FOCO #1 PARA MEJORAR | L48: COMISION MATEO | Q48: 0.08 | R48: 350000 | S48: PISO 4
L49: CARTERA | M49: COMISION | Q49: 0.09 | R49: 500000 | S49: PISO 5
D50: CARTERAS MIXTAS | L50: S1 | M50: =IF(M3<=Q45,0,IF(M3<=Q46,R45,IF(M3<=Q47,R46,IF(M3<=Q48,R47,IF(M3<=Q49,R48,IF(M3<=100%,R49)))))) -> #N/A | Q50: S2
D51: CUMPLIDO | E51: META | F51: CUMPLIMIENTO | L51: S2 | M51: =IF(M18<=Q52,0,IF(M18<=Q53,R52,IF(M18<=Q54,R53,IF(M18<=Q55,R54,IF(M18<=Q56,R55,IF(M18<=100%,R56)))))) -> #N/A | Q51: % DE RECUPERACION | R51: COMISION | S51: PISO
D52: 0.102 | E52: 0.11 | F52: =D52/E52 -> 0.92727273 | L52: M1 | M52: =IF(M32<=Q59,0,IF(M32<=Q60,R59,IF(M32<=Q61,R60,IF(M32<=Q62,R61,IF(M32<=Q63,R62,IF(M32<=100%,R63)))))) -> #N/A | Q52: 0.006 | R52: 140000 | S52: PISO 1
D53: 0.0119 | E53: 0.015 | F53: =D53/E53 -> 0.79333333 | L53: TOTAL | M53: =SUM(M50:M52) -> #N/A | Q53: 0.008 | R53: 200000 | S53: PISO 2
D54: 0.00172 | E54: 0.0015 | F54: =D54/E54 -> 1.1466667 | Q54: 0.01 | R54: 280000 | S54: PISO 3
D55: CUMPLIMIENTO GOLBAL | F55: =AVERAGE(F52:F54) -> 0.95575758 | Q55: 0.012 | R55: 370000 | S55: PISO 4
D56: PERCENTIL | F56: =IF(F55>=0.95,"S",IF(F55>=0.9,"A",IF(F55>=0.8,"B",IF(F55>=0.7,"C",IF(F55>=0.6,"D","F"))))) -> S | Q56: 0.015 | R56: 460000 | S56: PISO 5
Q57: M1
D58: CARTERA ESPECIALIZADA S1 | Q58: % DE RECUPERACION | R58: COMISION | S58: PISO
D59: CUMPLIDO | E59: META | F59: CUMPLIMIENTO | Q59: 0.0007 | R59: 160000 | S59: PISO 1
D60: 0.0979 | E60: 0.11 | F60: =D60/E60 -> 0.89 | Q60: 0.0009 | R60: 230000 | S60: PISO 2
D61: 0.1023 | E61: 0.11 | F61: =D61/E61 -> 0.93 | Q61: 0.0011 | R61: 300000 | S61: PISO 3
D62: 0.0732 | E62: 0.11 | F62: =D62/E62 -> 0.66545455 | Q62: 0.0013 | R62: 410000 | S62: PISO 4
D63: CUMPLIMIENTO GOLBAL | F63: =AVERAGE(F60:F62) -> 0.82848485 | Q63: 0.0015 | R63: 560000 | S63: PISO 5
D64: PERCENTIL | F64: =IF(F63>=0.95,"S",IF(F63>=0.9,"A",IF(F63>=0.8,"B",IF(F63>=0.7,"C",IF(F63>=0.6,"D","F"))))) -> B
E69: Fecha | F69: =NOW() -> 46324.461 | G69: Grupo | H69: S1 OKDINERO | J69: TLJ | L69: KATHERINE | M69: % DEVOLUCIÓN | N69: %FALTA META | O69: POR ASESOR
E70: PRODUCTIVIDAD | G70: ASIGNACIÓN | H70: =SUM(F72:F86) -> 22008300 | J70: RECAUDO | L70: =SUM(H72:H86) -> 1884885 | M70: =L70/H70 -> 0.08564428 | N70: =(H70*9.5%)-L70 -> 205903.5 | O70: =N70/13 -> 15838.731
B71: META | C71: CUMPLIMIENTO | D71: PERCENTIL | E71: Asesor | F71: Asignacion | G71: Cuentas | H71: Recaudo | I71: %_Meta | J71: $_Meta | K71: # GESTIONES | L71: Falta | M71: %_Aporte | N71: DOMINGO 1 | O71: DOMINGO 2 | P71: DOMINGO 3 | Q71: FESTIVO 1 | R71: R DOMINGO 1 | S71: R DOMINGO 2 | T71: DOMINGO 3 | U71: FESTIVO | V71: FESTIVO 2
B72: 0.12 | C72: =M72/B72 -> 0.74495419 | D72: =IF(C72>=0.95,"S",IF(C72>=0.9,"A",IF(C72>=0.8,"B",IF(C72>=0.7,"C",IF(C72>=0.6,"D","F"))))) -> C | E72: A0258(CRIS URREGO) | F72: =VLOOKUP(E72,'ASIGNACION RANKING'!D:AB,7,0)-N72 -> 1636208 | G72: =VLOOKUP(E72,'ASIGNACION RANKING'!D:AB,6,0) -> 928 | H72: =VLOOKUP(E72,'ASIGNACION RANKING'!D:AB,11,0)-R72 -> 146268 | I72: 0.15 | J72: =F72*I72 -> 245431.2 | K72: =VLOOKUP(E72,[1]ASIGNACION!AA67:AM121,13,0) -> #N/A | L72: =J72-H72 -> 99163.2 | M72: =H72/F72 -> 0.089394502 | N72: =VLOOKUP(E72,'DOMINGO 1'!D:AB,7,0) -> 148155 | O72: =VLOOKUP(E72,'DOMINGO 2'!D:AB,7,0) -> 135241 | Q72: =VLOOKUP(E72,'FESTIVO 1'!D:AB,7,0) -> 102643 | R72: =VLOOKUP(E72,'DOMINGO 1'!D:AB,11,0) -> 3898 | S72: =VLOOKUP(E72,'DOMINGO 2'!D:AB,11,0) -> 6698 | T72: =VLOOKUP(E72,'DOMINGO 3'!D:AB,11,0) -> #N/A
B73: 0.12 | C73: =M73/B73 -> 0.7713807 | D73: =IF(C73>=0.95,"S",IF(C73>=0.9,"A",IF(C73>=0.8,"B",IF(C73>=0.7,"C",IF(C73>=0.6,"D","F"))))) -> C | E73: A0221(DAVID GOMEZ) | F73: =VLOOKUP(E73,'ASIGNACION RANKING'!D:AB,7,0)-N73 -> 1569102 | G73: =VLOOKUP(E73,'ASIGNACION RANKING'!D:AB,6,0) -> 892 | H73: =VLOOKUP(E73,'ASIGNACION RANKING'!D:AB,11,0)-R73 -> 145245 | I73: 0.15 | J73: =F73*I73 -> 235365.3 | K73: =VLOOKUP(E73,[1]ASIGNACION!AA68:AM122,13,0) -> #N/A | L73: =J73-H73 -> 90120.3 | M73: =H73/F73 -> 0.092565684 | N73: =VLOOKUP(E73,'DOMINGO 1'!D:AB,7,0) -> 130494 | O73: =VLOOKUP(E73,'DOMINGO 2'!D:AB,7,0) -> 116669 | Q73: =VLOOKUP(E73,'FESTIVO 1'!D:AB,7,0) -> 118427 | R73: =VLOOKUP(E73,'DOMINGO 1'!D:AB,11,0) -> 17387 | S73: =VLOOKUP(E73,'DOMINGO 2'!D:AB,11,0) -> 680 | T73: =VLOOKUP(E73,'DOMINGO 3'!D:AB,11,0) -> #N/A
B74: 0.12 | C74: =M74/B74 -> 0.76193875 | D74: =IF(C74>=0.95,"S",IF(C74>=0.9,"A",IF(C74>=0.8,"B",IF(C74>=0.7,"C",IF(C74>=0.6,"D","F"))))) -> C | E74: A0288(FABIAN STIVEN) | F74: =VLOOKUP(E74,'ASIGNACION RANKING'!D:AB,7,0)-N74 -> 1539811 | G74: =VLOOKUP(E74,'ASIGNACION RANKING'!D:AB,6,0) -> 960 | H74: =VLOOKUP(E74,'ASIGNACION RANKING'!D:AB,11,0)-R74 -> 140789 | I74: 0.15 | J74: =F74*I74 -> 230971.65 | K74: =VLOOKUP(E74,[1]ASIGNACION!AA69:AM123,13,0) -> #N/A | L74: =J74-H74 -> 90182.65 | M74: =H74/F74 -> 0.09143265 | N74: =VLOOKUP(E74,'DOMINGO 1'!D:AB,7,0) -> 144616 | O74: =VLOOKUP(E74,'DOMINGO 2'!D:AB,7,0) -> 104116 | Q74: =VLOOKUP(E74,'FESTIVO 1'!D:AB,7,0) -> 103509 | R74: =VLOOKUP(E74,'DOMINGO 1'!D:AB,11,0) -> 5765 | S74: =VLOOKUP(E74,'DOMINGO 2'!D:AB,11,0) -> 3989 | T74: =VLOOKUP(E74,'DOMINGO 3'!D:AB,11,0) -> #N/A
B75: 0.12 | C75: =M75/B75 -> #DIV/0! | D75: =IF(C75>=0.95,"S",IF(C75>=0.9,"A",IF(C75>=0.8,"B",IF(C75>=0.7,"C",IF(C75>=0.6,"D","F"))))) -> #DIV/0! | I75: 0.15 | J75: =F75*I75 -> 0 | K75: =VLOOKUP(E75,[1]ASIGNACION!AA70:AM124,13,0) -> #N/A | L75: =J75-H75 -> 0 | M75: =H75/F75 -> #DIV/0! | N75: =VLOOKUP(E75,'DOMINGO 1'!D:AB,7,0) -> #N/A | O75: =VLOOKUP(E75,'DOMINGO 2'!D:AB,7,0) -> #N/A | Q75: =VLOOKUP(E75,'FESTIVO 1'!D:AB,7,0) -> #N/A | R75: =VLOOKUP(E75,'DOMINGO 1'!D:AB,11,0) -> #N/A | S75: =VLOOKUP(E75,'DOMINGO 2'!D:AB,11,0) -> #N/A | T75: =VLOOKUP(E75,'DOMINGO 3'!D:AB,11,0) -> #N/A
B76: 0.12 | C76: =M76/B76 -> 0.66188259 | D76: =IF(C76>=0.95,"S",IF(C76>=0.9,"A",IF(C76>=0.8,"B",IF(C76>=0.7,"C",IF(C76>=0.6,"D","F"))))) -> D | E76: A0128(LEIDY TORRES) | F76: =VLOOKUP(E76,'ASIGNACION RANKING'!D:AB,7,0)-N76 -> 1608392 | G76: =VLOOKUP(E76,'ASIGNACION RANKING'!D:AB,6,0) -> 1002 | H76: =VLOOKUP(E76,'ASIGNACION RANKING'!D:AB,11,0)-R76 -> 127748 | I76: 0.15 | J76: =F76*I76 -> 241258.8 | K76: =VLOOKUP(E76,[1]ASIGNACION!AA71:AM125,13,0) -> #N/A | L76: =J76-H76 -> 113510.8 | M76: =H76/F76 -> 0.079425911 | N76: =VLOOKUP(E76,'DOMINGO 1'!D:AB,7,0) -> 125992 | O76: =VLOOKUP(E76,'DOMINGO 2'!D:AB,7,0) -> 136031 | Q76: =VLOOKUP(E76,'FESTIVO 1'!D:AB,7,0) -> 126710 | R76: =VLOOKUP(E76,'DOMINGO 1'!D:AB,11,0) -> 6647 | S76: =VLOOKUP(E76,'DOMINGO 2'!D:AB,11,0) -> 2252 | T76: =VLOOKUP(E76,'DOMINGO 3'!D:AB,11,0) -> #N/A
B77: 0.12 | C77: =M77/B77 -> 0.71610303 | D77: =IF(C77>=0.95,"S",IF(C77>=0.9,"A",IF(C77>=0.8,"B",IF(C77>=0.7,"C",IF(C77>=0.6,"D","F"))))) -> C | E77: A0447(LORENA SALGADO) | F77: =VLOOKUP(E77,'ASIGNACION RANKING'!D:AB,7,0)-N77 -> 1600212 | G77: =VLOOKUP(E77,'ASIGNACION RANKING'!D:AB,6,0) -> 938 | H77: =VLOOKUP(E77,'ASIGNACION RANKING'!D:AB,11,0)-R77 -> 137510 | I77: 0.15 | J77: =F77*I77 -> 240031.8 | K77: =VLOOKUP(E77,[1]ASIGNACION!AA67:AM126,13,0) -> #N/A | L77: =J77-H77 -> 102521.8 | M77: =H77/F77 -> 0.085932364 | N77: =VLOOKUP(E77,'DOMINGO 1'!D:AB,7,0) -> 137639 | O77: =VLOOKUP(E77,'DOMINGO 2'!D:AB,7,0) -> 121021 | Q77: =VLOOKUP(E77,'FESTIVO 1'!D:AB,7,0) -> 152081 | R77: =VLOOKUP(E77,'DOMINGO 1'!D:AB,11,0) -> 7708 | S77: =VLOOKUP(E77,'DOMINGO 2'!D:AB,11,0) -> 5405 | T77: =VLOOKUP(E77,'DOMINGO 3'!D:AB,11,0) -> #N/A
B78: 0.12 | C78: =M78/B78 -> 0.54717379 | D78: =IF(C78>=0.95,"S",IF(C78>=0.9,"A",IF(C78>=0.8,"B",IF(C78>=0.7,"C",IF(C78>=0.6,"D","F"))))) -> F | E78: A0388(MICHAEL BARRIOS) | F78: =VLOOKUP(E78,'ASIGNACION RANKING'!D:AB,7,0)-N78 -> 1892269 | G78: =VLOOKUP(E78,'ASIGNACION RANKING'!D:AB,6,0) -> 1011 | H78: =VLOOKUP(E78,'ASIGNACION RANKING'!D:AB,11,0)-R78 -> 124248 | I78: 0.15 | J78: =F78*I78 -> 283840.35 | K78: =VLOOKUP(E78,[1]ASIGNACION!AA68:AM127,13,0) -> #N/A | L78: =J78-H78 -> 159592.35 | M78: =H78/F78 -> 0.065660855 | N78: =VLOOKUP(E78,'DOMINGO 1'!D:AB,7,0) -> 155182 | O78: =VLOOKUP(E78,'DOMINGO 2'!D:AB,7,0) -> 153195 | Q78: =VLOOKUP(E78,'FESTIVO 1'!D:AB,7,0) -> 130435 | R78: =VLOOKUP(E78,'DOMINGO 1'!D:AB,11,0) -> 5161 | S78: =VLOOKUP(E78,'DOMINGO 2'!D:AB,11,0) -> 5798
B79: 0.12 | C79: =M79/B79 -> 0.72902477 | D79: =IF(C79>=0.95,"S",IF(C79>=0.9,"A",IF(C79>=0.8,"B",IF(C79>=0.7,"C",IF(C79>=0.6,"D","F"))))) -> C | E79: A0096(NATALYA PACHECO) | F79: =VLOOKUP(E79,'ASIGNACION RANKING'!D:AB,7,0)-N79 -> 1566602 | G79: =VLOOKUP(E79,'ASIGNACION RANKING'!D:AB,6,0) -> 922 | H79: =VLOOKUP(E79,'ASIGNACION RANKING'!D:AB,11,0)-R79 -> 137051 | I79: 0.15 | J79: =F79*I79 -> 234990.3 | K79: =VLOOKUP(E79,[1]ASIGNACION!AA69:AM128,13,0) -> #N/A | L79: =J79-H79 -> 97939.3 | M79: =H79/F79 -> 0.087482973 | N79: =VLOOKUP(E79,'DOMINGO 1'!D:AB,7,0) -> 130446 | O79: =VLOOKUP(E79,'DOMINGO 2'!D:AB,7,0) -> 105178 | Q79: =VLOOKUP(E79,'FESTIVO 1'!D:AB,7,0) -> 102259 | R79: =VLOOKUP(E79,'DOMINGO 1'!D:AB,11,0) -> 7024 | S79: =VLOOKUP(E79,'DOMINGO 2'!D:AB,11,0) -> 7590
B80: 0.12 | C80: =M80/B80 -> 0.65790023 | D80: =IF(C80>=0.95,"S",IF(C80>=0.9,"A",IF(C80>=0.8,"B",IF(C80>=0.7,"C",IF(C80>=0.6,"D","F"))))) -> D | E80: A0214(NEIDY FORERO ) | F80: =VLOOKUP(E80,'ASIGNACION RANKING'!D:AB,7,0)-N80 -> 1515972 | G80: =VLOOKUP(E80,'ASIGNACION RANKING'!D:AB,6,0) -> 936 | H80: =VLOOKUP(E80,'ASIGNACION RANKING'!D:AB,11,0)-R80 -> 119683 | I80: 0.15 | J80: =F80*I80 -> 227395.8 | K80: =VLOOKUP(E80,[1]ASIGNACION!AA70:AM129,13,0) -> #N/A | L80: =J80-H80 -> 107712.8 | M80: =H80/F80 -> 0.078948028 | N80: =VLOOKUP(E80,'DOMINGO 1'!D:AB,7,0) -> 126385 | O80: =VLOOKUP(E80,'DOMINGO 2'!D:AB,7,0) -> 128760 | Q80: =VLOOKUP(E80,'FESTIVO 1'!D:AB,7,0) -> #N/A | R80: =VLOOKUP(E80,'DOMINGO 1'!D:AB,11,0) -> 3147 | S80: =VLOOKUP(E80,'DOMINGO 2'!D:AB,11,0) -> 7512
B81: 0.12 | C81: =M81/B81 -> 0.85825501 | D81: =IF(C81>=0.95,"S",IF(C81>=0.9,"A",IF(C81>=0.8,"B",IF(C81>=0.7,"C",IF(C81>=0.6,"D","F"))))) -> B | E81: A0444(NICOL AMEZQUITA) | F81: =VLOOKUP(E81,'ASIGNACION RANKING'!D:AB,7,0)-N81 -> 1391292 | G81: =VLOOKUP(E81,'ASIGNACION RANKING'!D:AB,6,0) -> 844 | H81: =VLOOKUP(E81,'ASIGNACION RANKING'!D:AB,11,0)-R81 -> 143290 | I81: 0.15 | J81: =F81*I81 -> 208693.8 | K81: =VLOOKUP(E81,[1]ASIGNACION!AA73:AM127,13,0) -> #N/A | L81: =J81-H81 -> 65403.8 | M81: =H81/F81 -> 0.1029906 | N81: =VLOOKUP(E81,'DOMINGO 1'!D:AB,7,0) -> 124629 | O81: =VLOOKUP(E81,'DOMINGO 2'!D:AB,7,0) -> 106613 | Q81: =VLOOKUP(E81,'FESTIVO 1'!D:AB,7,0) -> 164651 | R81: =VLOOKUP(E81,'DOMINGO 1'!D:AB,11,0) -> 9235 | S81: =VLOOKUP(E81,'DOMINGO 2'!D:AB,11,0) -> 2655 | T81: =VLOOKUP(E81,'DOMINGO 3'!D:AB,11,0) -> #N/A
B82: 0.12 | C82: =M82/B82 -> 0.70131111 | D82: =IF(C82>=0.95,"S",IF(C82>=0.9,"A",IF(C82>=0.8,"B",IF(C82>=0.7,"C",IF(C82>=0.6,"D","F"))))) -> C | E82: A0232(PAU ALDANA) | F82: =VLOOKUP(E82,'ASIGNACION RANKING'!D:AB,7,0)-N82 -> 1435680 | G82: =VLOOKUP(E82,'ASIGNACION RANKING'!D:AB,6,0) -> 956 | H82: =VLOOKUP(E82,'ASIGNACION RANKING'!D:AB,11,0)-R82 -> 120823 | I82: 0.15 | J82: =F82*I82 -> 215352 | K82: =VLOOKUP(E82,[1]ASIGNACION!AA74:AM128,13,0) -> #N/A | L82: =J82-H82 -> 94529 | M82: =H82/F82 -> 0.084157333 | N82: =VLOOKUP(E82,'DOMINGO 1'!D:AB,7,0) -> 119412 | O82: =VLOOKUP(E82,'DOMINGO 2'!D:AB,7,0) -> 116136 | Q82: =VLOOKUP(E82,'FESTIVO 1'!D:AB,7,0) -> 125854 | R82: =VLOOKUP(E82,'DOMINGO 1'!D:AB,11,0) -> 3083 | S82: =VLOOKUP(E82,'DOMINGO 2'!D:AB,11,0) -> 8970 | T82: =VLOOKUP(E82,'DOMINGO 3'!D:AB,11,0) -> #N/A
B83: 0.12 | C83: =M83/B83 -> 0.61791017 | D83: =IF(C83>=0.95,"S",IF(C83>=0.9,"A",IF(C83>=0.8,"B",IF(C83>=0.7,"C",IF(C83>=0.6,"D","F"))))) -> D | E83: PAULAG08(PAULA GUTIERREZ) | F83: =VLOOKUP(E83,'ASIGNACION RANKING'!D:AB,7,0)-N83 -> 1656511 | G83: =VLOOKUP(E83,'ASIGNACION RANKING'!D:AB,6,0) -> 926 | H83: =VLOOKUP(E83,'ASIGNACION RANKING'!D:AB,11,0)-R83 -> 122829 | I83: 0.15 | J83: =F83*I83 -> 248476.65 | K83: =VLOOKUP(E83,[1]ASIGNACION!AA75:AM129,13,0) -> #N/A | L83: =J83-H83 -> 125647.65 | M83: =H83/F83 -> 0.074149221 | N83: =VLOOKUP(E83,'DOMINGO 1'!D:AB,7,0) -> 133250 | O83: =VLOOKUP(E83,'DOMINGO 2'!D:AB,7,0) -> 141398 | Q83: =VLOOKUP(E83,'FESTIVO 1'!D:AB,7,0) -> 116632 | R83: =VLOOKUP(E83,'DOMINGO 1'!D:AB,11,0) -> 3159 | S83: =VLOOKUP(E83,'DOMINGO 2'!D:AB,11,0) -> 6760 | T83: =VLOOKUP(E83,'DOMINGO 3'!D:AB,11,0) -> #N/A
B84: 0.12 | C84: =M84/B84 -> 0.71410708 | D84: =IF(C84>=0.95,"S",IF(C84>=0.9,"A",IF(C84>=0.8,"B",IF(C84>=0.7,"C",IF(C84>=0.6,"D","F"))))) -> C | E84: A0222(PIPE GONZALEZ) | F84: =VLOOKUP(E84,'ASIGNACION RANKING'!D:AB,7,0)-N84 -> 1627452 | G84: =VLOOKUP(E84,'ASIGNACION RANKING'!D:AB,6,0) -> 965 | H84: =VLOOKUP(E84,'ASIGNACION RANKING'!D:AB,11,0)-R84 -> 139461 | I84: 0.15 | J84: =F84*I84 -> 244117.8 | K84: =VLOOKUP(E84,[1]ASIGNACION!AA74:AM128,13,0) -> #N/A | L84: =J84-H84 -> 104656.8 | M84: =H84/F84 -> 0.08569285 | N84: =VLOOKUP(E84,'DOMINGO 1'!D:AB,7,0) -> 143787 | O84: =VLOOKUP(E84,'DOMINGO 2'!D:AB,7,0) -> 128633 | Q84: =VLOOKUP(E84,'FESTIVO 1'!D:AB,7,0) -> 143794 | R84: =VLOOKUP(E84,'DOMINGO 1'!D:AB,11,0) -> 7726 | S84: =VLOOKUP(E84,'DOMINGO 2'!D:AB,11,0) -> 2250 | T84: =VLOOKUP(E84,'DOMINGO 3'!D:AB,11,0) -> #N/A
B85: 0.12 | C85: =M85/B85 -> 1.0438112 | D85: =IF(C85>=0.95,"S",IF(C85>=0.9,"A",IF(C85>=0.8,"B",IF(C85>=0.7,"C",IF(C85>=0.6,"D","F"))))) -> S | E85: A0119(WILL) | F85: =VLOOKUP(E85,'ASIGNACION RANKING'!D:AB,7,0)-N85 -> 1229357 | G85: =VLOOKUP(E85,'ASIGNACION RANKING'!D:AB,6,0) -> 903 | H85: =VLOOKUP(E85,'ASIGNACION RANKING'!D:AB,11,0)-R85 -> 153986 | I85: 0.15 | J85: =F85*I85 -> 184403.55 | L85: =J85-H85 -> 30417.55 | M85: =H85/F85 -> 0.12525735 | N85: =VLOOKUP(E85,'DOMINGO 1'!D:AB,7,0) -> 104658 | O85: =VLOOKUP(E85,'DOMINGO 2'!D:AB,7,0) -> 82610 | Q85: =VLOOKUP(E85,'FESTIVO 1'!D:AB,7,0) -> 114771 | R85: =VLOOKUP(E85,'DOMINGO 1'!D:AB,11,0) -> 1847 | S85: =VLOOKUP(E85,'DOMINGO 2'!D:AB,11,0) -> 6305 | T85: =VLOOKUP(E85,'DOMINGO 3'!D:AB,11,0) -> #N/A
B86: 0.12 | C86: =M86/B86 -> 0.60342217 | D86: =IF(C86>=0.95,"S",IF(C86>=0.9,"A",IF(C86>=0.8,"B",IF(C86>=0.7,"C",IF(C86>=0.6,"D","F"))))) -> D | E86: A0438(YULI CASTRO) | F86: =VLOOKUP(E86,'ASIGNACION RANKING'!D:AB,7,0)-N86 -> 1739440 | G86: =VLOOKUP(E86,'ASIGNACION RANKING'!D:AB,6,0) -> 997 | H86: =VLOOKUP(E86,'ASIGNACION RANKING'!D:AB,11,0)-R86 -> 125954 | I86: 0.15 | J86: =F86*I86 -> 260916 | L86: =J86-H86 -> 134962 | M86: =H86/F86 -> 0.072410661 | N86: =VLOOKUP(E86,'DOMINGO 1'!D:AB,7,0) -> 148717 | O86: =VLOOKUP(E86,'DOMINGO 2'!D:AB,7,0) -> 132382 | Q86: =VLOOKUP(E86,'FESTIVO 1'!D:AB,7,0) -> 172217 | R86: =VLOOKUP(E86,'DOMINGO 1'!D:AB,11,0) -> 6216 | S86: =VLOOKUP(E86,'DOMINGO 2'!D:AB,11,0) -> 2586 | T86: =VLOOKUP(E86,'DOMINGO 3'!D:AB,11,0) -> #N/A
E88: Fecha | F88: =NOW() -> 46324.461 | G88: Grupo | H88: S2 OKDINERO | J88: TLJ | L88: GINA | M88: % DEVOLUCIÓN | N88: %FALTA META | O88: POR ASESOR
E89: PRODUCTIVIDAD | G89: ASIGNACIÓN | H89: =SUM(F91:F103) -> #N/A | J89: RECUADO | L89: =SUM(H91:H103) -> #N/A | M89: =L89/H89 -> #N/A | N89: =(H89*1.2%)-L89 -> #N/A | O89: =N89/13 -> #N/A
B90: META | C90: CUMPLIMIENTO | D90: PERCENTIL | E90: Asesor | F90: Asignacion | G90: Cuentas | H90: Recaudo | I90: %_Meta | J90: $_Meta | K90: # GESTIONES | L90: Falta | M90: %_Aporte | N90: DOMINGO 1 | O90: DOMINGO 2 | P90: DOMINGO 3 | Q90: FESTIVO 1 | R90: FESTIVO 2
B91: 0.012 | C91: =M91/B91 -> #N/A | D91: =IF(C91>=0.95,"S",IF(C91>=0.9,"A",IF(C91>=0.8,"B",IF(C91>=0.7,"C",IF(C91>=0.6,"D","F"))))) -> #N/A | E91: A0446(ANGIE HUERTAS) | F91: =VLOOKUP(E91,'ASIGNACION RANKING'!D:AB,7,0)-N91-O91 -> #N/A | G91: =VLOOKUP(E91,'ASIGNACION RANKING'!D:AB,6,0) -> #N/A | H91: =VLOOKUP(E91,'ASIGNACION RANKING'!D:AB,11,0) -> #N/A | I91: 0.018 | J91: =F91*I91 -> #N/A | K91: =VLOOKUP(E91,[1]ASIGNACION!AA67:AM141,13,0) -> #N/A | L91: =J91-H91 -> #N/A | M91: =H91/F91 -> #N/A | N91: =VLOOKUP(E91,'DOMINGO 1'!D:AB,7,0) -> #N/A | O91: =VLOOKUP(E91,'DOMINGO 2'!D:AB,7,0) -> #N/A | P91: =VLOOKUP(E91,'DOMINGO 3'!D:AB,7,0) -> #N/A | Q91: 0
B92: 0.012 | C92: =M92/B92 -> #N/A | D92: =IF(C92>=0.95,"S",IF(C92>=0.9,"A",IF(C92>=0.8,"B",IF(C92>=0.7,"C",IF(C92>=0.6,"D","F"))))) -> #N/A | E92: A0324(DANI P) | F92: =VLOOKUP(E92,'ASIGNACION RANKING'!D:AB,7,0)-N92-O92 -> #N/A | G92: =VLOOKUP(E92,'ASIGNACION RANKING'!D:AB,6,0) -> #N/A | H92: =VLOOKUP(E92,'ASIGNACION RANKING'!D:AB,11,0) -> #N/A | I92: 0.018 | J92: =F92*I92 -> #N/A | K92: =VLOOKUP(E92,[1]ASIGNACION!AA68:AM142,13,0) -> #N/A | L92: =J92-H92 -> #N/A | M92: =H92/F92 -> #N/A | N92: =VLOOKUP(E92,'DOMINGO 1'!D:AB,7,0) -> #N/A | O92: =VLOOKUP(E92,'DOMINGO 2'!D:AB,7,0) -> #N/A | P92: 0 | Q92: =VLOOKUP(E92,'FESTIVO 1'!D:AB,7,0) -> #N/A
B93: 0.012 | C93: =M93/B93 -> #N/A | D93: =IF(C93>=0.95,"S",IF(C93>=0.9,"A",IF(C93>=0.8,"B",IF(C93>=0.7,"C",IF(C93>=0.6,"D","F"))))) -> #N/A | E93: A0433(ESTEBAN RODRIGUEZ) | F93: =VLOOKUP(E93,'ASIGNACION RANKING'!D:AB,7,0)-N93-O93 -> #N/A | G93: =VLOOKUP(E93,'ASIGNACION RANKING'!D:AB,6,0) -> #N/A | H93: =VLOOKUP(E93,'ASIGNACION RANKING'!D:AB,11,0) -> #N/A | I93: 0.018 | J93: =F93*I93 -> #N/A | K93: =VLOOKUP(E93,[1]ASIGNACION!AA69:AM143,13,0) -> #N/A | L93: =J93-H93 -> #N/A | M93: =H93/F93 -> #N/A | N93: =VLOOKUP(E93,'DOMINGO 1'!D:AB,7,0) -> #N/A | O93: =VLOOKUP(E93,'DOMINGO 2'!D:AB,7,0) -> #N/A | P93: =VLOOKUP(E93,'DOMINGO 3'!D:AB,7,0) -> #N/A | Q93: 0
B94: 0.012 | C94: =M94/B94 -> #N/A | D94: =IF(C94>=0.95,"S",IF(C94>=0.9,"A",IF(C94>=0.8,"B",IF(C94>=0.7,"C",IF(C94>=0.6,"D","F"))))) -> #N/A | E94: A0448(JHON VARGAS) | F94: =VLOOKUP(E94,'ASIGNACION RANKING'!D:AB,7,0)-N94-O94 -> #N/A | G94: =VLOOKUP(E94,'ASIGNACION RANKING'!D:AB,6,0) -> #N/A | H94: =VLOOKUP(E94,'ASIGNACION RANKING'!D:AB,11,0) -> #N/A | I94: 0.018 | J94: =F94*I94 -> #N/A | K94: =VLOOKUP(E94,[1]ASIGNACION!AA70:AM144,13,0) -> #N/A | L94: =J94-H94 -> #N/A | M94: =H94/F94 -> #N/A | N94: =VLOOKUP(E94,'DOMINGO 1'!D:AB,7,0) -> #N/A | O94: =VLOOKUP(E94,'DOMINGO 2'!D:AB,7,0) -> #N/A | P94: =VLOOKUP(E94,'DOMINGO 3'!D:AB,7,0) -> #N/A | Q94: =VLOOKUP(E94,'FESTIVO 1'!D:AB,7,0) -> #N/A
B95: 0.012 | C95: =M95/B95 -> #N/A | D95: =IF(C95>=0.95,"S",IF(C95>=0.9,"A",IF(C95>=0.8,"B",IF(C95>=0.7,"C",IF(C95>=0.6,"D","F"))))) -> #N/A | E95: A0352(K MURILLO) | F95: =VLOOKUP(E95,'ASIGNACION RANKING'!D:AB,7,0)-N95-O95 -> #N/A | G95: =VLOOKUP(E95,'ASIGNACION RANKING'!D:AB,6,0) -> #N/A | H95: =VLOOKUP(E95,'ASIGNACION RANKING'!D:AB,11,0) -> #N/A | I95: 0.018 | J95: =F95*I95 -> #N/A | K95: =VLOOKUP(E95,[1]ASIGNACION!AA71:AM145,13,0) -> #N/A | L95: =J95-H95 -> #N/A | M95: =H95/F95 -> #N/A | N95: =VLOOKUP(E95,'DOMINGO 1'!D:AB,7,0) -> #N/A | O95: =VLOOKUP(E95,'DOMINGO 2'!D:AB,7,0) -> #N/A | P95: =VLOOKUP(E95,'DOMINGO 3'!D:AB,7,0) -> #N/A | Q95: =VLOOKUP(E95,'FESTIVO 1'!D:AB,7,0) -> #N/A
B96: 0.012 | C96: =M96/B96 -> #N/A | D96: =IF(C96>=0.95,"S",IF(C96>=0.9,"A",IF(C96>=0.8,"B",IF(C96>=0.7,"C",IF(C96>=0.6,"D","F"))))) -> #N/A | E96: A0332(L AVILA) | F96: =VLOOKUP(E96,'ASIGNACION RANKING'!D:AB,7,0)-N96-O96 -> #N/A | G96: =VLOOKUP(E96,'ASIGNACION RANKING'!D:AB,6,0) -> #N/A | H96: =VLOOKUP(E96,'ASIGNACION RANKING'!D:AB,11,0) -> #N/A | I96: 0.018 | J96: =F96*I96 -> #N/A | K96: =VLOOKUP(E96,[1]ASIGNACION!AA72:AM146,13,0) -> #N/A | L96: =J96-H96 -> #N/A | M96: =H96/F96 -> #N/A | N96: =VLOOKUP(E96,'DOMINGO 1'!D:AB,7,0) -> #N/A | O96: =VLOOKUP(E96,'DOMINGO 2'!D:AB,7,0) -> #N/A | P96: =VLOOKUP(E96,'DOMINGO 3'!D:AB,7,0) -> #N/A | Q96: =VLOOKUP(E96,'FESTIVO 1'!D:AB,7,0) -> #N/A
B97: 0.012 | C97: =M97/B97 -> 8.1811612 | D97: =IF(C97>=0.95,"S",IF(C97>=0.9,"A",IF(C97>=0.8,"B",IF(C97>=0.7,"C",IF(C97>=0.6,"D","F"))))) -> S | E97: A0447(LORENA SALGADO) | F97: =VLOOKUP(E97,'ASIGNACION RANKING'!D:AB,7,0)-N97-O97 -> 1479191 | G97: =VLOOKUP(E97,'ASIGNACION RANKING'!D:AB,6,0) -> 938 | H97: =VLOOKUP(E97,'ASIGNACION RANKING'!D:AB,11,0) -> 145218 | I97: 0.018 | J97: =F97*I97 -> 26625.438 | K97: =VLOOKUP(E97,[1]ASIGNACION!AA73:AM147,13,0) -> #N/A | L97: =J97-H97 -> -118592.56 | M97: =H97/F97 -> 0.098173934 | N97: =VLOOKUP(E97,'DOMINGO 1'!D:AB,7,0) -> 137639 | O97: =VLOOKUP(E97,'DOMINGO 2'!D:AB,7,0) -> 121021 | P97: =VLOOKUP(E97,'DOMINGO 3'!D:AB,7,0) -> #N/A | Q97: =VLOOKUP(E97,'FESTIVO 1'!D:AB,7,0) -> 152081 | S97: S2 = 200mil = +1.7% - 100mil% + 1.2 50mil +1% S1 = 200mil +15% 100 +13% 50+ 11%
B98: 0.012 | C98: =M98/B98 -> #N/A | D98: =IF(C98>=0.95,"S",IF(C98>=0.9,"A",IF(C98>=0.8,"B",IF(C98>=0.7,"C",IF(C98>=0.6,"D","F"))))) -> #N/A | E98: A0140(M RAMIREZ) | F98: =VLOOKUP(E98,'ASIGNACION RANKING'!D:AB,7,0)-N98-O98 -> #N/A | G98: =VLOOKUP(E98,'ASIGNACION RANKING'!D:AB,6,0) -> #N/A | H98: =VLOOKUP(E98,'ASIGNACION RANKING'!D:AB,11,0) -> #N/A | I98: 0.018 | J98: =F98*I98 -> #N/A | K98: =VLOOKUP(E98,[1]ASIGNACION!AA74:AM148,13,0) -> #N/A | L98: =J98-H98 -> #N/A | M98: =H98/F98 -> #N/A | N98: =VLOOKUP(E98,'DOMINGO 1'!D:AB,7,0) -> #N/A | O98: =VLOOKUP(E98,'DOMINGO 2'!D:AB,7,0) -> #N/A
B99: 0.012 | C99: =M99/B99 -> #N/A | D99: =IF(C99>=0.95,"S",IF(C99>=0.9,"A",IF(C99>=0.8,"B",IF(C99>=0.7,"C",IF(C99>=0.6,"D","F"))))) -> #N/A | E99: A0427(MATEO DOMINGUEZ) | F99: =VLOOKUP(E99,'ASIGNACION RANKING'!D:AB,7,0)-N99-O99 -> #N/A | G99: =VLOOKUP(E99,'ASIGNACION RANKING'!D:AB,6,0) -> #N/A | H99: =VLOOKUP(E99,'ASIGNACION RANKING'!D:AB,11,0) -> #N/A | I99: 0.018 | J99: =F99*I99 -> #N/A | K99: =VLOOKUP(E99,[1]ASIGNACION!AA75:AM149,13,0) -> #N/A | L99: =J99-H99 -> #N/A | M99: =H99/F99 -> #N/A | N99: =VLOOKUP(E99,'DOMINGO 1'!D:AB,7,0) -> #N/A | O99: =VLOOKUP(E99,'DOMINGO 2'!D:AB,7,0) -> #N/A
B100: 0.012 | C100: =M100/B100 -> #N/A | D100: =IF(C100>=0.95,"S",IF(C100>=0.9,"A",IF(C100>=0.8,"B",IF(C100>=0.7,"C",IF(C100>=0.6,"D","F"))))) -> #N/A | E100: A0205(MATEUS) | F100: =VLOOKUP(E100,'ASIGNACION RANKING'!D:AB,7,0)-N100-O100 -> #N/A | G100: =VLOOKUP(E100,'ASIGNACION RANKING'!D:AB,6,0) -> #N/A | H100: =VLOOKUP(E100,'ASIGNACION RANKING'!D:AB,11,0) -> #N/A | I100: 0.018 | J100: =F100*I100 -> #N/A | K100: =VLOOKUP(E100,[1]ASIGNACION!AA74:AM148,13,0) -> #N/A | L100: =J100-H100 -> #N/A | M100: =H100/F100 -> #N/A | N100: =VLOOKUP(E100,'DOMINGO 1'!D:AB,7,0) -> #N/A | O100: =VLOOKUP(E100,'DOMINGO 2'!D:AB,7,0) -> #N/A | P100: =VLOOKUP(E100,'DOMINGO 3'!D:AB,7,0) -> #N/A | Q100: 0
B101: 0.012 | C101: =M101/B101 -> #N/A | D101: =IF(C101>=0.95,"S",IF(C101>=0.9,"A",IF(C101>=0.8,"B",IF(C101>=0.7,"C",IF(C101>=0.6,"D","F"))))) -> #N/A | E101: A0172(MICHEL R) | F101: =VLOOKUP(E101,'ASIGNACION RANKING'!D:AB,7,0)-N101-O101 -> #N/A | G101: =VLOOKUP(E101,'ASIGNACION RANKING'!D:AB,6,0) -> #N/A | H101: =VLOOKUP(E101,'ASIGNACION RANKING'!D:AB,11,0) -> #N/A | I101: 0.018 | J101: =F101*I101 -> #N/A | K101: =VLOOKUP(E101,[1]ASIGNACION!AA75:AM149,13,0) -> #N/A | L101: =J101-H101 -> #N/A | M101: =H101/F101 -> #N/A | N101: =VLOOKUP(E101,'DOMINGO 1'!D:AB,7,0) -> #N/A | O101: =VLOOKUP(E101,'DOMINGO 2'!D:AB,7,0) -> #N/A | P101: =VLOOKUP(E101,'DOMINGO 3'!D:AB,7,0) -> #N/A | Q101: =VLOOKUP(E101,'FESTIVO 1'!D:AB,7,0) -> #N/A
B102: 0.012 | C102: =M102/B102 -> #N/A | D102: =IF(C102>=0.95,"S",IF(C102>=0.9,"A",IF(C102>=0.8,"B",IF(C102>=0.7,"C",IF(C102>=0.6,"D","F"))))) -> #N/A | E102: A0348(SANTI CAR) | F102: =VLOOKUP(E102,'ASIGNACION RANKING'!D:AB,7,0)-N102-O102 -> #N/A | G102: =VLOOKUP(E102,'ASIGNACION RANKING'!D:AB,6,0) -> #N/A | H102: =VLOOKUP(E102,'ASIGNACION RANKING'!D:AB,11,0) -> #N/A | I102: 0.018 | J102: =F102*I102 -> #N/A | K102: =VLOOKUP(E102,[1]ASIGNACION!AA73:AM147,13,0) -> #N/A | L102: =J102-H102 -> #N/A | M102: =H102/F102 -> #N/A | N102: =VLOOKUP(E102,'DOMINGO 1'!D:AB,7,0) -> #N/A | O102: =VLOOKUP(E102,'DOMINGO 2'!D:AB,7,0) -> #N/A | P102: =VLOOKUP(E102,'DOMINGO 3'!D:AB,7,0) -> #N/A | Q102: =VLOOKUP(E102,'FESTIVO 1'!D:AB,7,0) -> #N/A
B103: 0.012 | C103: =M103/B103 -> #N/A | D103: =IF(C103>=0.95,"S",IF(C103>=0.9,"A",IF(C103>=0.8,"B",IF(C103>=0.7,"C",IF(C103>=0.6,"D","F"))))) -> #N/A | E103: A0084(SEBASTIAN CUESTA) | F103: =VLOOKUP(E103,'ASIGNACION RANKING'!D:AB,7,0)-N103-O103 -> #N/A | G103: =VLOOKUP(E103,'ASIGNACION RANKING'!D:AB,6,0) -> #N/A | H103: =VLOOKUP(E103,'ASIGNACION RANKING'!D:AB,11,0) -> #N/A | I103: 0.018 | J103: =F103*I103 -> #N/A | L103: =J103-H103 -> #N/A | M103: =H103/F103 -> #N/A | N103: =VLOOKUP(E103,'DOMINGO 1'!D:AB,7,0) -> #N/A | O103: =VLOOKUP(E103,'DOMINGO 2'!D:AB,7,0) -> #N/A | P103: =VLOOKUP(E103,'DOMINGO 3'!D:AB,7,0) -> #N/A | Q103: =VLOOKUP(E103,'FESTIVO 1'!D:AB,7,0) -> #N/A
E105: Fecha | F105: =NOW() -> 46324.461 | G105: Grupo | H105: M2 OKDINERO | J105: TLJ | L105: GINA | M105: % DEVOLUCIÓN | N105: %FALTA META | O105: POR ASESOR
E106: PRODUCTIVIDAD | G106: ASIGNACIÓN | H106: =SUM(F108:F115) -> #N/A | J106: RECUADO | L106: =SUM(H108:H115) -> #N/A | M106: =L106/H106 -> #N/A | N106: =(H106*0.15%)-L106 -> #N/A | O106: =N106/8 -> #N/A
B107: META | C107: CUMPLIMIENTO | D107: PERCENTIL | E107: Asesor | F107: Asignacion | G107: Cuentas | H107: Recaudo | I107: %_Meta | J107: $_Meta | K107: # GESTIONES | L107: Falta | M107: %_Aporte | N107: DOMINGO 1 | O107: DOMINGO 2 | P107: DOMINGO 3 | Q107: FESTIVO 1 | R107: FESTIVO 2
B108: 0.0015 | C108: =M108/B108 -> #N/A | D108: =IF(C108>=0.95,"S",IF(C108>=0.9,"A",IF(C108>=0.8,"B",IF(C108>=0.7,"C",IF(C108>=0.6,"D","F"))))) -> #N/A | E108: BRANDON R1(BRANDON ROD) | F108: =VLOOKUP(E108,'ASIGNACION RANKING'!D:AB,7,0)-N108-O108 -> #N/A | G108: =VLOOKUP(E108,'ASIGNACION RANKING'!D:AB,6,0) -> #N/A | H108: =VLOOKUP(E108,'ASIGNACION RANKING'!D:AB,11,0) -> #N/A | I108: 0.002 | J108: =F108*I108 -> #N/A | K108: =VLOOKUP(E108,[1]ASIGNACION!AA67:AM151,13,0) -> #N/A | L108: =J108-H108 -> #N/A | M108: =H108/F108 -> #N/A | N108: =VLOOKUP(E108,'DOMINGO 1'!D:AB,7,0) -> #N/A | O108: =VLOOKUP(E108,'DOMINGO 2'!D:AB,7,0) -> #N/A | P108: =VLOOKUP(E108,'DOMINGO 3'!D:AB,7,0) -> #N/A | Q108: =VLOOKUP(E108,'FESTIVO 1'!D:AB,7,0) -> #N/A
B109: 0.0015 | C109: =M109/B109 -> #N/A | D109: =IF(C109>=0.95,"S",IF(C109>=0.9,"A",IF(C109>=0.8,"B",IF(C109>=0.7,"C",IF(C109>=0.6,"D","F"))))) -> #N/A | E109: A0327(DIEGO MELO) | F109: =VLOOKUP(E109,'ASIGNACION RANKING'!D:AB,7,0)-N109-O109 -> #N/A | G109: =VLOOKUP(E109,'ASIGNACION RANKING'!D:AB,6,0) -> #N/A | H109: =VLOOKUP(E109,'ASIGNACION RANKING'!D:AB,11,0) -> #N/A | I109: 0.002 | J109: =F109*I109 -> #N/A | K109: =VLOOKUP(E109,[1]ASIGNACION!AA68:AM152,13,0) -> #N/A | L109: =J109-H109 -> #N/A | M109: =H109/F109 -> #N/A | N109: =VLOOKUP(E109,'DOMINGO 1'!D:AB,7,0) -> #N/A | O109: =VLOOKUP(E109,'DOMINGO 2'!D:AB,7,0) -> #N/A | P109: =VLOOKUP(E109,'DOMINGO 3'!D:AB,7,0) -> #N/A | Q109: =VLOOKUP(E109,'FESTIVO 1'!D:AB,7,0) -> #N/A
B110: 0.0015 | C110: =M110/B110 -> #N/A | D110: =IF(C110>=0.95,"S",IF(C110>=0.9,"A",IF(C110>=0.8,"B",IF(C110>=0.7,"C",IF(C110>=0.6,"D","F"))))) -> #N/A | E110: A0013(ESTIVEN CUESTA) | F110: =VLOOKUP(E110,'ASIGNACION RANKING'!D:AB,7,0)-N110-O110 -> #N/A | G110: =VLOOKUP(E110,'ASIGNACION RANKING'!D:AB,6,0) -> #N/A | H110: =VLOOKUP(E110,'ASIGNACION RANKING'!D:AB,11,0) -> #N/A | I110: 0.002 | J110: =F110*I110 -> #N/A | K110: =VLOOKUP(E110,[1]ASIGNACION!AA69:AM152,13,0) -> #N/A | L110: =J110-H110 -> #N/A | M110: =H110/F110 -> #N/A | N110: =VLOOKUP(E110,'DOMINGO 1'!D:AB,7,0) -> #N/A | O110: =VLOOKUP(E110,'DOMINGO 2'!D:AB,7,0) -> #N/A | P110: =VLOOKUP(E110,'DOMINGO 3'!D:AB,7,0) -> #N/A | Q110: =VLOOKUP(E110,'FESTIVO 1'!D:AB,7,0) -> #N/A
...

Sheet COMISIONES
A1: SEGMENTO | B1: APLICACIÓN | C1: NOMBRE SISTEMA | D1: EJECUTIVO | E1: CC | F1: TLJ | G1: TL | H1: CUENTAS ASIGNADAS | I1: MONTO DE PEDIDOS EN BASE | J1: MONTO RECUPERADO | K1: DOMINGO 1 | L1: DOMINGO 2 | M1: PAGOS DOMINGO1 | N1: PAGOS DOMINGO2 | O1: ALL MONTO PEDIDOS EN BASE | P1: ALL MONTO RECUPERADO | Q1: % DE RETORNO | R1: BONO | S1: BONOS DIARIOS | T1: DESCUENTOS | U1: TOTAL BONUS
A2: S2 | B2: CASHMAX | C2: A0120(CRISTIAN RODRIGUEZ ) | F2: MATEO CANO | G2: JOSE SANCHEZ | H2: =VLOOKUP(C2,'ASIGNACION RANKING'!D:AB,6,0) -> #N/A | I2: =VLOOKUP(C2,'ASIGNACION RANKING'!D:AB,7,0) -> #N/A | J2: =VLOOKUP(C2,'ASIGNACION RANKING'!D:AB,11,0) -> #N/A | K2: =VLOOKUP(C2,'DOMINGO 1'!D:AB,7,0) -> #N/A | L2: =VLOOKUP(C2,'DOMINGO 2'!D:AB,7,0) -> #N/A | M2: =VLOOKUP(C2,'DOMINGO 1'!D:AB,11,0) -> #N/A | N2: =VLOOKUP(C2,'DOMINGO 2'!D:AB,11,0) -> #N/A | O2: =I2-K2-L2 -> #N/A | P2: =J2-M2-N2 -> #N/A | Q2: =P2/O2 -> #N/A | R2: =VLOOKUP(C2,RANKING!E:O,9,0) -> #N/A
A3: S2 | B3: CASHMAX | C3: A0068(JENNY MENDIETA) | F3: MATEO CANO | G3: JOSE SANCHEZ | H3: =VLOOKUP(C3,'ASIGNACION RANKING'!D:AB,6,0) -> #N/A | I3: =VLOOKUP(C3,'ASIGNACION RANKING'!D:AB,7,0) -> #N/A | J3: =VLOOKUP(C3,'ASIGNACION RANKING'!D:AB,11,0) -> #N/A | K3: =VLOOKUP(C3,'DOMINGO 1'!D:AB,7,0) -> #N/A | L3: =VLOOKUP(C3,'DOMINGO 2'!D:AB,7,0) -> #N/A | M3: =VLOOKUP(C3,'DOMINGO 1'!D:AB,11,0) -> #N/A | N3: =VLOOKUP(C3,'DOMINGO 2'!D:AB,11,0) -> #N/A | O3: =I3-K3-L3 -> #N/A | P3: =J3-M3-N3 -> #N/A | Q3: =P3/O3 -> #N/A | R3: =VLOOKUP(C3,RANKING!E:O,9,0) -> #N/A
A4: S2 | B4: CASHMAX | C4: A03290(JOHAN OJEDA) | F4: MATEO CANO | G4: JOSE SANCHEZ | H4: =VLOOKUP(C4,'ASIGNACION RANKING'!D:AB,6,0) -> #N/A | I4: =VLOOKUP(C4,'ASIGNACION RANKING'!D:AB,7,0) -> #N/A | J4: =VLOOKUP(C4,'ASIGNACION RANKING'!D:AB,11,0) -> #N/A | K4: =VLOOKUP(C4,'DOMINGO 1'!D:AB,7,0) -> #N/A | L4: =VLOOKUP(C4,'DOMINGO 2'!D:AB,7,0) -> #N/A | M4: =VLOOKUP(C4,'DOMINGO 1'!D:AB,11,0) -> #N/A | N4: =VLOOKUP(C4,'DOMINGO 2'!D:AB,11,0) -> #N/A | O4: =I4-K4-L4 -> #N/A | P4: =J4-M4-N4 -> #N/A | Q4: =P4/O4 -> #N/A | R4: =VLOOKUP(C4,RANKING!E:O,9,0) -> #N/A
A5: S2 | B5: CASHMAX | C5: A0364(JOSE VERA) | F5: MATEO CANO | G5: JOSE SANCHEZ | H5: =VLOOKUP(C5,'ASIGNACION RANKING'!D:AB,6,0) -> #N/A | I5: =VLOOKUP(C5,'ASIGNACION RANKING'!D:AB,7,0) -> #N/A | J5: =VLOOKUP(C5,'ASIGNACION RANKING'!D:AB,11,0) -> #N/A | K5: =VLOOKUP(C5,'DOMINGO 1'!D:AB,7,0) -> #N/A | L5: =VLOOKUP(C5,'DOMINGO 2'!D:AB,7,0) -> #N/A | M5: =VLOOKUP(C5,'DOMINGO 1'!D:AB,11,0) -> #N/A | N5: =VLOOKUP(C5,'DOMINGO 2'!D:AB,11,0) -> #N/A | O5: =I5-K5-L5 -> #N/A | P5: =J5-M5-N5 -> #N/A | Q5: =P5/O5 -> #N/A | R5: =VLOOKUP(C5,RANKING!E:O,9,0) -> #N/A
A6: S2 | B6: CASHMAX | C6: A0340(KAFFYR PUERTAS) | F6: MATEO CANO | G6: JOSE SANCHEZ | H6: =VLOOKUP(C6,'ASIGNACION RANKING'!D:AB,6,0) -> #N/A | I6: =VLOOKUP(C6,'ASIGNACION RANKING'!D:AB,7,0) -> #N/A | J6: =VLOOKUP(C6,'ASIGNACION RANKING'!D:AB,11,0) -> #N/A | K6: =VLOOKUP(C6,'DOMINGO 1'!D:AB,7,0) -> #N/A | L6: =VLOOKUP(C6,'DOMINGO 2'!D:AB,7,0) -> #N/A | M6: =VLOOKUP(C6,'DOMINGO 1'!D:AB,11,0) -> #N/A | N6: =VLOOKUP(C6,'DOMINGO 2'!D:AB,11,0) -> #N/A | O6: =I6-K6-L6 -> #N/A | P6: =J6-M6-N6 -> #N/A | Q6: =P6/O6 -> #N/A | R6: =VLOOKUP(C6,RANKING!E:O,9,0) -> #N/A
A7: S2 | B7: CASHMAX | C7: A0053(LAURA RUBIANO) | F7: MATEO CANO | G7: JOSE SANCHEZ | H7: =VLOOKUP(C7,'ASIGNACION RANKING'!D:AB,6,0) -> #N/A | I7: =VLOOKUP(C7,'ASIGNACION RANKING'!D:AB,7,0) -> #N/A | J7: =VLOOKUP(C7,'ASIGNACION RANKING'!D:AB,11,0) -> #N/A | K7: =VLOOKUP(C7,'DOMINGO 1'!D:AB,7,0) -> #N/A | L7: =VLOOKUP(C7,'DOMINGO 2'!D:AB,7,0) -> #N/A | M7: =VLOOKUP(C7,'DOMINGO 1'!D:AB,11,0) -> #N/A | N7: =VLOOKUP(C7,'DOMINGO 2'!D:AB,11,0) -> #N/A | O7: =I7-K7-L7 -> #N/A | P7: =J7-M7-N7 -> #N/A | Q7: =P7/O7 -> #N/A | R7: =VLOOKUP(C7,RANKING!E:O,9,0) -> #N/A
A8: S2 | B8: CASHMAX | C8: A0360(MARCELA VALDERRAMA) | F8: MATEO CANO | G8: JOSE SANCHEZ | H8: =VLOOKUP(C8,'ASIGNACION RANKING'!D:AB,6,0) -> #N/A | I8: =VLOOKUP(C8,'ASIGNACION RANKING'!D:AB,7,0) -> #N/A | J8: =VLOOKUP(C8,'ASIGNACION RANKING'!D:AB,11,0) -> #N/A | K8: =VLOOKUP(C8,'DOMINGO 1'!D:AB,7,0) -> #N/A | L8: =VLOOKUP(C8,'DOMINGO 2'!D:AB,7,0) -> #N/A | M8: =VLOOKUP(C8,'DOMINGO 1'!D:AB,11,0) -> #N/A | N8: =VLOOKUP(C8,'DOMINGO 2'!D:AB,11,0) -> #N/A | O8: =I8-K8-L8 -> #N/A | P8: =J8-M8-N8 -> #N/A | Q8: =P8/O8 -> #N/A | R8: =VLOOKUP(C8,RANKING!E:O,9,0) -> #N/A
A9: S2 | B9: CASHMAX | C9: A0315(MATEO PINTO) | F9: MATEO CANO | G9: JOSE SANCHEZ | H9: =VLOOKUP(C9,'ASIGNACION RANKING'!D:AB,6,0) -> #N/A | I9: =VLOOKUP(C9,'ASIGNACION RANKING'!D:AB,7,0) -> #N/A | J9: =VLOOKUP(C9,'ASIGNACION RANKING'!D:AB,11,0) -> #N/A | K9: =VLOOKUP(C9,'DOMINGO 1'!D:AB,7,0) -> #N/A | L9: =VLOOKUP(C9,'DOMINGO 2'!D:AB,7,0) -> #N/A | M9: =VLOOKUP(C9,'DOMINGO 1'!D:AB,11,0) -> #N/A | N9: =VLOOKUP(C9,'DOMINGO 2'!D:AB,11,0) -> #N/A | O9: =I9-K9-L9 -> #N/A | P9: =J9-M9-N9 -> #N/A | Q9: =P9/O9 -> #N/A | R9: =VLOOKUP(C9,RANKING!E:O,9,0) -> #N/A
A10: S2 | B10: CASHMAX | C10: A0135(PAULA RODRIGUEZ ) | F10: MATEO CANO | G10: JOSE SANCHEZ | H10: =VLOOKUP(C10,'ASIGNACION RANKING'!D:AB,6,0) -> #N/A | I10: =VLOOKUP(C10,'ASIGNACION RANKING'!D:AB,7,0) -> #N/A | J10: =VLOOKUP(C10,'ASIGNACION RANKING'!D:AB,11,0) -> #N/A | K10: =VLOOKUP(C10,'DOMINGO 1'!D:AB,7,0) -> #N/A | L10: =VLOOKUP(C10,'DOMINGO 2'!D:AB,7,0) -> #N/A | M10: =VLOOKUP(C10,'DOMINGO 1'!D:AB,11,0) -> #N/A | N10: =VLOOKUP(C10,'DOMINGO 2'!D:AB,11,0) -> #N/A | O10: =I10-K10-L10 -> #N/A | P10: =J10-M10-N10 -> #N/A | Q10: =P10/O10 -> #N/A | R10: =VLOOKUP(C10,RANKING!E:O,9,0) -> #N/A
A11: S2 | B11: CASHMAX | C11: A0217(SEBASTIAN BARRIOS) | F11: MATEO CANO | G11: JOSE SANCHEZ | H11: =VLOOKUP(C11,'ASIGNACION RANKING'!D:AB,6,0) -> #N/A | I11: =VLOOKUP(C11,'ASIGNACION RANKING'!D:AB,7,0) -> #N/A | J11: =VLOOKUP(C11,'ASIGNACION RANKING'!D:AB,11,0) -> #N/A | K11: =VLOOKUP(C11,'DOMINGO 1'!D:AB,7,0) -> #N/A | L11: =VLOOKUP(C11,'DOMINGO 2'!D:AB,7,0) -> #N/A | M11: =VLOOKUP(C11,'DOMINGO 1'!D:AB,11,0) -> #N/A | N11: =VLOOKUP(C11,'DOMINGO 2'!D:AB,11,0) -> #N/A | O11: =I11-K11-L11 -> #N/A | P11: =J11-M11-N11 -> #N/A | Q11: =P11/O11 -> #N/A | R11: =VLOOKUP(C11,RANKING!E:O,9,0) -> #N/A
A12: M2 | B12: CASHMAX | C12: A0325(DAYANA QUILINDO) | F12: MATEO CANO | G12: JOSE SANCHEZ | H12: =VLOOKUP(C12,'ASIGNACION RANKING'!D:AB,6,0) -> 935 | I12: =VLOOKUP(C12,'ASIGNACION RANKING'!D:AB,7,0) -> 1897052 | J12: =VLOOKUP(C12,'ASIGNACION RANKING'!D:AB,11,0) -> 150727 | K12: =VLOOKUP(C12,'DOMINGO 1'!D:AB,7,0) -> 122758 | L12: =VLOOKUP(C12,'DOMINGO 2'!D:AB,7,0) -> 162651 | M12: =VLOOKUP(C12,'DOMINGO 1'!D:AB,11,0) -> 4090 | N12: =VLOOKUP(C12,'DOMINGO 2'!D:AB,11,0) -> 4019 | O12: =I12-K12-L12 -> 1611643 | P12: =J12-M12-N12 -> 142618 | Q12: =P12/O12 -> 0.088492303 | R12: =VLOOKUP(C12,RANKING!E:O,9,0) -> B6
A13: M2 | B13: CASHMAX | C13: A0314(JASBLEIDY MARTINEZ) | F13: MATEO CANO | G13: JOSE SANCHEZ | H13: =VLOOKUP(C13,'ASIGNACION RANKING'!D:AB,6,0) -> #N/A | I13: =VLOOKUP(C13,'ASIGNACION RANKING'!D:AB,7,0) -> #N/A | J13: =VLOOKUP(C13,'ASIGNACION RANKING'!D:AB,11,0) -> #N/A | K13: =VLOOKUP(C13,'DOMINGO 1'!D:AB,7,0) -> #N/A | L13: =VLOOKUP(C13,'DOMINGO 2'!D:AB,7,0) -> #N/A | M13: =VLOOKUP(C13,'DOMINGO 1'!D:AB,11,0) -> #N/A | N13: =VLOOKUP(C13,'DOMINGO 2'!D:AB,11,0) -> #N/A | O13: =I13-K13-L13 -> #N/A | P13: =J13-M13-N13 -> #N/A | Q13: =P13/O13 -> #N/A | R13: =VLOOKUP(C13,RANKING!E:O,9,0) -> #N/A
A14: M2 | B14: CASHMAX | C14: A0099(NESLY SOSA) | F14: MATEO CANO | G14: JOSE SANCHEZ | H14: =VLOOKUP(C14,'ASIGNACION RANKING'!D:AB,6,0) -> #N/A | I14: =VLOOKUP(C14,'ASIGNACION RANKING'!D:AB,7,0) -> #N/A | J14: =VLOOKUP(C14,'ASIGNACION RANKING'!D:AB,11,0) -> #N/A | K14: =VLOOKUP(C14,'DOMINGO 1'!D:AB,7,0) -> #N/A | L14: =VLOOKUP(C14,'DOMINGO 2'!D:AB,7,0) -> #N/A | M14: =VLOOKUP(C14,'DOMINGO 1'!D:AB,11,0) -> #N/A | N14: =VLOOKUP(C14,'DOMINGO 2'!D:AB,11,0) -> #N/A | O14: =I14-K14-L14 -> #N/A | P14: =J14-M14-N14 -> #N/A | Q14: =P14/O14 -> #N/A | R14: =VLOOKUP(C14,RANKING!E:O,9,0) -> #N/A
A15: S1 | B15: OKDINERO | C15: A0258(CRIS URREGO) | F15: GINA VARONI | G15: JOSE SANCHEZ | H15: =VLOOKUP(C15,'ASIGNACION RANKING'!D:AB,6,0) -> 928 | I15: =VLOOKUP(C15,'ASIGNACION RANKING'!D:AB,7,0) -> 1784363 | J15: =VLOOKUP(C15,'ASIGNACION RANKING'!D:AB,11,0) -> 150166 | K15: =VLOOKUP(C15,'DOMINGO 1'!D:AB,7,0) -> 148155 | L15: =VLOOKUP(C15,'DOMINGO 2'!D:AB,7,0) -> 135241 | M15: =VLOOKUP(C15,'DOMINGO 1'!D:AB,11,0) -> 3898 | N15: =VLOOKUP(C15,'DOMINGO 2'!D:AB,11,0) -> 6698 | O15: =I15-K15-L15 -> 1500967 | P15: =J15-M15-N15 -> 139570 | Q15: =P15/O15 -> 0.092986721 | R15: =VLOOKUP(C15,RANKING!E:O,9,0) -> B3 | S15: 10000
A16: S1 | B16: OKDINERO | C16: A0221(DAVID GOMEZ) | F16: GINA VARONI | G16: JOSE SANCHEZ | H16: =VLOOKUP(C16,'ASIGNACION RANKING'!D:AB,6,0) -> 892 | I16: =VLOOKUP(C16,'ASIGNACION RANKING'!D:AB,7,0) -> 1699596 | J16: =VLOOKUP(C16,'ASIGNACION RANKING'!D:AB,11,0) -> 162632 | K16: =VLOOKUP(C16,'DOMINGO 1'!D:AB,7,0) -> 130494 | L16: =VLOOKUP(C16,'DOMINGO 2'!D:AB,7,0) -> 116669 | M16: =VLOOKUP(C16,'DOMINGO 1'!D:AB,11,0) -> 17387 | N16: =VLOOKUP(C16,'DOMINGO 2'!D:AB,11,0) -> 680 | O16: =I16-K16-L16 -> 1452433 | P16: =J16-M16-N16 -> 144565 | Q16: =P16/O16 -> 0.099532991 | R16: =VLOOKUP(C16,RANKING!E:O,9,0) -> B2
A17: S1 | B17: OKDINERO | C17: A0288(FABIAN STIVEN) | F17: GINA VARONI | G17: JOSE SANCHEZ | H17: =VLOOKUP(C17,'ASIGNACION RANKING'!D:AB,6,0) -> 960 | I17: =VLOOKUP(C17,'ASIGNACION RANKING'!D:AB,7,0) -> 1684427 | J17: =VLOOKUP(C17,'ASIGNACION RANKING'!D:AB,11,0) -> 146554 | K17: =VLOOKUP(C17,'DOMINGO 1'!D:AB,7,0) -> 144616 | L17: =VLOOKUP(C17,'DOMINGO 2'!D:AB,7,0) -> 104116 | M17: =VLOOKUP(C17,'DOMINGO 1'!D:AB,11,0) -> 5765 | N17: =VLOOKUP(C17,'DOMINGO 2'!D:AB,11,0) -> 3989 | O17: =I17-K17-L17 -> 1435695 | P17: =J17-M17-N17 -> 136800 | Q17: =P17/O17 -> 0.095284862 | R17: =VLOOKUP(C17,RANKING!E:O,9,0) -> B2
A18: S1 | B18: OKDINERO | C18: A0208(JAVIER RINCON) | F18: GINA VARONI | G18: JOSE SANCHEZ | H18: =VLOOKUP(C18,'ASIGNACION RANKING'!D:AB,6,0) -> #N/A | I18: =VLOOKUP(C18,'ASIGNACION RANKING'!D:AB,7,0) -> #N/A | J18: =VLOOKUP(C18,'ASIGNACION RANKING'!D:AB,11,0) -> #N/A | K18: =VLOOKUP(C18,'DOMINGO 1'!D:AB,7,0) -> #N/A | L18: =VLOOKUP(C18,'DOMINGO 2'!D:AB,7,0) -> #N/A | M18: =VLOOKUP(C18,'DOMINGO 1'!D:AB,11,0) -> #N/A | N18: =VLOOKUP(C18,'DOMINGO 2'!D:AB,11,0) -> #N/A | O18: =I18-K18-L18 -> #N/A | P18: =J18-M18-N18 -> #N/A | Q18: =P18/O18 -> #N/A | R18: =VLOOKUP(C18,RANKING!E:O,9,0) -> #N/A
A19: S1 | B19: OKDINERO | C19: A0399(JHULIET VARGAS) | F19: GINA VARONI | G19: JOSE SANCHEZ | H19: =VLOOKUP(C19,'ASIGNACION RANKING'!D:AB,6,0) -> 231 | I19: =VLOOKUP(C19,'ASIGNACION RANKING'!D:AB,7,0) -> 356300 | J19: =VLOOKUP(C19,'ASIGNACION RANKING'!D:AB,11,0) -> 16051 | K19: =VLOOKUP(C19,'DOMINGO 1'!D:AB,7,0) -> 119843 | L19: =VLOOKUP(C19,'DOMINGO 2'!D:AB,7,0) -> #N/A | M19: =VLOOKUP(C19,'DOMINGO 1'!D:AB,11,0) -> 6611 | N19: =VLOOKUP(C19,'DOMINGO 2'!D:AB,11,0) -> #N/A | O19: =I19-K19-L19 -> #N/A | P19: =J19-M19-N19 -> #N/A | Q19: =P19/O19 -> #N/A | R19: =VLOOKUP(C19,RANKING!E:O,9,0) -> #N/A
A20: S1 | B20: OKDINERO | C20: A0128(LEIDY TORRES) | F20: GINA VARONI | G20: JOSE SANCHEZ | H20: =VLOOKUP(C20,'ASIGNACION RANKING'!D:AB,6,0) -> 1002 | I20: =VLOOKUP(C20,'ASIGNACION RANKING'!D:AB,7,0) -> 1734384 | J20: =VLOOKUP(C20,'ASIGNACION RANKING'!D:AB,11,0) -> 134395 | K20: =VLOOKUP(C20,'DOMINGO 1'!D:AB,7,0) -> 125992 | L20: =VLOOKUP(C20,'DOMINGO 2'!D:AB,7,0) -> 136031 | M20: =VLOOKUP(C20,'DOMINGO 1'!D:AB,11,0) -> 6647 | N20: =VLOOKUP(C20,'DOMINGO 2'!D:AB,11,0) -> 2252 | O20: =I20-K20-L20 -> 1472361 | P20: =J20-M20-N20 -> 125496 | Q20: =P20/O20 -> 0.085234531 | R20: =VLOOKUP(C20,RANKING!E:O,9,0) -> B7 | S20: 30000
A21: S1 | B21: OKDINERO | C21: A0388(MICHAEL BARRIOS) | F21: GINA VARONI | G21: JOSE SANCHEZ | H21: =VLOOKUP(C21,'ASIGNACION RANKING'!D:AB,6,0) -> 1011 | I21: =VLOOKUP(C21,'ASIGNACION RANKING'!D:AB,7,0) -> 2047451 | J21: =VLOOKUP(C21,'ASIGNACION RANKING'!D:AB,11,0) -> 129409 | K21: =VLOOKUP(C21,'DOMINGO 1'!D:AB,7,0) -> 155182 | L21: =VLOOKUP(C21,'DOMINGO 2'!D:AB,7,0) -> 153195 | M21: =VLOOKUP(C21,'DOMINGO 1'!D:AB,11,0) -> 5161 | N21: =VLOOKUP(C21,'DOMINGO 2'!D:AB,11,0) -> 5798 | O21: =I21-K21-L21 -> 1739074 | P21: =J21-M21-N21 -> 118450 | Q21: =P21/O21 -> 0.06811096 | R21: =VLOOKUP(C21,RANKING!E:O,9,0) -> C0 | S21: 10000
A22: S1 | B22: OKDINERO | C22: 0445(MIGUEL ZULETA) | F22: GINA VARONI | G22: JOSE SANCHEZ | H22: =VLOOKUP(C22,'ASIGNACION RANKING'!D:AB,6,0) -> #N/A | I22: =VLOOKUP(C22,'ASIGNACION RANKING'!D:AB,7,0) -> #N/A | J22: =VLOOKUP(C22,'ASIGNACION RANKING'!D:AB,11,0) -> #N/A | K22: =VLOOKUP(C22,'DOMINGO 1'!D:AB,7,0) -> #N/A | L22: =VLOOKUP(C22,'DOMINGO 2'!D:AB,7,0) -> #N/A | M22: =VLOOKUP(C22,'DOMINGO 1'!D:AB,11,0) -> #N/A | N22: =VLOOKUP(C22,'DOMINGO 2'!D:AB,11,0) -> #N/A | O22: =I22-K22-L22 -> #N/A | P22: =J22-M22-N22 -> #N/A | Q22: =P22/O22 -> #N/A | R22: =VLOOKUP(C22,RANKING!E:O,9,0) -> #N/A
A23: S1 | B23: OKDINERO | C23: A0096(NATALYA PACHECO) | F23: GINA VARONI | G23: JOSE SANCHEZ | H23: =VLOOKUP(C23,'ASIGNACION RANKING'!D:AB,6,0) -> 922 | I23: =VLOOKUP(C23,'ASIGNACION RANKING'!D:AB,7,0) -> 1697048 | J23: =VLOOKUP(C23,'ASIGNACION RANKING'!D:AB,11,0) -> 144075 | K23: =VLOOKUP(C23,'DOMINGO 1'!D:AB,7,0) -> 130446 | L23: =VLOOKUP(C23,'DOMINGO 2'!D:AB,7,0) -> 105178 | M23: =VLOOKUP(C23,'DOMINGO 1'!D:AB,11,0) -> 7024 | N23: =VLOOKUP(C23,'DOMINGO 2'!D:AB,11,0) -> 7590 | O23: =I23-K23-L23 -> 1461424 | P23: =J23-M23-N23 -> 129461 | Q23: =P23/O23 -> 0.088585517 | R23: =VLOOKUP(C23,RANKING!E:O,9,0) -> B5 | S23: 30000
A24: S1 | B24: OKDINERO | C24: A0444(NICOL AMEZQUITA) | F24: GINA VARONI | G24: JOSE SANCHEZ | H24: =VLOOKUP(C24,'ASIGNACION RANKING'!D:AB,6,0) -> 844 | I24: =VLOOKUP(C24,'ASIGNACION RANKING'!D:AB,7,0) -> 1515921 | J24: =VLOOKUP(C24,'ASIGNACION RANKING'!D:AB,11,0) -> 152525 | K24: =VLOOKUP(C24,'DOMINGO 1'!D:AB,7,0) -> 124629 | L24: =VLOOKUP(C24,'DOMINGO 2'!D:AB,7,0) -> 106613 | M24: =VLOOKUP(C24,'DOMINGO 1'!D:AB,11,0) -> 9235 | N24: =VLOOKUP(C24,'DOMINGO 2'!D:AB,11,0) -> 2655 | O24: =I24-K24-L24 -> 1284679 | P24: =J24-M24-N24 -> 140635 | Q24: =P24/O24 -> 0.10947093 | R24: =VLOOKUP(C24,RANKING!E:O,9,0) -> A5
A25: S1 | B25: OKDINERO | C25: A0232(PAU ALDANA) | F25: GINA VARONI | G25: JOSE SANCHEZ | H25: =VLOOKUP(C25,'ASIGNACION RANKING'!D:AB,6,0) -> 956 | I25: =VLOOKUP(C25,'ASIGNACION RANKING'!D:AB,7,0) -> 1555092 | J25: =VLOOKUP(C25,'ASIGNACION RANKING'!D:AB,11,0) -> 123906 | K25: =VLOOKUP(C25,'DOMINGO 1'!D:AB,7,0) -> 119412 | L25: =VLOOKUP(C25,'DOMINGO 2'!D:AB,7,0) -> 116136 | M25: =VLOOKUP(C25,'DOMINGO 1'!D:AB,11,0) -> 3083 | N25: =VLOOKUP(C25,'DOMINGO 2'!D:AB,11,0) -> 8970 | O25: =I25-K25-L25 -> 1319544 | P25: =J25-M25-N25 -> 111853 | Q25: =P25/O25 -> 0.084766404 | R25: =VLOOKUP(C25,RANKING!E:O,9,0) -> B7
A26: S1 | B26: OKDINERO | C26: PAULAG08(PAULA GUTIERREZ) | F26: GINA VARONI | G26: JOSE SANCHEZ | H26: =VLOOKUP(C26,'ASIGNACION RANKING'!D:AB,6,0) -> 926 | I26: =VLOOKUP(C26,'ASIGNACION RANKING'!D:AB,7,0) -> 1789761 | J26: =VLOOKUP(C26,'ASIGNACION RANKING'!D:AB,11,0) -> 125988 | K26: =VLOOKUP(C26,'DOMINGO 1'!D:AB,7,0) -> 133250 | L26: =VLOOKUP(C26,'DOMINGO 2'!D:AB,7,0) -> 141398 | M26: =VLOOKUP(C26,'DOMINGO 1'!D:AB,11,0) -> 3159 | N26: =VLOOKUP(C26,'DOMINGO 2'!D:AB,11,0) -> 6760 | O26: =I26-K26-L26 -> 1515113 | P26: =J26-M26-N26 -> 116069 | Q26: =P26/O26 -> 0.076607487 | R26: =VLOOKUP(C26,RANKING!E:O,9,0) -> C0 | S26: 10000
A27: S1 | B27: OKDINERO | C27: A0222(PIPE GONZALEZ) | F27: GINA VARONI | G27: JOSE SANCHEZ | H27: =VLOOKUP(C27,'ASIGNACION RANKING'!D:AB,6,0) -> 965 | I27: =VLOOKUP(C27,'ASIGNACION RANKING'!D:AB,7,0) -> 1771239 | J27: =VLOOKUP(C27,'ASIGNACION RANKING'!D:AB,11,0) -> 147187 | K27: =VLOOKUP(C27,'DOMINGO 1'!D:AB,7,0) -> 143787 | L27: =VLOOKUP(C27,'DOMINGO 2'!D:AB,7,0) -> 128633 | M27: =VLOOKUP(C27,'DOMINGO 1'!D:AB,11,0) -> 7726 | N27: =VLOOKUP(C27,'DOMINGO 2'!D:AB,11,0) -> 2250 | O27: =I27-K27-L27 -> 1498819 | P27: =J27-M27-N27 -> 137211 | Q27: =P27/O27 -> 0.091546077 | R27: =VLOOKUP(C27,RANKING!E:O,9,0) -> B4
A28: S1 | B28: OKDINERO | C28: A0119(WILL) | F28: GINA VARONI | G28: JOSE SANCHEZ | H28: =VLOOKUP(C28,'ASIGNACION RANKING'!D:AB,6,0) -> 903 | I28: =VLOOKUP(C28,'ASIGNACION RANKING'!D:AB,7,0) -> 1334015 | J28: =VLOOKUP(C28,'ASIGNACION RANKING'!D:AB,11,0) -> 155833 | K28: =VLOOKUP(C28,'DOMINGO 1'!D:AB,7,0) -> 104658 | L28: =VLOOKUP(C28,'DOMINGO 2'!D:AB,7,0) -> 82610 | M28: =VLOOKUP(C28,'DOMINGO 1'!D:AB,11,0) -> 1847 | N28: =VLOOKUP(C28,'DOMINGO 2'!D:AB,11,0) -> 6305 | O28: =I28-K28-L28 -> 1146747 | P28: =J28-M28-N28 -> 147681 | Q28: =P28/O28 -> 0.12878255 | R28: =VLOOKUP(C28,RANKING!E:O,9,0) -> A2 | S28: 30000
A29: S1 | B29: OKDINERO | C29: A0438(YULI CASTRO) | F29: GINA VARONI | G29: JOSE SANCHEZ | H29: =VLOOKUP(C29,'ASIGNACION RANKING'!D:AB,6,0) -> 997 | I29: =VLOOKUP(C29,'ASIGNACION RANKING'!D:AB,7,0) -> 1888157 | J29: =VLOOKUP(C29,'ASIGNACION RANKING'!D:AB,11,0) -> 132170 | K29: =VLOOKUP(C29,'DOMINGO 1'!D:AB,7,0) -> 148717 | L29: =VLOOKUP(C29,'DOMINGO 2'!D:AB,7,0) -> 132382 | M29: =VLOOKUP(C29,'DOMINGO 1'!D:AB,11,0) -> 6216 | N29: =VLOOKUP(C29,'DOMINGO 2'!D:AB,11,0) -> 2586 | O29: =I29-K29-L29 -> 1607058 | P29: =J29-M29-N29 -> 123368 | Q29: =P29/O29 -> 0.076766364 | R29: =VLOOKUP(C29,RANKING!E:O,9,0) -> B10 | S29: 10000
A30: S2 | B30: OKDINERO | C30: A0446(ANGIE HUERTAS) | F30: GINA VARONI | G30: JOSE SANCHEZ | H30: =VLOOKUP(C30,'ASIGNACION RANKING'!D:AB,6,0) -> #N/A | I30: =VLOOKUP(C30,'ASIGNACION RANKING'!D:AB,7,0) -> #N/A | J30: =VLOOKUP(C30,'ASIGNACION RANKING'!D:AB,11,0) -> #N/A | K30: =VLOOKUP(C30,'DOMINGO 1'!D:AB,7,0) -> #N/A | L30: =VLOOKUP(C30,'DOMINGO 2'!D:AB,7,0) -> #N/A | M30: 0 | N30: 0 | O30: =I30-K30-L30 -> #N/A | P30: =J30-M30-N30 -> #N/A | Q30: =P30/O30 -> #N/A | R30: =VLOOKUP(C30,RANKING!E:O,9,0) -> #N/A
A31: S2 | B31: OKDINERO | C31: A0324(DANI P) | F31: GINA VARONI | G31: JOSE SANCHEZ | H31: =VLOOKUP(C31,'ASIGNACION RANKING'!D:AB,6,0) -> #N/A | I31: =VLOOKUP(C31,'ASIGNACION RANKING'!D:AB,7,0) -> #N/A | J31: =VLOOKUP(C31,'ASIGNACION RANKING'!D:AB,11,0) -> #N/A | K31: =VLOOKUP(C31,'DOMINGO 1'!D:AB,7,0) -> #N/A | L31: =VLOOKUP(C31,'DOMINGO 2'!D:AB,7,0) -> #N/A | M31: 0 | N31: 0 | O31: =I31-K31-L31 -> #N/A | P31: =J31-M31-N31 -> #N/A | Q31: =P31/O31 -> #N/A | R31: =VLOOKUP(C31,RANKING!E:O,9,0) -> #N/A
A32: S2 | B32: OKDINERO | C32: A0433(ESTEBAN RODRIGUEZ) | F32: GINA VARONI | G32: JOSE SANCHEZ | H32: =VLOOKUP(C32,'ASIGNACION RANKING'!D:AB,6,0) -> #N/A | I32: =VLOOKUP(C32,'ASIGNACION RANKING'!D:AB,7,0) -> #N/A | J32: =VLOOKUP(C32,'ASIGNACION RANKING'!D:AB,11,0) -> #N/A | K32: =VLOOKUP(C32,'DOMINGO 1'!D:AB,7,0) -> #N/A | L32: =VLOOKUP(C32,'DOMINGO 2'!D:AB,7,0) -> #N/A | M32: 0 | N32: 0 | O32: =I32-K32-L32 -> #N/A | P32: =J32-M32-N32 -> #N/A | Q32: =P32/O32 -> #N/A | R32: =VLOOKUP(C32,RANKING!E:O,9,0) -> #N/A
A33: S2 | B33: OKDINERO | C33: A0448(JHON VARGAS) | F33: GINA VARONI | G33: JOSE SANCHEZ | H33: =VLOOKUP(C33,'ASIGNACION RANKING'!D:AB,6,0) -> #N/A | I33: =VLOOKUP(C33,'ASIGNACION RANKING'!D:AB,7,0) -> #N/A | J33: =VLOOKUP(C33,'ASIGNACION RANKING'!D:AB,11,0) -> #N/A | K33: =VLOOKUP(C33,'DOMINGO 1'!D:AB,7,0) -> #N/A | L33: =VLOOKUP(C33,'DOMINGO 2'!D:AB,7,0) -> #N/A | M33: 0 | N33: 0 | O33: =I33-K33-L33 -> #N/A | P33: =J33-M33-N33 -> #N/A | Q33: =P33/O33 -> #N/A | R33: =VLOOKUP(C33,RANKING!E:O,9,0) -> #N/A
A34: S2 | B34: OKDINERO | C34: A0352(K MURILLO) | F34: GINA VARONI | G34: JOSE SANCHEZ | H34: =VLOOKUP(C34,'ASIGNACION RANKING'!D:AB,6,0) -> #N/A | I34: =VLOOKUP(C34,'ASIGNACION RANKING'!D:AB,7,0) -> #N/A | J34: =VLOOKUP(C34,'ASIGNACION RANKING'!D:AB,11,0) -> #N/A | K34: =VLOOKUP(C34,'DOMINGO 1'!D:AB,7,0) -> #N/A | L34: =VLOOKUP(C34,'DOMINGO 2'!D:AB,7,0) -> #N/A | M34: 0 | N34: 0 | O34: =I34-K34-L34 -> #N/A | P34: =J34-M34-N34 -> #N/A | Q34: =P34/O34 -> #N/A | R34: =VLOOKUP(C34,RANKING!E:O,9,0) -> #N/A
A35: S2 | B35: OKDINERO | C35: A0332(L AVILA) | F35: GINA VARONI | G35: JOSE SANCHEZ | H35: =VLOOKUP(C35,'ASIGNACION RANKING'!D:AB,6,0) -> #N/A | I35: =VLOOKUP(C35,'ASIGNACION RANKING'!D:AB,7,0) -> #N/A | J35: =VLOOKUP(C35,'ASIGNACION RANKING'!D:AB,11,0) -> #N/A | K35: =VLOOKUP(C35,'DOMINGO 1'!D:AB,7,0) -> #N/A | L35: =VLOOKUP(C35,'DOMINGO 2'!D:AB,7,0) -> #N/A | M35: 0 | N35: 0 | O35: =I35-K35-L35 -> #N/A | P35: =J35-M35-N35 -> #N/A | Q35: =P35/O35 -> #N/A | R35: =VLOOKUP(C35,RANKING!E:O,9,0) -> #N/A | S35: 20000
A36: S2 | B36: OKDINERO | C36: A0447(LORENA SALGADO) | F36: GINA VARONI | G36: JOSE SANCHEZ | H36: =VLOOKUP(C36,'ASIGNACION RANKING'!D:AB,6,0) -> 938 | I36: =VLOOKUP(C36,'ASIGNACION RANKING'!D:AB,7,0) -> 1737851 | J36: =VLOOKUP(C36,'ASIGNACION RANKING'!D:AB,11,0) -> 145218 | K36: =VLOOKUP(C36,'DOMINGO 1'!D:AB,7,0) -> 137639 | L36: =VLOOKUP(C36,'DOMINGO 2'!D:AB,7,0) -> 121021 | M36: 0 | N36: 0 | O36: =I36-K36-L36 -> 1479191 | P36: =J36-M36-N36 -> 145218 | Q36: =P36/O36 -> 0.098173934 | R36: =VLOOKUP(C36,RANKING!E:O,9,0) -> B5 | S36: 60000
A37: S2 | B37: OKDINERO | C37: A0140(M RAMIREZ) | F37: GINA VARONI | G37: JOSE SANCHEZ | H37: =VLOOKUP(C37,'ASIGNACION RANKING'!D:AB,6,0) -> #N/A | I37: =VLOOKUP(C37,'ASIGNACION RANKING'!D:AB,7,0) -> #N/A | J37: =VLOOKUP(C37,'ASIGNACION RANKING'!D:AB,11,0) -> #N/A | K37: =VLOOKUP(C37,'DOMINGO 1'!D:AB,7,0) -> #N/A | L37: =VLOOKUP(C37,'DOMINGO 2'!D:AB,7,0) -> #N/A | M37: 0 | N37: 0 | O37: =I37-K37-L37 -> #N/A | P37: =J37-M37-N37 -> #N/A | Q37: =P37/O37 -> #N/A | R37: =VLOOKUP(C37,RANKING!E:O,9,0) -> #N/A
A38: S2 | B38: OKDINERO | C38: A0427(MATEO DOMINGUEZ) | F38: GINA VARONI | G38: JOSE SANCHEZ | H38: =VLOOKUP(C38,'ASIGNACION RANKING'!D:AB,6,0) -> #N/A | I38: =VLOOKUP(C38,'ASIGNACION RANKING'!D:AB,7,0) -> #N/A | J38: =VLOOKUP(C38,'ASIGNACION RANKING'!D:AB,11,0) -> #N/A | K38: =VLOOKUP(C38,'DOMINGO 1'!D:AB,7,0) -> #N/A | L38: =VLOOKUP(C38,'DOMINGO 2'!D:AB,7,0) -> #N/A | M38: 0 | N38: 0 | O38: =I38-K38-L38 -> #N/A | P38: =J38-M38-N38 -> #N/A | Q38: =P38/O38 -> #N/A | R38: =VLOOKUP(C38,RANKING!E:O,9,0) -> #N/A | S38: 40000
A39: S2 | B39: OKDINERO | C39: A0205(MATEUS) | F39: GINA VARONI | G39: JOSE SANCHEZ | H39: =VLOOKUP(C39,'ASIGNACION RANKING'!D:AB,6,0) -> #N/A | I39: =VLOOKUP(C39,'ASIGNACION RANKING'!D:AB,7,0) -> #N/A | J39: =VLOOKUP(C39,'ASIGNACION RANKING'!D:AB,11,0) -> #N/A | K39: =VLOOKUP(C39,'DOMINGO 1'!D:AB,7,0) -> #N/A | L39: =VLOOKUP(C39,'DOMINGO 2'!D:AB,7,0) -> #N/A | M39: 0 | N39: 0 | O39: =I39-K39-L39 -> #N/A | P39: =J39-M39-N39 -> #N/A | Q39: =P39/O39 -> #N/A | R39: =VLOOKUP(C39,RANKING!E:O,9,0) -> #N/A
A40: S2 | B40: OKDINERO | C40: A0172(MICHEL R) | F40: GINA VARONI | G40: JOSE SANCHEZ | H40: =VLOOKUP(C40,'ASIGNACION RANKING'!D:AB,6,0) -> #N/A | I40: =VLOOKUP(C40,'ASIGNACION RANKING'!D:AB,7,0) -> #N/A | J40: =VLOOKUP(C40,'ASIGNACION RANKING'!D:AB,11,0) -> #N/A | K40: =VLOOKUP(C40,'DOMINGO 1'!D:AB,7,0) -> #N/A | L40: =VLOOKUP(C40,'DOMINGO 2'!D:AB,7,0) -> #N/A | M40: 0 | N40: 0 | O40: =I40-K40-L40 -> #N/A | P40: =J40-M40-N40 -> #N/A | Q40: =P40/O40 -> #N/A | R40: =VLOOKUP(C40,RANKING!E:O,9,0) -> #N/A
A41: S2 | B41: OKDINERO | C41: A0348(SANTI CAR) | F41: GINA VARONI | G41: JOSE SANCHEZ | H41: =VLOOKUP(C41,'ASIGNACION RANKING'!D:AB,6,0) -> #N/A | I41: =VLOOKUP(C41,'ASIGNACION RANKING'!D:AB,7,0) -> #N/A | J41: =VLOOKUP(C41,'ASIGNACION RANKING'!D:AB,11,0) -> #N/A | K41: =VLOOKUP(C41,'DOMINGO 1'!D:AB,7,0) -> #N/A | L41: =VLOOKUP(C41,'DOMINGO 2'!D:AB,7,0) -> #N/A | M41: 0 | N41: 0 | O41: =I41-K41-L41 -> #N/A | P41: =J41-M41-N41 -> #N/A | Q41: =P41/O41 -> #N/A | R41: =VLOOKUP(C41,RANKING!E:O,9,0) -> #N/A | S41: 20000
A42: S2 | B42: OKDINERO | C42: A0084(SEBASTIAN CUESTA) | F42: GINA VARONI | G42: JOSE SANCHEZ | H42: =VLOOKUP(C42,'ASIGNACION RANKING'!D:AB,6,0) -> #N/A | I42: =VLOOKUP(C42,'ASIGNACION RANKING'!D:AB,7,0) -> #N/A | J42: =VLOOKUP(C42,'ASIGNACION RANKING'!D:AB,11,0) -> #N/A | K42: =VLOOKUP(C42,'DOMINGO 1'!D:AB,7,0) -> #N/A | L42: =VLOOKUP(C42,'DOMINGO 2'!D:AB,7,0) -> #N/A | M42: 0 | N42: 0 | O42: =I42-K42-L42 -> #N/A | P42: =J42-M42-N42 -> #N/A | Q42: =P42/O42 -> #N/A | R42: =VLOOKUP(C42,RANKING!E:O,9,0) -> #N/A
A43: M2 | B43: OKDINERO | C43: A0319(KATERINTH VANEGAS) | F43: GINA VARONI | G43: JOSE SANCHEZ | H43: =VLOOKUP(C43,'ASIGNACION RANKING'!D:AB,6,0) -> #N/A | I43: =VLOOKUP(C43,'ASIGNACION RANKING'!D:AB,7,0) -> #N/A | J43: =VLOOKUP(C43,'ASIGNACION RANKING'!D:AB,11,0) -> #N/A | K43: =VLOOKUP(C43,'DOMINGO 1'!D:AB,7,0) -> #N/A | L43: =VLOOKUP(C43,'DOMINGO 2'!D:AB,7,0) -> #N/A | M43: 0 | N43: 0 | O43: =I43-K43-L43 -> #N/A | P43: =J43-M43-N43 -> #N/A | Q43: =P43/O43 -> #N/A | R43: =VLOOKUP(C43,RANKING!E:O,9,0) -> #N/A
A44: M2 | B44: OKDINERO | C44: A0163(MANUEL GODOY) | F44: GINA VARONI | G44: JOSE SANCHEZ | H44: =VLOOKUP(C44,'ASIGNACION RANKING'!D:AB,6,0) -> #N/A | I44: =VLOOKUP(C44,'ASIGNACION RANKING'!D:AB,7,0) -> #N/A | J44: =VLOOKUP(C44,'ASIGNACION RANKING'!D:AB,11,0) -> #N/A | K44: =VLOOKUP(C44,'DOMINGO 1'!D:AB,7,0) -> #N/A | L44: =VLOOKUP(C44,'DOMINGO 2'!D:AB,7,0) -> #N/A | M44: 0 | N44: 0 | O44: =I44-K44-L44 -> #N/A | P44: =J44-M44-N44 -> #N/A | Q44: =P44/O44 -> #N/A | R44: =VLOOKUP(C44,RANKING!E:O,9,0) -> #N/A
A45: S1 | B45: RAPIKREDITO | C45: A0392(ANGELA GOMEZ ) | F45: JUAN ZORRO | G45: JOSE SANCHEZ | H45: =VLOOKUP(C45,'ASIGNACION RANKING'!D:AB,6,0) -> 960 | I45: =VLOOKUP(C45,'ASIGNACION RANKING'!D:AB,7,0) -> 2340514 | J45: =VLOOKUP(C45,'ASIGNACION RANKING'!D:AB,11,0) -> 161754 | K45: =VLOOKUP(C45,'DOMINGO 1'!D:AB,7,0) -> 178083 | L45: =VLOOKUP(C45,'DOMINGO 2'!D:AB,7,0) -> 180598 | M45: =VLOOKUP(C45,'DOMINGO 1'!D:AB,11,0) -> 6946 | N45: =VLOOKUP(C45,'DOMINGO 2'!D:AB,11,0) -> 6129 | O45: =I45-K45-L45 -> 1981833 | P45: =J45-M45-N45 -> 148679 | Q45: =P45/O45 -> 0.075020953 | R45: =VLOOKUP(C45,RANKING!E:O,9,0) -> C0 | S45: 10000
A46: S1 | B46: RAPIKREDITO | C46: ESTEFANIA R(ESTEFANIA R) | F46: JUAN ZORRO | G46: JOSE SANCHEZ | H46: =VLOOKUP(C46,'ASIGNACION RANKING'!D:AB,6,0) -> #N/A | I46: =VLOOKUP(C46,'ASIGNACION RANKING'!D:AB,7,0) -> #N/A | J46: =VLOOKUP(C46,'ASIGNACION RANKING'!D:AB,11,0) -> #N/A | K46: =VLOOKUP(C46,'DOMINGO 1'!D:AB,7,0) -> #N/A | L46: =VLOOKUP(C46,'DOMINGO 2'!D:AB,7,0) -> #N/A | M46: =VLOOKUP(C46,'DOMINGO 1'!D:AB,11,0) -> #N/A | N46: =VLOOKUP(C46,'DOMINGO 2'!D:AB,11,0) -> #N/A | O46: =I46-K46-L46 -> #N/A | P46: =J46-M46-N46 -> #N/A | Q46: =P46/O46 -> #N/A | R46: =VLOOKUP(C46,RANKING!E:O,9,0) -> #N/A | S46: 20000
A47: S1 | B47: RAPIKREDITO | C47: A0299(INGRID HUERTAS) | F47: JUAN ZORRO | G47: JOSE SANCHEZ | H47: =VLOOKUP(C47,'ASIGNACION RANKING'!D:AB,6,0) -> 884 | I47: =VLOOKUP(C47,'ASIGNACION RANKING'!D:AB,7,0) -> 2170252 | J47: =VLOOKUP(C47,'ASIGNACION RANKING'!D:AB,11,0) -> 175187 | K47: =VLOOKUP(C47,'DOMINGO 1'!D:AB,7,0) -> 177873 | L47: =VLOOKUP(C47,'DOMINGO 2'!D:AB,7,0) -> 147791 | M47: =VLOOKUP(C47,'DOMINGO 1'!D:AB,11,0) -> 7612 | N47: =VLOOKUP(C47,'DOMINGO 2'!D:AB,11,0) -> 6488 | O47: =I47-K47-L47 -> 1844588 | P47: =J47-M47-N47 -> 161087 | Q47: =P47/O47 -> 0.087329528 | R47: =VLOOKUP(C47,RANKING!E:O,9,0) -> B6 | S47: 10000
A48: S1 | B48: RAPIKREDITO | C48: A0148(JUAN MONTENEGRO) | F48: JUAN ZORRO | G48: JOSE SANCHEZ | H48: =VLOOKUP(C48,'ASIGNACION RANKING'!D:AB,6,0) -> 971 | I48: =VLOOKUP(C48,'ASIGNACION RANKING'!D:AB,7,0) -> 2058105 | J48: =VLOOKUP(C48,'ASIGNACION RANKING'!D:AB,11,0) -> 157603 | K48: =VLOOKUP(C48,'DOMINGO 1'!D:AB,7,0) -> 140080 | L48: =VLOOKUP(C48,'DOMINGO 2'!D:AB,7,0) -> 165025 | M48: =VLOOKUP(C48,'DOMINGO 1'!D:AB,11,0) -> 4209 | N48: =VLOOKUP(C48,'DOMINGO 2'!D:AB,11,0) -> 9490 | O48: =I48-K48-L48 -> 1753000 | P48: =J48-M48-N48 -> 143904 | Q48: =P48/O48 -> 0.082090131 | R48: =VLOOKUP(C48,RANKING!E:O,9,0) -> B8
A49: S1 | B49: RAPIKREDITO | C49: A0166(JULIAN KUHNE) | F49: JUAN ZORRO | G49: JOSE SANCHEZ | H49: =VLOOKUP(C49,'ASIGNACION RANKING'!D:AB,6,0) -> 893 | I49: =VLOOKUP(C49,'ASIGNACION RANKING'!D:AB,7,0) -> 1977404 | J49: =VLOOKUP(C49,'ASIGNACION RANKING'!D:AB,11,0) -> 138833 | K49: =VLOOKUP(C49,'DOMINGO 1'!D:AB,7,0) -> 135978 | L49: =VLOOKUP(C49,'DOMINGO 2'!D:AB,7,0) -> 156861 | M49: =VLOOKUP(C49,'DOMINGO 1'!D:AB,11,0) -> 7253 | N49: =VLOOKUP(C49,'DOMINGO 2'!D:AB,11,0) -> 3482 | O49: =I49-K49-L49 -> 1684565 | P49: =J49-M49-N49 -> 128098 | Q49: =P49/O49 -> 0.076042183 | R49: =VLOOKUP(C49,RANKING!E:O,9,0) -> B10 | S49: 10000
A50: S1 | B50: RAPIKREDITO | C50: A0083(MARIANA CORTES) | F50: JUAN ZORRO | G50: JOSE SANCHEZ | H50: =VLOOKUP(C50,'ASIGNACION RANKING'!D:AB,6,0) -> 964 | I50: =VLOOKUP(C50,'ASIGNACION RANKING'!D:AB,7,0) -> 2105451 | J50: =VLOOKUP(C50,'ASIGNACION RANKING'!D:AB,11,0) -> 164885 | K50: =VLOOKUP(C50,'DOMINGO 1'!D:AB,7,0) -> 177881 | L50: =VLOOKUP(C50,'DOMINGO 2'!D:AB,7,0) -> 132526 | M50: =VLOOKUP(C50,'DOMINGO 1'!D:AB,11,0) -> 4206 | N50: =VLOOKUP(C50,'DOMINGO 2'!D:AB,11,0) -> 8788 | O50: =I50-K50-L50 -> 1795044 | P50: =J50-M50-N50 -> 151891 | Q50: =P50/O50 -> 0.084616867 | R50: =VLOOKUP(C50,RANKING!E:O,9,0) -> B7 | S50: 10000
A51: S1 | B51: RAPIKREDITO | C51: MICHEL P(MICHEL P) | F51: JUAN ZORRO | G51: JOSE SANCHEZ | H51: =VLOOKUP(C51,'ASIGNACION RANKING'!D:AB,6,0) -> #N/A | I51: =VLOOKUP(C51,'ASIGNACION RANKING'!D:AB,7,0) -> #N/A | J51: =VLOOKUP(C51,'ASIGNACION RANKING'!D:AB,11,0) -> #N/A | K51: =VLOOKUP(C51,'DOMINGO 1'!D:AB,7,0) -> #N/A | L51: =VLOOKUP(C51,'DOMINGO 2'!D:AB,7,0) -> #N/A | M51: =VLOOKUP(C51,'DOMINGO 1'!D:AB,11,0) -> #N/A | N51: =VLOOKUP(C51,'DOMINGO 2'!D:AB,11,0) -> #N/A | O51: =I51-K51-L51 -> #N/A | P51: =J51-M51-N51 -> #N/A | Q51: =P51/O51 -> #N/A | R51: =VLOOKUP(C51,RANKING!E:O,9,0) -> #N/A | S51: 40000
A52: S1 | B52: RAPIKREDITO | C52: A0214(NEIDY FORERO) | F52: JUAN ZORRO | G52: JOSE SANCHEZ | H52: =VLOOKUP(C52,'ASIGNACION RANKING'!D:AB,6,0) -> #N/A | I52: =VLOOKUP(C52,'ASIGNACION RANKING'!D:AB,7,0) -> #N/A | J52: =VLOOKUP(C52,'ASIGNACION RANKING'!D:AB,11,0) -> #N/A | K52: =VLOOKUP(C52,'DOMINGO 1'!D:AB,7,0) -> #N/A | L52: =VLOOKUP(C52,'DOMINGO 2'!D:AB,7,0) -> #N/A | M52: =VLOOKUP(C52,'DOMINGO 1'!D:AB,11,0) -> #N/A | N52: =VLOOKUP(C52,'DOMINGO 2'!D:AB,11,0) -> #N/A | O52: =I52-K52-L52 -> #N/A | P52: =J52-M52-N52 -> #N/A | Q52: =P52/O52 -> #N/A | R52: =VLOOKUP(C52,RANKING!E:O,9,0) -> #N/A | S52: 10000
A53: S1 | B53: RAPIKREDITO | C53: PAULA R(PAULA R) | F53: JUAN ZORRO | G53: JOSE SANCHEZ | H53: =VLOOKUP(C53,'ASIGNACION RANKING'!D:AB,6,0) -> #N/A | I53: =VLOOKUP(C53,'ASIGNACION RANKING'!D:AB,7,0) -> #N/A | J53: =VLOOKUP(C53,'ASIGNACION RANKING'!D:AB,11,0) -> #N/A | K53: =VLOOKUP(C53,'DOMINGO 1'!D:AB,7,0) -> #N/A | L53: =VLOOKUP(C53,'DOMINGO 2'!D:AB,7,0) -> #N/A | M53: =VLOOKUP(C53,'DOMINGO 1'!D:AB,11,0) -> #N/A | N53: =VLOOKUP(C53,'DOMINGO 2'!D:AB,11,0) -> #N/A | O53: =I53-K53-L53 -> #N/A | P53: =J53-M53-N53 -> #N/A | Q53: =P53/O53 -> #N/A | R53: =VLOOKUP(C53,RANKING!E:O,9,0) -> #N/A
A54: S1 | B54: RAPIKREDITO | C54: SEBASTIAN S(SEBASTIAN S) | F54: JUAN ZORRO | G54: JOSE SANCHEZ | H54: =VLOOKUP(C54,'ASIGNACION RANKING'!D:AB,6,0) -> #N/A | I54: =VLOOKUP(C54,'ASIGNACION RANKING'!D:AB,7,0) -> #N/A | J54: =VLOOKUP(C54,'ASIGNACION RANKING'!D:AB,11,0) -> #N/A | K54: =VLOOKUP(C54,'DOMINGO 1'!D:AB,7,0) -> #N/A | L54: =VLOOKUP(C54,'DOMINGO 2'!D:AB,7,0) -> #N/A | M54: =VLOOKUP(C54,'DOMINGO 1'!D:AB,11,0) -> #N/A | N54: =VLOOKUP(C54,'DOMINGO 2'!D:AB,11,0) -> #N/A | O54: =I54-K54-L54 -> #N/A | P54: =J54-M54-N54 -> #N/A | Q54: =P54/O54 -> #N/A | R54: =VLOOKUP(C54,RANKING!E:O,9,0) -> #N/A
A55: S1 | B55: RAPIKREDITO | C55: A0387(TATIANA BARINAS) | F55: JUAN ZORRO | G55: JOSE SANCHEZ | H55: =VLOOKUP(C55,'ASIGNACION RANKING'!D:AB,6,0) -> 856 | I55: =VLOOKUP(C55,'ASIGNACION RANKING'!D:AB,7,0) -> 1907427 | J55: =VLOOKUP(C55,'ASIGNACION RANKING'!D:AB,11,0) -> 163763 | K55: =VLOOKUP(C55,'DOMINGO 1'!D:AB,7,0) -> 133268 | L55: =VLOOKUP(C55,'DOMINGO 2'!D:AB,7,0) -> 156985 | M55: =VLOOKUP(C55,'DOMINGO 1'!D:AB,11,0) -> 9288 | N55: =VLOOKUP(C55,'DOMINGO 2'!D:AB,11,0) -> 8428 | O55: =I55-K55-L55 -> 1617174 | P55: =J55-M55-N55 -> 146047 | Q55: =P55/O55 -> 0.09031001 | R55: =VLOOKUP(C55,RANKING!E:O,9,0) -> B5
A56: S1 | B56: RAPIKREDITO | C56: A0272(TATIANA ZORRO) | F56: JUAN ZORRO | G56: JOSE SANCHEZ | H56: =VLOOKUP(C56,'ASIGNACION RANKING'!D:AB,6,0) -> 892 | I56: =VLOOKUP(C56,'ASIGNACION RANKING'!D:AB,7,0) -> 1873250 | J56: =VLOOKUP(C56,'ASIGNACION RANKING'!D:AB,11,0) -> 166066 | K56: =VLOOKUP(C56,'DOMINGO 1'!D:AB,7,0) -> 135647 | L56: =VLOOKUP(C56,'DOMINGO 2'!D:AB,7,0) -> 146563 | M56: =VLOOKUP(C56,'DOMINGO 1'!D:AB,11,0) -> 5020 | N56: =VLOOKUP(C56,'DOMINGO 2'!D:AB,11,0) -> 5639 | O56: =I56-K56-L56 -> 1591040 | P56: =J56-M56-N56 -> 155407 | Q56: =P56/O56 -> 0.097676363 | R56: =VLOOKUP(C56,RANKING!E:O,9,0) -> B2 | S56: 20000
A57: S2 | B57: RAPIKREDITO | C57: A0051(ALEJANDRA CUBILLOS ) | F57: JUAN ZORRO | G57: JOSE SANCHEZ | H57: =VLOOKUP(C57,'ASIGNACION RANKING'!D:AB,6,0) -> #N/A | I57: =VLOOKUP(C57,'ASIGNACION RANKING'!D:AB,7,0) -> #N/A | J57: =VLOOKUP(C57,'ASIGNACION RANKING'!D:AB,11,0) -> #N/A | K57: =VLOOKUP(C57,'DOMINGO 1'!D:AB,7,0) -> #N/A | L57: =VLOOKUP(C57,'DOMINGO 2'!D:AB,7,0) -> #N/A | M57: 0 | N57: 0 | O57: =I57-K57-L57 -> #N/A | P57: =J57-M57-N57 -> #N/A | Q57: =P57/O57 -> #N/A | R57: =VLOOKUP(C57,RANKING!E:O,9,0) -> #N/A | S57: 20000
A58: S2 | B58: RAPIKREDITO | C58: A0159(CAROL TATIANA ) | F58: JUAN ZORRO | G58: JOSE SANCHEZ | H58: =VLOOKUP(C58,'ASIGNACION RANKING'!D:AB,6,0) -> #N/A | I58: =VLOOKUP(C58,'ASIGNACION RANKING'!D:AB,7,0) -> #N/A | J58: =VLOOKUP(C58,'ASIGNACION RANKING'!D:AB,11,0) -> #N/A | K58: =VLOOKUP(C58,'DOMINGO 1'!D:AB,7,0) -> #N/A | L58: =VLOOKUP(C58,'DOMINGO 2'!D:AB,7,0) -> #N/A | M58: 0 | N58: 0 | O58: =I58-K58-L58 -> #N/A | P58: =J58-M58-N58 -> #N/A | Q58: =P58/O58 -> #N/A | R58: =VLOOKUP(C58,RANKING!E:O,9,0) -> #N/A
A59: S2 | B59: RAPIKREDITO | C59: A0328(GERMAN MAURICIO ) | F59: JUAN ZORRO | G59: JOSE SANCHEZ | H59: =VLOOKUP(C59,'ASIGNACION RANKING'!D:AB,6,0) -> #N/A | I59: =VLOOKUP(C59,'ASIGNACION RANKING'!D:AB,7,0) -> #N/A | J59: =VLOOKUP(C59,'ASIGNACION RANKING'!D:AB,11,0) -> #N/A | K59: =VLOOKUP(C59,'DOMINGO 1'!D:AB,7,0) -> #N/A | L59: =VLOOKUP(C59,'DOMINGO 2'!D:AB,7,0) -> #N/A | M59: 0 | N59: 0 | O59: =I59-K59-L59 -> #N/A | P59: =J59-M59-N59 -> #N/A | Q59: =P59/O59 -> #N/A | R59: =VLOOKUP(C59,RANKING!E:O,9,0) -> #N/A | S59: 20000
A60: S2 | B60: RAPIKREDITO | C60: A0436(HEIDY GOMEZ) | F60: JUAN ZORRO | G60: JOSE SANCHEZ | H60: =VLOOKUP(C60,'ASIGNACION RANKING'!D:AB,6,0) -> #N/A | I60: =VLOOKUP(C60,'ASIGNACION RANKING'!D:AB,7,0) -> #N/A | J60: =VLOOKUP(C60,'ASIGNACION RANKING'!D:AB,11,0) -> #N/A | K60: =VLOOKUP(C60,'DOMINGO 1'!D:AB,7,0) -> #N/A | L60: =VLOOKUP(C60,'DOMINGO 2'!D:AB,7,0) -> #N/A | M60: 0 | N60: 0 | O60: =I60-K60-L60 -> #N/A | P60: =J60-M60-N60 -> #N/A | Q60: =P60/O60 -> #N/A | R60: =VLOOKUP(C60,RANKING!E:O,9,0) -> #N/A
A61: S2 | B61: RAPIKREDITO | C61: A031(KAREN M) | F61: JUAN ZORRO | G61: JOSE SANCHEZ | H61: =VLOOKUP(C61,'ASIGNACION RANKING'!D:AB,6,0) -> #N/A | I61: =VLOOKUP(C61,'ASIGNACION RANKING'!D:AB,7,0) -> #N/A | J61: =VLOOKUP(C61,'ASIGNACION RANKING'!D:AB,11,0) -> #N/A | K61: =VLOOKUP(C61,'DOMINGO 1'!D:AB,7,0) -> #N/A | L61: =VLOOKUP(C61,'DOMINGO 2'!D:AB,7,0) -> #N/A | M61: 0 | N61: 0 | O61: =I61-K61-L61 -> #N/A | P61: =J61-M61-N61 -> #N/A | Q61: =P61/O61 -> #N/A | R61: =VLOOKUP(C61,RANKING!E:O,9,0) -> #N/A | S61: 60000
A62: S2 | B62: RAPIKREDITO | C62: A0293(KATERINE NIÑO) | F62: JUAN ZORRO | G62: JOSE SANCHEZ | H62: =VLOOKUP(C62,'ASIGNACION RANKING'!D:AB,6,0) -> #N/A | I62: =VLOOKUP(C62,'ASIGNACION RANKING'!D:AB,7,0) -> #N/A | J62: =VLOOKUP(C62,'ASIGNACION RANKING'!D:AB,11,0) -> #N/A | K62: =VLOOKUP(C62,'DOMINGO 1'!D:AB,7,0) -> #N/A | L62: =VLOOKUP(C62,'DOMINGO 2'!D:AB,7,0) -> #N/A | M62: 0 | N62: 0 | O62: =I62-K62-L62 -> #N/A | P62: =J62-M62-N62 -> #N/A | Q62: =P62/O62 -> #N/A | R62: =VLOOKUP(C62,RANKING!E:O,9,0) -> #N/A
A63: S2 | B63: RAPIKREDITO | C63: A0397(LAURA PENAGOS ) | F63: JUAN ZORRO | G63: JOSE SANCHEZ | H63: =VLOOKUP(C63,'ASIGNACION RANKING'!D:AB,6,0) -> #N/A | I63: =VLOOKUP(C63,'ASIGNACION RANKING'!D:AB,7,0) -> #N/A | J63: =VLOOKUP(C63,'ASIGNACION RANKING'!D:AB,11,0) -> #N/A | K63: =VLOOKUP(C63,'DOMINGO 1'!D:AB,7,0) -> #N/A | L63: =VLOOKUP(C63,'DOMINGO 2'!D:AB,7,0) -> #N/A | M63: 0 | N63: 0 | O63: =I63-K63-L63 -> #N/A | P63: =J63-M63-N63 -> #N/A | Q63: =P63/O63 -> #N/A | R63: =VLOOKUP(C63,RANKING!E:O,9,0) -> #N/A | S63: 40000
A64: S2 | B64: RAPIKREDITO | C64: A0073(Laura Dayana Torres Carvajal) | F64: JUAN ZORRO | G64: JOSE SANCHEZ | H64: =VLOOKUP(C64,'ASIGNACION RANKING'!D:AB,6,0) -> #N/A | I64: =VLOOKUP(C64,'ASIGNACION RANKING'!D:AB,7,0) -> #N/A | J64: =VLOOKUP(C64,'ASIGNACION RANKING'!D:AB,11,0) -> #N/A | K64: =VLOOKUP(C64,'DOMINGO 1'!D:AB,7,0) -> #N/A | L64: =VLOOKUP(C64,'DOMINGO 2'!D:AB,7,0) -> #N/A | M64: 0 | N64: 0 | O64: =I64-K64-L64 -> #N/A | P64: =J64-M64-N64 -> #N/A | Q64: =P64/O64 -> #N/A | R64: =VLOOKUP(C64,RANKING!E:O,9,0) -> #N/A
A65: S2 | B65: RAPIKREDITO | C65: A035(NATALIA B) | F65: JUAN ZORRO | G65: JOSE SANCHEZ | H65: =VLOOKUP(C65,'ASIGNACION RANKING'!D:AB,6,0) -> #N/A | I65: =VLOOKUP(C65,'ASIGNACION RANKING'!D:AB,7,0) -> #N/A | J65: =VLOOKUP(C65,'ASIGNACION RANKING'!D:AB,11,0) -> #N/A | K65: =VLOOKUP(C65,'DOMINGO 1'!D:AB,7,0) -> #N/A | L65: =VLOOKUP(C65,'DOMINGO 2'!D:AB,7,0) -> #N/A | M65: 0 | N65: 0 | O65: =I65-K65-L65 -> #N/A | P65: =J65-M65-N65 -> #N/A | Q65: =P65/O65 -> #N/A | R65: =VLOOKUP(C65,RANKING!E:O,9,0) -> #N/A
A66: S2 | B66: RAPIKREDITO | C66: A0136(SANDRA MILENA ) | F66: JUAN ZORRO | G66: JOSE SANCHEZ | H66: =VLOOKUP(C66,'ASIGNACION RANKING'!D:AB,6,0) -> #N/A | I66: =VLOOKUP(C66,'ASIGNACION RANKING'!D:AB,7,0) -> #N/A | J66: =VLOOKUP(C66,'ASIGNACION RANKING'!D:AB,11,0) -> #N/A | K66: =VLOOKUP(C66,'DOMINGO 1'!D:AB,7,0) -> #N/A | L66: =VLOOKUP(C66,'DOMINGO 2'!D:AB,7,0) -> #N/A | M66: 0 | N66: 0 | O66: =I66-K66-L66 -> #N/A | P66: =J66-M66-N66 -> #N/A | Q66: =P66/O66 -> #N/A | R66: =VLOOKUP(C66,RANKING!E:O,9,0) -> #N/A
A67: S2 | B67: RAPIKREDITO | C67: A0410(SANDY MENDIETA ) | F67: JUAN ZORRO | G67: JOSE SANCHEZ | H67: =VLOOKUP(C67,'ASIGNACION RANKING'!D:AB,6,0) -> #N/A | I67: =VLOOKUP(C67,'ASIGNACION RANKING'!D:AB,7,0) -> #N/A | J67: =VLOOKUP(C67,'ASIGNACION RANKING'!D:AB,11,0) -> #N/A | K67: =VLOOKUP(C67,'DOMINGO 1'!D:AB,7,0) -> #N/A | L67: =VLOOKUP(C67,'DOMINGO 2'!D:AB,7,0) -> #N/A | M67: 0 | N67: 0 | O67: =I67-K67-L67 -> #N/A | P67: =J67-M67-N67 -> #N/A | Q67: =P67/O67 -> #N/A | R67: =VLOOKUP(C67,RANKING!E:O,9,0) -> #N/A | S67: 20000
A68: M2 | B68: RAPIKREDITO | C68: A0147(EMMANUEL ZAMORA) | F68: JUAN ZORRO | G68: JOSE SANCHEZ | H68: =VLOOKUP(C68,'ASIGNACION RANKING'!D:AB,6,0) -> #N/A | I68: =VLOOKUP(C68,'ASIGNACION RANKING'!D:AB,7,0) -> #N/A | J68: =VLOOKUP(C68,'ASIGNACION RANKING'!D:AB,11,0) -> #N/A | K68: =VLOOKUP(C68,'DOMINGO 1'!D:AB,7,0) -> #N/A | L68: =VLOOKUP(C68,'DOMINGO 2'!D:AB,7,0) -> #N/A | M68: 0 | N68: 0 | O68: =I68-K68-L68 -> #N/A | P68: =J68-M68-N68 -> #N/A | Q68: =P68/O68 -> #N/A | R68: =VLOOKUP(C68,RANKING!E:O,9,0) -> #N/A
A69: M2 | B69: RAPIKREDITO | C69: A0294(LAURA RODRIGUEZ ) | F69: JUAN ZORRO | G69: JOSE SANCHEZ | H69: =VLOOKUP(C69,'ASIGNACION RANKING'!D:AB,6,0) -> #N/A | I69: =VLOOKUP(C69,'ASIGNACION RANKING'!D:AB,7,0) -> #N/A | J69: =VLOOKUP(C69,'ASIGNACION RANKING'!D:AB,11,0) -> #N/A | K69: =VLOOKUP(C69,'DOMINGO 1'!D:AB,7,0) -> #N/A | L69: =VLOOKUP(C69,'DOMINGO 2'!D:AB,7,0) -> #N/A | M69: 0 | N69: 0 | O69: =I69-K69-L69 -> #N/A | P69: =J69-M69-N69 -> #N/A | Q69: =P69/O69 -> #N/A | R69: =VLOOKUP(C69,RANKING!E:O,9,0) -> #N/A
A70: M2 | B70: RAPIKREDITO | C70: A0182(NELSON TORRES ) | F70: JUAN ZORRO | G70: JOSE SANCHEZ | H70: =VLOOKUP(C70,'ASIGNACION RANKING'!D:AB,6,0) -> #N/A | I70: =VLOOKUP(C70,'ASIGNACION RANKING'!D:AB,7,0) -> #N/A | J70: =VLOOKUP(C70,'ASIGNACION RANKING'!D:AB,11,0) -> #N/A | K70: =VLOOKUP(C70,'DOMINGO 1'!D:AB,7,0) -> #N/A | L70: =VLOOKUP(C70,'DOMINGO 2'!D:AB,7,0) -> #N/A | M70: 0 | N70: 0 | O70: =I70-K70-L70 -> #N/A | P70: =J70-M70-N70 -> #N/A | Q70: =P70/O70 -> #N/A | R70: =VLOOKUP(C70,RANKING!E:O,9,0) -> #N/A

Sheet DATOS ASESORES
A1: NOMBRE | B1: ESTAN EN TELETRABAJO | C1: PUEDE TELETRABAJAR | D1: TIENE MOTO | E1: REGISTRO SEDE 2 | F1: Periodo de prueba | G1: Fin periodo de prueba | H1: Fecha ingreso | I1: Procesos disciplinarios
A2: Johan Sebastian Cuesta Garcia | B2: NO | C2: SI | D2: NO | E2: SI | F2: NO | H2: 45917 | I2: Descargos
A3: Laura Alejandra Velandia Martinez | B3: NO | C3: NO | D3: NO | E3: SI | F3: NO | H3: 46113 | M3: rapi s1 | N3: 13
A4: Daniel Stiven Mayorga Galindo | B4: NO | C4: SI | D4: NO | E4: SI | F4: NO | H4: 46155 | M4: rapi s2 | N4: 11
A5: Johan Sebastian Ojeda Garcia | B5: NO | D5: NO | E5: SI | F5: SI | G5: 46239 | H5: 46178 | M5: rapi m1 | N5: 7
A6: Leidy Diana Torres | B6: NO | D6: NO | E6: NO | F6: NO | H6: 46028 | I6: Descargos | J6: GRUPO 1 | M6: RAPI | N6: =SUM(N3:N5) -> 31
A7: Kevin Sebastian Murillo Avila | B7: NO | D7: NO | E7: NO | F7: SI | G7: 46266 | H7: 46204 | M7: s1 ok | N7: 13
A8: Juan Diego Melo Zuleta | B8: NO | D8: NO | E8: NO | F8: SI | G8: 46239 | H8: 46178 | M8: s2 ok | N8: 13
A9: Emilie Brigitte Alarcon Gonzalez | B9: NO | D9: NO | E9: NO | F9: NO | H9: 46158 | M9: m1 ok | N9: 8
A10: Yeison Nicolas Suarez Granados | B10: NO | C10: SI | D10: NO | E10: SI | F10: NO | H10: 45512 | M10: OK | N10: =SUM(N7:N9) -> 34
A11: Carol Tatiana Sierra Ulloa | B11: NO | C11: SI | D11: NO | E11: SI | F11: NO | H11: 46072 | M11: cash s1 | N11: 11
A12: Sandra Yuliana Huertas Perez | B12: NO | C12: NO | D12: SI | E12: SI | F12: NO | H12: 46128 | M12: cash s2 | N12: 10
A13: Jhon Jairo Alarcon Parra | B13: NO | C13: SI | D13: NO | E13: SI | F13: NO | H13: 46158 | M13: cash m1 | N13: 7
A14: Gabriela Sofia Castaño Pineda | B14: NO | C14: SI | D14: NO | E14: NO | F14: SI | G14: 46252 | H14: 46191 | M14: CASH | N14: =SUM(N11:N13) -> 28
A15: Juan Sebastian Barrios Parra | B15: NO | C15: SI | D15: NO | E15: NO | F15: NO | H15: 46137 | M15: tl jose | N15: =N6+N10+N14 -> 93
A16: Mateo Pinto Marin | B16: NO | C16: SI | D16: SI | E16: NO | F16: SI | G16: 46235 | H16: 01//06/2026
A17: Alejandro Castro Herrera | B17: NO | C17: SI | D17: SI | E17: NO | F17: NO | H17: 45932
A18: Alonso Navarro Munevar | B18: NO | C18: SI | D18: NO | E18: NO | F18: NO | H18: 46158
A19: Cristian Arley Rodriguez Lopez | B19: NO | C19: SI | D19: NO | E19: NO | F19: NO | H19: 46009
A20: Cristian David Urrego Garzon | B20: NO | C20: NO | D20: SI | E20: SI | F20: NO | H20: 46155
A21: Eddy Santiago Gomez Cabrera | B21: NO | C21: NO | D21: NO | E21: SI | F21: NO | H21: 46158 | I21: Ausencia
A22: Ingrid Dayana Huertas Perez | B22: NO | C22: SI | D22: NO | E22: SI | F22: NO | H22: 46164
A23: Jhosep Escandon Zambrano | B23: NO | C23: SI | D23: SI | E23: SI | F23: NO | H23: 46151 | I23: Ausencia
A24: John Fredy Florez Coronado | B24: NO | C24: NO | D24: NO | E24: SI | F24: NO | H24: 45962 | I24: Falta grave
A25: Jose Alejandro Vera Lopez | B25: NO | C25: SI | D25: NO | E25: NO | F25: SI | G25: 46271 | H25: 46209 | J25: GRUPO 2
A26: Manuela Cubillos Lozano | B26: NO | C26: SI | D26: NO | E26: NO | F26: NO | H26: 46155
A27: Laura Dayana Torres Carvajal | B27: NO | C27: NO | D27: NO | E27: NO | F27: NO | H27: 45885 | K27: Vacaciones 16/08/2026
A28: Nelson Andres Torres Lopez | B28: NO | C28: NO | D28: NO | E28: NO | F28: NO | H28: 46102
A29: Nesly Magyoly Sosa Ortiz | B29: NO | C29: SI | D29: NO | E29: NO | F29: NO | H29: 45952
A30: Yurany Dasney Giraldo Reyes | B30: NO | C30: NO | D30: NO | E30: NO | F30: NO | H30: 46155
A31: Andrea Juenssy Valentina Galindo | B31: NO | C31: SI | D31: SI | E31: NO | F31: SI | G31: 46244 | H31: 46183 | I31: Ausencias
A32: Daniel Leonardo Avila Lopez | B32: NO | C32: NO | D32: SI | E32: NO | F32: NO | G32: 46240 | H32: 46179
A33: Daniel Rojas Perilla | B33: NO | C33: SI | D33: NO | E33: NO | F33: SI | G33: 46244 | H33: 46183 | I33: Ausencias
A34: Fabian Estiben Arias | B34: NO | C34: SI | D34: NO | E34: NO | F34: NO | H34: 46158
A35: German Mauricio Molina Perea | B35: NO | C35: NO | D35: NO | E35: NO | F35: SI | G35: 46239 | H35: 46178 | I35: Ausencia
A36: Jasbleidy Johanna Martinez Casas | B36: NO | C36: SI | D36: NO | E36: NO | F36: SI | G36: 46235 | H36: 01//06/2026 | J36: GRUPO 3
A37: Johan Santiago Cardenas Ramirez | B37: NO | C37: SI | D37: SI | E37: NO | F37: SI | G37: 46266 | H37: 46204
A38: Juan Sebastian Ortiz Suarez | B38: NO | C38: SI | D38: NO | E38: NO | F38: NO | H38: 46155
A39: Kaffyr David Puertas Novoa | B39: NO | C39: SI | D39: NO | E39: NO | F39: SI | G39: 46252 | H39: 46191
A40: Katerinth Vanesa Vanegas Guerrero | B40: NO | C40: SI | D40: NO | E40: NO | F40: SI | G40: 46235 | H40: 01//06/2026
A41: Marcela Sanchez Valderrama | B41: NO | C41: NO | D41: NO | E41: NO | F41: SI | G41: 46267 | H41: 46205
A42: Natalia Stefania Barbosa Moreno | B42: NO | C42: SI | D42: NO | E42: NO | F42: SI | G42: 46267 | H42: 46205
A43: Evelin Katherin Morales Vargas | B43: NO | C43: NO | D43: NO | E43: NO | F43: NO | H43: 45855
A44: Sandra Milena Serrano | B44: NO | C44: SI | D44: NO | E44: NO | F44: NO | H44: 46036
A45: Brayan Javier Rincon Hernandez | B45: NO | C45: NO | D45: NO | E45: NO | F45: NO | H45: 46128
A46: Neidy Sofia Forero Suarez | B46: SI | E46: NO | F46: NO | H46: 46132 | J46: GRUPO 4
A47: Yudrein Daniela Panciarro Morales | B47: NO | C47: SI | D47: NO | E47: NO | F47: SI | G47: 46237 | H47: 46176 | I47: Retardos
A48: Mariana Cortes Helmsdorff | B48: NO | C48: SI | D48: NO | E48: NO | F48: NO | H48: 45917
A49: Caren Dayana Quilindo Montoya | B49: NO | C49: SI | D49: NO | E49: NO | F49: SI | G49: 46237 | H49: 46176
A50: Monica Patricia Oviedo Cuadros | B50: NO | C50: SI | D50: NO | E50: NO | F50: NO | H50: 46155
A51: Manuel Felipe Godoy Barrera | B51: NO | C51: SI | D51: SI | E51: NO | F51: NO | H51: 46083
A52: Santiago Sanchez Otero | B52: NO | C52: NO | D52: NO | E52: NO | F52: NO | H52: 45793
A53: Paula Andrea Rivas Vanegas | B53: NO | C53: NO | D53: NO | E53: NO | F53: NO | H53: 45982
A54: Juan Camilo Silva Paternina | B54: NO | C54: NO | D54: SI | E54: SI | F54: NO | H54: 45917
A55: Ashley Tatiana Zorro Chica | B55: NO | C55: SI | D55: NO | E55: SI | F55: NO | H55: 46158
A56: Milena Alexandra Gonzalez Chiquito | B56: NO | C56: NO | D56: NO | E56: SI | F56: NO | H56: 46155
A57: Paula Daniela Aldana Calderon | B57: NO | C57: NO | D57: NO | E57: SI | F57: NO | H57: 46155
A58: Brandon Esteban Rodriguez Perafan | B58: NO | C58: SI | D58: SI | E58: NO | F58: NO | H58: 46128
A59: Jenny Juley Mendieta Moreno | B59: NO | C59: SI | D59: NO | E59: NO | F59: NO | H59: 45870 | I59: Retardos | J59: GRUPO 5
A60: Jonatan Camilo Castillo Rincon | B60: NO | C60: SI | D60: SI | E60: NO | F60: NO | H60: 45832 | K60: Vacaciones 01/08/2026
A61: Estefania Ramos Guerrero | B61: NO | C61: NO | D61: NO | E61: NO | F61: SI | G61: 46237 | H61: 46176
A62: Juan David Gomez Daza | B62: NO | C62: NO | D62: NO | E62: NO | F62: NO | H62: 46139
A63: Julian David Arango Kuhne | B63: NO | C63: NO | D63: NO | E63: NO | F63: NO | H63: 46084
A64: Karen Daniela Rodriguez Murcia | B64: NO | C64: SI | D64: NO | E64: NO | F64: NO | H64: 46169
A65: Diana Miled Moreno Diaz | B65: NO | C65: SI | D65: NO | E65: NO | F65: NO | H65: 46155
A66: Paula Natalia Pacheco Lopez | B66: SI | C66: SI | D66: NO | E66: NO | F66: NO | H66: 45950
A67: Juan Pablo Lancheros Montenegro | B67: NO | C67: SI | D67: NO | E67: NO | F67: NO | H67: 46059
A68: Michell Nicol Rodriguez Cortes | B68: SI | C68: SI | D68: NO | E68: NO | F68: NO | H68: 46093 | I68: Descargos
A69: Sharic Cecilia Salazar Runza | B69: NO | C69: SI | D69: NO | E69: NO | F69: NO | H69: 46084 | J69: GRUPO 6
A70: Luz Andrea Garcia Hueso | B70: NO | C70: SI | D70: NO | E70: NO | F70: NO | H70: 45875 | K70: Vacaciones 18/08/2026
A71: Karoll Mariana Leon Rojas | B71: NO | C71: NO | D71: NO | E71: NO | F71: NO | H71: 45749 | I71: Retardos
A72: Lina Maria Silva Castro | B72: NO | C72: SI | D72: SI | E72: NO | F72: SI | G72: 46282 | H72: 46220
A73: Yulieth Andrea Rodriguez Vargas | B73: NO | C73: SI | D73: NO | E73: SI | F73: NO | H73: 46030
A74: Maria Paula Ramirez Cruz | B74: NO | C74: SI | D74: NO | E74: SI | F74: NO | H74: 46097
A75: Jordan Estmi Valderrama Lozano | B75: NO | C75: SI | D75: NO | E75: SI | F75: NO | H75: 45763
A76: Erika Valentina Moreno Leiton | B76: NO | C76: SI | D76: NO | E76: SI | F76: NO | H76: 46158
A77: Emanuel Zamora Gaviria | B77: NO | C77: SI | D77: SI | E77: NO | F77: NO | H77: 46057 | I77: Ausencia
A78: Juan Felipe Mateus | B78: NO | C78: SI | D78: NO | E78: NO | F78: NO | H78: 46128 | I78: Ausencia
A79: Edgar Felipe Gonzalez Carreño | B79: NO | C79: SI | D79: SI | E79: NO | F79: NO | H79: 46139
A80: Maria Alejandra Cubillos Castillo | B80: NO | C80: NO | D80: NO | E80: NO | F80: NO | H80: 45782
A81: Sandra Daniela Bocanegra Vera | B81: NO | C81: NO | D81: NO | E81: SI | F81: NO | H81: 45901
A82: Laura Camila Vega Rubiano | B82: NO | C82: NO | D82: SI | E82: SI | F82: NO | H82: 45786
A83: Andrea Veronica Chavez Ramos | B83: NO | C83: SI | D83: NO | E83: SI | F83: NO | H83: 46102
A84: Maria Fernanda Salamanca Briceño | B84: SI | D84: NO | E84: NO | F84: NO | H84: 45839
A85: Nasly Katerine Martinez Niño | B85: SI | C85: SI
A86: Luisa Fernanda Velosa Roncancio | B86: SI | C86: SI | D86: NO | E86: NO | F86: NO | H86: 45839
A87: PERSONAS SIN REGISTRO | E87: =COUNTIF(E2:E84,"NO") -> 59
U88: ALEJANDRA CUBILLOS | V88: ya esta en s2 rapi
U89: DAYANA CARVAJAL | V89: ya esta en s2 rapi
U90: GERMAN MAURICIO | V90: ya esta en s2 rapi
U91: LAURA PENAGOS | V91: ya esta en s2 rapi
U92: SANDY MENDIETA | V92: ya esta en s2 rapi
B93: NOMBRE | C93: CARTERA | D93: TLJ | E93: TL | F93: LIDER | H93: NOMBRE SISTEMA | I93: EJECUTIVO | J93: CC | U93: PAULA RAMIREZ | V93: ya esta en s2 ok
B94: BRAYAN RINCON | C94: S1 OKDINERO | D94: KATHERINE PARDO | E94: JOSE SANCHEZ | F94: JOSE SANCHEZ | H94: JUAN MONTENEGRO | I94: JUAN PABLO LANCHEROS MONTENEGRO | J94: 1069759144 | U94: MICHELLE RODRIGUEZ | V94: ya esta en s2 ok
B95: LEIDY TORRES | H95: DANI CAMACHO1 | I95: Daniela Camacho Guerrero | J95: 1074526378 | U95: DANIEL AVILA | V95: ya esta en s2 ok
B96: JULIETH VARGAS | H96: CAROL LARROTA | I96: CAROL JULIETH LARROTA SOTO | J96: 1000833623 | U96: JUAN MATEUS | V96: ya esta en s2 ok
B97: PAULA GUTIERREZ | H97: JULIAN KUHNE | I97: JULIAN DAVID ARANGO KUHNE | J97: 1021395581 | U97: MIGUEL ZULETA | V97: esta en s1 ok
B98: EDGAR FELIPE GONZALEZ | H98: TATIANA BARINAS | I98: TATIANA MARCELA BARINAS ROBLES | J98: 1033100219 | U98: MATEO DOMINGUEZ | V98: ya esta en s2 ok
B99: NICOL BARRIOS | H99: SARA DIAZ | I99: SARA DIAZ | J99: 1033720732 | U99: KEVIN SEBASTIAN MURILLO | V99: ya esta en s2 ok
B100: DANIELA ALDANA | H100: MARIANA CORTES | I100: MARIANA CORTES HELMSDORFF | J100: 1027281784 | U100: PAULA RODRIGUEZ | V100: ya esta en s2 cash
...

Sheet RANKING
E2: Fecha | F2: =NOW() -> 46324.461 | G2: Grupo | H2: S1 CASHMAX | J2: TLJ | K2: MATEO CANO | N2: % DEVOLUCIÓN | O2: %FALTA META | R2: https://cs.cashimax.com/indexBack
E3: RANKING COMISION | G3: ASIGNACIÓN | H3: =SUM(F5:F26) -> #N/A | I3: RECUADO | J3: RECAUDO | K3: =SUM(H5:H26) -> #N/A | N3: ='COMISION STAFF'!M3 -> #N/A | O3: ='COMISION STAFF'!N3 -> #N/A | AB3: OK S1 KATHE | AF3: OK S1 EVELIN | AJ3: OK S1 MARULANDA
E4: ASESOR | F4: Asignacion | G4: Cuentas | H4: Recaudo | I4: %_Meta | J4: % RECUPERADO | K4: TOP | N4: SIGUIENTE PISO | O4: BONO | P4: DOMINGO 1 | Q4: DOMINGO 2 | R4: DOMINGO 3 | S4: R DOMINGO 1 | T4: R DOMINGO 2 | U4: R DOMINGO 3 | V4: FESTIVO 1 | W4: R FESTIVO 1 | X4: DOMINGO 3 | AB4: ASESOR | AC4: ASIGNACION | AD4: RECAUDO | AF4: ASESOR | AG4: ASIGNACION | AH4: RECUADO | AJ4: ASESOR | AK4: ASIGNACION | AL4: RECAUDO
F5: =VLOOKUP(E5,'ASIGNACION RANKING'!D:AB,7,0) -> #N/A | G5: =VLOOKUP(E5,'ASIGNACION RANKING'!D:AB,6,0) -> #N/A | H5: =VLOOKUP(E5,'ASIGNACION RANKING'!D:AB,11,0) -> #N/A | I5: 11.12 | J5: =H5/F5 -> #N/A | K5: 1 | N5: =(H5+(H5*10%))-H5 -> #N/A | O5: 1400000 | P5: =VLOOKUP(E5,'DOMINGO 1'!D:AB,7,0) -> #N/A | Q5: =VLOOKUP(E5,'DOMINGO 2'!D:AB,7,0) -> #N/A | R5: =VLOOKUP(E5,'DOMINGO 3'!D:AB,7,0) -> #N/A | S5: =VLOOKUP(E5,'DOMINGO 1'!D:AB,11,0) -> #N/A | T5: =VLOOKUP(E5,'DOMINGO 2'!D:AB,11,0) -> #N/A | U5: =VLOOKUP(E5,'DOMINGO 3'!D:AB,11,0) -> #N/A | V5: =VLOOKUP(E5,'FESTIVO 1'!D:AB,7,0) -> #N/A | W5: =VLOOKUP(E5,'FESTIVO 1'!D:AB,11,0) -> #N/A | AB5: A0258(CRIS URREGO) | AC5: =VLOOKUP(AB5,E:O,2,0) -> 1500967 | AD5: =VLOOKUP(AB5,E:O,4,0) -> 139570 | AF5: A0144(DANIEL HERNANDEZ) | AG5: =VLOOKUP(AF5,E:O,2,0) -> 1462441 | AH5: =VLOOKUP(AF5,E:O,4,0) -> 125888 | AJ5: A0151(ALISSON CARRERO) | AK5: =VLOOKUP(AJ5,E:O,2,0) -> 1291435 | AL5: =VLOOKUP(AJ5,E:O,4,0) -> 108491
F6: =VLOOKUP(E6,'ASIGNACION RANKING'!D:AB,7,0) -> #N/A | G6: =VLOOKUP(E6,'ASIGNACION RANKING'!D:AB,6,0) -> #N/A | H6: =VLOOKUP(E6,'ASIGNACION RANKING'!D:AB,11,0) -> #N/A | I6: 16.12 | J6: =H6/F6 -> #N/A | K6: 2 | N6: =F6*J5-H6 -> #N/A | O6: 1200000 | P6: =VLOOKUP(E6,'DOMINGO 1'!D:AB,7,0) -> #N/A | Q6: =VLOOKUP(E6,'DOMINGO 2'!D:AB,7,0) -> #N/A | R6: =VLOOKUP(E6,'DOMINGO 3'!D:AB,7,0) -> #N/A | S6: =VLOOKUP(E6,'DOMINGO 1'!D:AB,11,0) -> #N/A | T6: =VLOOKUP(E6,'DOMINGO 2'!D:AB,11,0) -> #N/A | U6: =VLOOKUP(E6,'DOMINGO 3'!D:AB,11,0) -> #N/A | V6: =VLOOKUP(E6,'FESTIVO 1'!D:AB,7,0) -> #N/A | W6: =VLOOKUP(E6,'FESTIVO 1'!D:AB,11,0) -> #N/A | AB6: A0221(DAVID GOMEZ) | AC6: =VLOOKUP(AB6,E:O,2,0) -> 1452433 | AD6: =VLOOKUP(AB6,E:O,4,0) -> 144565 | AF6: A0249(DANIEL MAYORGA) | AG6: =VLOOKUP(AF6,E:O,2,0) -> 1375501 | AH6: =VLOOKUP(AF6,E:O,4,0) -> 120001 | AJ6: A0383(ALISSON MACIAS) | AK6: =VLOOKUP(AJ6,E:O,2,0) -> 1375082 | AL6: =VLOOKUP(AJ6,E:O,4,0) -> 153894
F7: =VLOOKUP(E7,'ASIGNACION RANKING'!D:AB,7,0) -> #N/A | G7: =VLOOKUP(E7,'ASIGNACION RANKING'!D:AB,6,0) -> #N/A | H7: =VLOOKUP(E7,'ASIGNACION RANKING'!D:AB,11,0) -> #N/A | J7: =H7/F7 -> #N/A | K7: 3 | N7: =F7*J6-H7 -> #N/A | O7: 1000000 | P7: =VLOOKUP(E7,'DOMINGO 1'!D:AB,7,0) -> #N/A | Q7: =VLOOKUP(E7,'DOMINGO 2'!D:AB,7,0) -> #N/A | R7: =VLOOKUP(E7,'DOMINGO 3'!D:AB,7,0) -> #N/A | S7: =VLOOKUP(E7,'DOMINGO 1'!D:AB,11,0) -> #N/A | T7: =VLOOKUP(E7,'DOMINGO 2'!D:AB,11,0) -> #N/A | U7: =VLOOKUP(E7,'DOMINGO 3'!D:AB,11,0) -> #N/A | V7: =VLOOKUP(E7,'FESTIVO 1'!D:AB,7,0) -> #N/A | W7: =VLOOKUP(E7,'FESTIVO 1'!D:AB,11,0) -> #N/A | AB7: A0288(FABIAN STIVEN) | AC7: =VLOOKUP(AB7,E:O,2,0) -> 1435695 | AD7: =VLOOKUP(AB7,E:O,4,0) -> 136800 | AF7: A0220(HEIDY AGUILAR) | AG7: =VLOOKUP(AF7,E:O,2,0) -> 855025 | AH7: =VLOOKUP(AF7,E:O,4,0) -> 56936 | AJ7: A0197(ASLE PERLAZA) | AK7: =VLOOKUP(AJ7,E:O,2,0) -> 1437376 | AL7: =VLOOKUP(AJ7,E:O,4,0) -> 140701
F8: =VLOOKUP(E8,'ASIGNACION RANKING'!D:AB,7,0) -> #N/A | G8: =VLOOKUP(E8,'ASIGNACION RANKING'!D:AB,6,0) -> #N/A | H8: =VLOOKUP(E8,'ASIGNACION RANKING'!D:AB,11,0) -> #N/A | J8: =H8/F8 -> #N/A | K8: 4 | N8: =F8*J7-H8 -> #N/A | O8: 800000 | P8: =VLOOKUP(E8,'DOMINGO 1'!D:AB,7,0) -> #N/A | Q8: =VLOOKUP(E8,'DOMINGO 2'!D:AB,7,0) -> #N/A | R8: =VLOOKUP(E8,'DOMINGO 3'!D:AB,7,0) -> #N/A | S8: =VLOOKUP(E8,'DOMINGO 1'!D:AB,11,0) -> #N/A | T8: =VLOOKUP(E8,'DOMINGO 2'!D:AB,11,0) -> #N/A | U8: =VLOOKUP(E8,'DOMINGO 3'!D:AB,11,0) -> #N/A | V8: =VLOOKUP(E8,'FESTIVO 1'!D:AB,7,0) -> #N/A | W8: =VLOOKUP(E8,'FESTIVO 1'!D:AB,11,0) -> #N/A | AB8: A0477(KAREN MARTINEZ) | AC8: =VLOOKUP(AB8,E:O,2,0) -> 259355 | AD8: =VLOOKUP(AB8,E:O,4,0) -> 15460 | AF8: A0401(HELLEN MARIN) | AG8: =VLOOKUP(AF8,E:O,2,0) -> 1245278 | AH8: =VLOOKUP(AF8,E:O,4,0) -> 116256 | AJ8: A0346(CATA TAMARA) | AK8: =VLOOKUP(AJ8,E:O,2,0) -> 1235282 | AL8: =VLOOKUP(AJ8,E:O,4,0) -> 130801
F9: =VLOOKUP(E9,'ASIGNACION RANKING'!D:AB,7,0) -> #N/A | G9: =VLOOKUP(E9,'ASIGNACION RANKING'!D:AB,6,0) -> #N/A | H9: =VLOOKUP(E9,'ASIGNACION RANKING'!D:AB,11,0) -> #N/A | J9: =H9/F9 -> #N/A | K9: 5 | N9: =F9*J8-H9 -> #N/A | O9: 600000 | P9: =VLOOKUP(E9,'DOMINGO 1'!D:AB,7,0) -> #N/A | Q9: =VLOOKUP(E9,'DOMINGO 2'!D:AB,7,0) -> #N/A | R9: =VLOOKUP(E9,'DOMINGO 3'!D:AB,7,0) -> #N/A | S9: =VLOOKUP(E9,'DOMINGO 1'!D:AB,11,0) -> #N/A | T9: =VLOOKUP(E9,'DOMINGO 2'!D:AB,11,0) -> #N/A | U9: =VLOOKUP(E9,'DOMINGO 3'!D:AB,11,0) -> #N/A | V9: =VLOOKUP(E9,'FESTIVO 1'!D:AB,7,0) -> #N/A | W9: =VLOOKUP(E9,'FESTIVO 1'!D:AB,11,0) -> #N/A | AB9: A0128(LEIDY TORRES) | AC9: =VLOOKUP(AB9,E:O,2,0) -> 1472361 | AD9: =VLOOKUP(AB9,E:O,4,0) -> 125496 | AF9: A0276(KAROLL FERNANDEZ) | AG9: =VLOOKUP(AF9,E:O,2,0) -> 1336105 | AH9: =VLOOKUP(AF9,E:O,4,0) -> 98319 | AJ9: A0161(E MACIAS) | AK9: =VLOOKUP(AJ9,E:O,2,0) -> 1383549 | AL9: =VLOOKUP(AJ9,E:O,4,0) -> 115577
F10: =VLOOKUP(E10,'ASIGNACION RANKING'!D:AB,7,0) -> #N/A | G10: =VLOOKUP(E10,'ASIGNACION RANKING'!D:AB,6,0) -> #N/A | H10: =VLOOKUP(E10,'ASIGNACION RANKING'!D:AB,11,0) -> #N/A | J10: =H10/F10 -> #N/A | K10: 6 | N10: =F10*J9-H10 -> #N/A | O10: 500000 | P10: =VLOOKUP(E10,'DOMINGO 1'!D:AB,7,0) -> #N/A | Q10: =VLOOKUP(E10,'DOMINGO 2'!D:AB,7,0) -> #N/A | R10: =VLOOKUP(E10,'DOMINGO 3'!D:AB,7,0) -> #N/A | S10: =VLOOKUP(E10,'DOMINGO 1'!D:AB,11,0) -> #N/A | T10: =VLOOKUP(E10,'DOMINGO 2'!D:AB,11,0) -> #N/A | U10: =VLOOKUP(E10,'DOMINGO 3'!D:AB,11,0) -> #N/A | V10: =VLOOKUP(E10,'FESTIVO 1'!D:AB,7,0) -> #N/A | W10: =VLOOKUP(E10,'FESTIVO 1'!D:AB,11,0) -> #N/A | AB10: A0447(LORENA SALGADO) | AC10: =VLOOKUP(AB10,E:O,2,0) -> 1479191 | AD10: =VLOOKUP(AB10,E:O,4,0) -> 132105 | AF10: A0363(Kevin Martinez) | AG10: =VLOOKUP(AF10,E:O,2,0) -> 1132129 | AH10: =VLOOKUP(AF10,E:O,4,0) -> 126847 | AJ10: A0216(JAVIER GIL) | AK10: =VLOOKUP(AJ10,E:O,2,0) -> 1507262 | AL10: =VLOOKUP(AJ10,E:O,4,0) -> 122286
F11: =VLOOKUP(E11,'ASIGNACION RANKING'!D:AB,7,0) -> #N/A | G11: =VLOOKUP(E11,'ASIGNACION RANKING'!D:AB,6,0) -> #N/A | H11: =VLOOKUP(E11,'ASIGNACION RANKING'!D:AB,11,0) -> #N/A | I11: 18.12 | J11: =H11/F11 -> #N/A | K11: 7 | N11: =F11*J10-H11 -> #N/A | O11: 400000 | P11: =VLOOKUP(E11,'DOMINGO 1'!D:AB,7,0) -> #N/A | Q11: =VLOOKUP(E11,'DOMINGO 2'!D:AB,7,0) -> #N/A | R11: =VLOOKUP(E11,'DOMINGO 3'!D:AB,7,0) -> #N/A | S11: =VLOOKUP(E11,'DOMINGO 1'!D:AB,11,0) -> #N/A | T11: =VLOOKUP(E11,'DOMINGO 2'!D:AB,11,0) -> #N/A | U11: =VLOOKUP(E11,'DOMINGO 3'!D:AB,11,0) -> #N/A | V11: =VLOOKUP(E11,'FESTIVO 1'!D:AB,7,0) -> #N/A | W11: =VLOOKUP(E11,'FESTIVO 1'!D:AB,11,0) -> #N/A | AB11: A0388(MICHAEL BARRIOS) | AC11: =VLOOKUP(AB11,E:O,2,0) -> 1739074 | AD11: =VLOOKUP(AB11,E:O,4,0) -> 118450 | AF11: A0022(Lorena Portacio) | AG11: =VLOOKUP(AF11,E:O,2,0) -> 1333664 | AH11: =VLOOKUP(AF11,E:O,4,0) -> 113219 | AJ11: A0044(JOHAN CASTILLO) | AK11: =VLOOKUP(AJ11,E:O,2,0) -> 1425071 | AL11: =VLOOKUP(AJ11,E:O,4,0) -> 137147
F12: =VLOOKUP(E12,'ASIGNACION RANKING'!D:AB,7,0) -> #N/A | G12: =VLOOKUP(E12,'ASIGNACION RANKING'!D:AB,6,0) -> #N/A | H12: =VLOOKUP(E12,'ASIGNACION RANKING'!D:AB,11,0) -> #N/A | I12: 7.12 | J12: =H12/F12 -> #N/A | K12: 8 | N12: =F12*J11-H12 -> #N/A | O12: 300000 | P12: =VLOOKUP(E12,'DOMINGO 1'!D:AB,7,0) -> #N/A | Q12: =VLOOKUP(E12,'DOMINGO 2'!D:AB,7,0) -> #N/A | R12: =VLOOKUP(E12,'DOMINGO 3'!D:AB,7,0) -> #N/A | S12: =VLOOKUP(E12,'DOMINGO 1'!D:AB,11,0) -> #N/A | T12: =VLOOKUP(E12,'DOMINGO 2'!D:AB,11,0) -> #N/A | U12: =VLOOKUP(E12,'DOMINGO 3'!D:AB,11,0) -> #N/A | V12: =VLOOKUP(E12,'FESTIVO 1'!D:AB,7,0) -> #N/A | W12: =VLOOKUP(E12,'FESTIVO 1'!D:AB,11,0) -> #N/A | AB12: A0096(NATALYA PACHECO) | AC12: =VLOOKUP(AB12,E:O,2,0) -> 1461424 | AD12: =VLOOKUP(AB12,E:O,4,0) -> 129461 | AF12: A0456(MELISSA FONQUE) | AG12: =VLOOKUP(AF12,E:O,2,0) -> 1486332 | AH12: =VLOOKUP(AF12,E:O,4,0) -> 116375 | AJ12: A0134(Jessica Fernanda Porras) | AK12: =VLOOKUP(AJ12,E:O,2,0) -> 1467542 | AL12: =VLOOKUP(AJ12,E:O,4,0) -> 129009
F13: =VLOOKUP(E13,'ASIGNACION RANKING'!D:AB,7,0) -> #N/A | G13: =VLOOKUP(E13,'ASIGNACION RANKING'!D:AB,6,0) -> #N/A | H13: =VLOOKUP(E13,'ASIGNACION RANKING'!D:AB,11,0) -> #N/A | J13: =H13/F13 -> #N/A | K13: 9 | N13: =F13*J12-H13 -> #N/A | O13: 180000 | P13: =VLOOKUP(E13,'DOMINGO 1'!D:AB,7,0) -> #N/A | Q13: =VLOOKUP(E13,'DOMINGO 2'!D:AB,7,0) -> #N/A | R13: =VLOOKUP(E13,'DOMINGO 3'!D:AB,7,0) -> #N/A | S13: =VLOOKUP(E13,'DOMINGO 1'!D:AB,11,0) -> #N/A | T13: =VLOOKUP(E13,'DOMINGO 2'!D:AB,11,0) -> #N/A | U13: =VLOOKUP(E13,'DOMINGO 3'!D:AB,11,0) -> #N/A | V13: =VLOOKUP(E13,'FESTIVO 1'!D:AB,7,0) -> #N/A | W13: =VLOOKUP(E13,'FESTIVO 1'!D:AB,11,0) -> #N/A | AB13: A0214(NEIDY FORERO ) | AC13: =VLOOKUP(AB13,E:O,2,0) -> 1387212 | AD13: =VLOOKUP(AB13,E:O,4,0) -> 112171 | AF13: A0072(MIGUEL GARCIA) | AG13: =VLOOKUP(AF13,E:O,2,0) -> 1266014 | AH13: =VLOOKUP(AF13,E:O,4,0) -> 144388 | AJ13: A0043(LAU SILVA) | AK13: =VLOOKUP(AJ13,E:O,2,0) -> 1460569 | AL13: =VLOOKUP(AJ13,E:O,4,0) -> 107350
F14: =VLOOKUP(E14,'ASIGNACION RANKING'!D:AB,7,0) -> #N/A | G14: =VLOOKUP(E14,'ASIGNACION RANKING'!D:AB,6,0) -> #N/A | H14: =VLOOKUP(E14,'ASIGNACION RANKING'!D:AB,11,0) -> #N/A | J14: =H14/F14 -> #N/A | K14: 10 | N14: =F14*J13-H14 -> #N/A | O14: 140000 | P14: =VLOOKUP(E14,'DOMINGO 1'!D:AB,7,0) -> #N/A | Q14: =VLOOKUP(E14,'DOMINGO 2'!D:AB,7,0) -> #N/A | R14: =VLOOKUP(E14,'DOMINGO 3'!D:AB,7,0) -> #N/A | S14: =VLOOKUP(E14,'DOMINGO 1'!D:AB,11,0) -> #N/A | T14: =VLOOKUP(E14,'DOMINGO 2'!D:AB,11,0) -> #N/A | U14: =VLOOKUP(E14,'DOMINGO 3'!D:AB,11,0) -> #N/A | V14: =VLOOKUP(E14,'FESTIVO 1'!D:AB,7,0) -> #N/A | W14: =VLOOKUP(E14,'FESTIVO 1'!D:AB,11,0) -> #N/A | AB14: A0444(NICOL AMEZQUITA) | AC14: =VLOOKUP(AB14,E:O,2,0) -> 1284679 | AD14: =VLOOKUP(AB14,E:O,4,0) -> 140635 | AF14: A0015(NATALY ROMERO) | AG14: =VLOOKUP(AF14,E:O,2,0) -> 1527864 | AH14: =VLOOKUP(AF14,E:O,4,0) -> 102324 | AJ14: A0305(NIK AVILA) | AK14: =VLOOKUP(AJ14,E:O,2,0) -> 1519818 | AL14: =VLOOKUP(AJ14,E:O,4,0) -> 117386
F15: =VLOOKUP(E15,'ASIGNACION RANKING'!D:AB,7,0) -> #N/A | G15: =VLOOKUP(E15,'ASIGNACION RANKING'!D:AB,6,0) -> #N/A | H15: =VLOOKUP(E15,'ASIGNACION RANKING'!D:AB,11,0) -> #N/A | J15: =H15/F15 -> #N/A | K15: 11 | N15: =F15*J14-H15 -> #N/A | O15: 120000 | P15: =VLOOKUP(E15,'DOMINGO 1'!D:AB,7,0) -> #N/A | Q15: =VLOOKUP(E15,'DOMINGO 2'!D:AB,7,0) -> #N/A | R15: =VLOOKUP(E15,'DOMINGO 3'!D:AB,7,0) -> #N/A | S15: =VLOOKUP(E15,'DOMINGO 1'!D:AB,11,0) -> #N/A | T15: =VLOOKUP(E15,'DOMINGO 2'!D:AB,11,0) -> #N/A | U15: =VLOOKUP(E15,'DOMINGO 3'!D:AB,11,0) -> #N/A | V15: =VLOOKUP(E15,'FESTIVO 1'!D:AB,7,0) -> #N/A | W15: =VLOOKUP(E15,'FESTIVO 1'!D:AB,11,0) -> #N/A | AB15: A0232(PAU ALDANA) | AC15: =VLOOKUP(AB15,E:O,2,0) -> 1319544 | AD15: =VLOOKUP(AB15,E:O,4,0) -> 111853 | AF15: A0263(NICOL MARQUEZ) | AG15: =VLOOKUP(AF15,E:O,2,0) -> 1406761 | AH15: =VLOOKUP(AF15,E:O,4,0) -> 140428 | AJ15: A0431(SEBASNTIAN PIRANQUIVE) | AK15: =VLOOKUP(AJ15,E:O,2,0) -> 1315254 | AL15: =VLOOKUP(AJ15,E:O,4,0) -> 122835
F16: =VLOOKUP(E16,'ASIGNACION RANKING'!D:AB,7,0) -> #N/A | G16: =VLOOKUP(E16,'ASIGNACION RANKING'!D:AB,6,0) -> #N/A | H16: =VLOOKUP(E16,'ASIGNACION RANKING'!D:AB,11,0) -> #N/A | I16: 2.12 | J16: =H16/F16 -> #N/A | K16: 12 | N16: =F16*J15-H16 -> #N/A | O16: 110000 | P16: =VLOOKUP(E16,'DOMINGO 1'!D:AB,7,0) -> #N/A | Q16: =VLOOKUP(E16,'DOMINGO 2'!D:AB,7,0) -> #N/A | R16: =VLOOKUP(E16,'DOMINGO 3'!D:AB,7,0) -> #N/A | S16: =VLOOKUP(E16,'DOMINGO 1'!D:AB,11,0) -> #N/A | T16: =VLOOKUP(E16,'DOMINGO 2'!D:AB,11,0) -> #N/A | U16: =VLOOKUP(E16,'DOMINGO 3'!D:AB,11,0) -> #N/A | V16: =VLOOKUP(E16,'FESTIVO 1'!D:AB,7,0) -> #N/A | W16: =VLOOKUP(E16,'FESTIVO 1'!D:AB,11,0) -> #N/A | AB16: PAULAG08(PAULA GUTIERREZ) | AC16: =VLOOKUP(AB16,E:O,2,0) -> 1515113 | AD16: =VLOOKUP(AB16,E:O,4,0) -> 116069 | AF16: A0017(NICOLARY MONTES) | AG16: =VLOOKUP(AF16,E:O,2,0) -> 1399846 | AH16: =VLOOKUP(AF16,E:O,4,0) -> 123297 | AJ16: A0201(SHARON PRIETO) | AK16: =VLOOKUP(AJ16,E:O,2,0) -> 1253367 | AL16: =VLOOKUP(AJ16,E:O,4,0) -> 129007
F17: =VLOOKUP(E17,'ASIGNACION RANKING'!D:AB,7,0) -> #N/A | G17: =VLOOKUP(E17,'ASIGNACION RANKING'!D:AB,6,0) -> #N/A | H17: =VLOOKUP(E17,'ASIGNACION RANKING'!D:AB,11,0) -> #N/A | I17: 8.12 | J17: =H17/F17 -> #N/A | K17: 13 | N17: =F17*J16-H17 -> #N/A | O17: 100000 | P17: =VLOOKUP(E17,'DOMINGO 1'!D:AB,7,0) -> #N/A | Q17: =VLOOKUP(E17,'DOMINGO 2'!D:AB,7,0) -> #N/A | R17: =VLOOKUP(E17,'DOMINGO 3'!D:AB,7,0) -> #N/A | S17: =VLOOKUP(E17,'DOMINGO 1'!D:AB,11,0) -> #N/A | T17: =VLOOKUP(E17,'DOMINGO 2'!D:AB,11,0) -> #N/A | U17: =VLOOKUP(E17,'DOMINGO 3'!D:AB,11,0) -> #N/A | V17: =VLOOKUP(E17,'FESTIVO 1'!D:AB,7,0) -> #N/A | W17: =VLOOKUP(E17,'FESTIVO 1'!D:AB,11,0) -> #N/A | AB17: A0222(PIPE GONZALEZ) | AC17: =VLOOKUP(AB17,E:O,2,0) -> 1498819 | AD17: =VLOOKUP(AB17,E:O,4,0) -> 137211 | AF17: A0339(RAFAEL NUÑEZ) | AG17: =VLOOKUP(AF17,E:O,2,0) -> 1658753 | AH17: =VLOOKUP(AF17,E:O,4,0) -> 116679 | AJ17: A0098(XIMENA BARRETO) | AK17: =VLOOKUP(AJ17,E:O,2,0) -> 1616383 | AL17: =VLOOKUP(AJ17,E:O,4,0) -> 118908
F18: =VLOOKUP(E18,'ASIGNACION RANKING'!D:AB,7,0) -> #N/A | G18: =VLOOKUP(E18,'ASIGNACION RANKING'!D:AB,6,0) -> #N/A | H18: =VLOOKUP(E18,'ASIGNACION RANKING'!D:AB,11,0) -> #N/A | I18: 12.12 | J18: =H18/F18 -> #N/A | K18: 14 | N18: =F18*J17-H18 -> #N/A | O18: 90000 | P18: =VLOOKUP(E18,'DOMINGO 1'!D:AB,7,0) -> #N/A | Q18: =VLOOKUP(E18,'DOMINGO 2'!D:AB,7,0) -> #N/A | R18: =VLOOKUP(E18,'DOMINGO 3'!D:AB,7,0) -> #N/A | S18: =VLOOKUP(E18,'DOMINGO 1'!D:AB,11,0) -> #N/A | T18: =VLOOKUP(E18,'DOMINGO 2'!D:AB,11,0) -> #N/A | U18: =VLOOKUP(E18,'DOMINGO 3'!D:AB,11,0) -> #N/A | V18: =VLOOKUP(E18,'FESTIVO 1'!D:AB,7,0) -> #N/A | W18: =VLOOKUP(E18,'FESTIVO 1'!D:AB,11,0) -> #N/A | AB18: A0119(WILL) | AC18: =VLOOKUP(AB18,E:O,2,0) -> 1146747 | AD18: =VLOOKUP(AB18,E:O,4,0) -> 147681 | AF18: A0459(SEBASTIAN MONTOYA) | AG18: =VLOOKUP(AF18,E:O,2,0) -> 1345720 | AH18: =VLOOKUP(AF18,E:O,4,0) -> 104448 | AJ18: A0114(YINETH LOPEZ) | AK18: =VLOOKUP(AJ18,E:O,2,0) -> 1742816 | AL18: =VLOOKUP(AJ18,E:O,4,0) -> 94197
F19: =VLOOKUP(E19,'ASIGNACION RANKING'!D:AB,7,0) -> #N/A | G19: =VLOOKUP(E19,'ASIGNACION RANKING'!D:AB,6,0) -> #N/A | H19: =VLOOKUP(E19,'ASIGNACION RANKING'!D:AB,11,0) -> #N/A | J19: =H19/F19 -> #N/A | K19: 15 | N19: =F19*J18-H19 -> #N/A | O19: 80000 | P19: =VLOOKUP(E19,'DOMINGO 1'!D:AB,7,0) -> #N/A | Q19: =VLOOKUP(E19,'DOMINGO 2'!D:AB,7,0) -> #N/A | R19: =VLOOKUP(E19,'DOMINGO 3'!D:AB,7,0) -> #N/A | S19: =VLOOKUP(E19,'DOMINGO 1'!D:AB,11,0) -> #N/A | T19: =VLOOKUP(E19,'DOMINGO 2'!D:AB,11,0) -> #N/A | U19: =VLOOKUP(E19,'DOMINGO 3'!D:AB,11,0) -> #N/A | V19: =VLOOKUP(E19,'FESTIVO 1'!D:AB,7,0) -> #N/A | W19: =VLOOKUP(E19,'FESTIVO 1'!D:AB,11,0) -> #N/A | AB19: A0438(YULI CASTRO) | AC19: =VLOOKUP(AB19,E:O,2,0) -> 1607058 | AD19: =VLOOKUP(AB19,E:O,4,0) -> 123368 | AF19: A0122(Sara Cortez) | AG19: =VLOOKUP(AF19,E:O,2,0) -> 1944095 | AH19: =VLOOKUP(AF19,E:O,4,0) -> 112869 | AJ19: A0125(YULI LEON) | AK19: =VLOOKUP(AJ19,E:O,2,0) -> 1328516 | AL19: =VLOOKUP(AJ19,E:O,4,0) -> 180893
F20: =VLOOKUP(E20,'ASIGNACION RANKING'!D:AB,7,0) -> #N/A | G20: =VLOOKUP(E20,'ASIGNACION RANKING'!D:AB,6,0) -> #N/A | H20: =VLOOKUP(E20,'ASIGNACION RANKING'!D:AB,11,0) -> #N/A | J20: =H20/F20 -> #N/A | K20: 16 | N20: =F20*J19-H20 -> #N/A | O20: 70000 | P20: =VLOOKUP(E20,'DOMINGO 1'!D:AB,7,0) -> #N/A | Q20: =VLOOKUP(E20,'DOMINGO 2'!D:AB,7,0) -> #N/A | R20: =VLOOKUP(E20,'DOMINGO 3'!D:AB,7,0) -> #N/A | S20: =VLOOKUP(E20,'DOMINGO 1'!D:AB,11,0) -> #N/A | T20: =VLOOKUP(E20,'DOMINGO 2'!D:AB,11,0) -> #N/A | U20: =VLOOKUP(E20,'DOMINGO 3'!D:AB,11,0) -> #N/A | V20: =VLOOKUP(E20,'FESTIVO 1'!D:AB,7,0) -> #N/A | W20: =VLOOKUP(E20,'FESTIVO 1'!D:AB,11,0) -> #N/A | AB20: TOTAL | AC20: =SUM(AC5:AC19) -> 20559672 | AD20: =SUM(AD5:AD19) -> 1830895 | AF20: TOTAL | AG20: =SUM(AG5:AG19) -> 20775528 | AH20: =SUM(AH5:AH19) -> 1718274 | AJ20: TOTAL | AK20: =SUM(AK5:AK19) -> 21359322 | AL20: =SUM(AL5:AL19) -> 1908482
F21: =VLOOKUP(E21,'ASIGNACION RANKING'!D:AB,7,0) -> #N/A | G21: =VLOOKUP(E21,'ASIGNACION RANKING'!D:AB,6,0) -> #N/A | H21: =VLOOKUP(E21,'ASIGNACION RANKING'!D:AB,11,0) -> #N/A | J21: =H21/F21 -> #N/A | K21: 17 | N21: =F21*J20-H21 -> #N/A | O21: 70000 | P21: =VLOOKUP(E21,'DOMINGO 1'!D:AB,7,0) -> #N/A | Q21: =VLOOKUP(E21,'DOMINGO 2'!D:AB,7,0) -> #N/A | R21: =VLOOKUP(E21,'DOMINGO 3'!D:AB,7,0) -> #N/A | S21: =VLOOKUP(E21,'DOMINGO 1'!D:AB,11,0) -> #N/A | T21: =VLOOKUP(E21,'DOMINGO 2'!D:AB,11,0) -> #N/A | U21: =VLOOKUP(E21,'DOMINGO 3'!D:AB,11,0) -> #N/A | V21: =VLOOKUP(E21,'FESTIVO 1'!D:AB,7,0) -> #N/A | W21: =VLOOKUP(E21,'FESTIVO 1'!D:AB,11,0) -> #N/A | AB21: =AD20/AC20 -> 0.089052734 | AF21: =AH20/AG20 -> 0.082706634 | AJ21: =AL20/AK20 -> 0.089351244
F22: =VLOOKUP(E22,'ASIGNACION RANKING'!D:AB,7,0) -> #N/A | G22: =VLOOKUP(E22,'ASIGNACION RANKING'!D:AB,6,0) -> #N/A | H22: =VLOOKUP(E22,'ASIGNACION RANKING'!D:AB,11,0) -> #N/A | J22: =H22/F22 -> #N/A | K22: 18 | N22: =F22*J21-H22 -> #N/A | O22: 60000 | P22: =VLOOKUP(E22,'DOMINGO 1'!D:AB,7,0) -> #N/A | Q22: =VLOOKUP(E22,'DOMINGO 2'!D:AB,7,0) -> #N/A | R22: =VLOOKUP(E22,'DOMINGO 3'!D:AB,7,0) -> #N/A | S22: =VLOOKUP(E22,'DOMINGO 1'!D:AB,11,0) -> #N/A | T22: =VLOOKUP(E22,'DOMINGO 2'!D:AB,11,0) -> #N/A | U22: =VLOOKUP(E22,'DOMINGO 3'!D:AB,11,0) -> #N/A | V22: =VLOOKUP(E22,'FESTIVO 1'!D:AB,7,0) -> #N/A | W22: =VLOOKUP(E22,'FESTIVO 1'!D:AB,11,0) -> #N/A | AC22: =(AC20*9%)-AD20 -> 19475.48
F23: =VLOOKUP(E23,'ASIGNACION RANKING'!D:AB,7,0) -> #N/A | G23: =VLOOKUP(E23,'ASIGNACION RANKING'!D:AB,6,0) -> #N/A | H23: =VLOOKUP(E23,'ASIGNACION RANKING'!D:AB,11,0) -> #N/A | I23: 20.12 | J23: =H23/F23 -> #N/A | K23: 19 | N23: =F23*J22-H23 -> #N/A | O23: 60000 | P23: =VLOOKUP(E23,'DOMINGO 1'!D:AB,7,0) -> #N/A | Q23: =VLOOKUP(E23,'DOMINGO 2'!D:AB,7,0) -> #N/A | R23: =VLOOKUP(E23,'DOMINGO 3'!D:AB,7,0) -> #N/A | S23: =VLOOKUP(E23,'DOMINGO 1'!D:AB,11,0) -> #N/A | T23: =VLOOKUP(E23,'DOMINGO 2'!D:AB,11,0) -> #N/A | U23: =VLOOKUP(E23,'DOMINGO 3'!D:AB,11,0) -> #N/A | V23: =VLOOKUP(E23,'FESTIVO 1'!D:AB,7,0) -> #N/A | W23: =VLOOKUP(E23,'FESTIVO 1'!D:AB,11,0) -> #N/A
F24: =VLOOKUP(E24,'ASIGNACION RANKING'!D:AB,7,0) -> #N/A | G24: =VLOOKUP(E24,'ASIGNACION RANKING'!D:AB,6,0) -> #N/A | H24: =VLOOKUP(E24,'ASIGNACION RANKING'!D:AB,11,0) -> #N/A | J24: =H24/F24 -> #N/A | K24: 20 | N24: =F24*J23-H24 -> #N/A | O24: 50000 | P24: =VLOOKUP(E24,'DOMINGO 1'!D:AB,7,0) -> #N/A | Q24: =VLOOKUP(E24,'DOMINGO 2'!D:AB,7,0) -> #N/A | R24: =VLOOKUP(E24,'DOMINGO 3'!D:AB,7,0) -> #N/A | S24: =VLOOKUP(E24,'DOMINGO 1'!D:AB,11,0) -> #N/A | T24: =VLOOKUP(E24,'DOMINGO 2'!D:AB,11,0) -> #N/A | U24: =VLOOKUP(E24,'DOMINGO 3'!D:AB,11,0) -> #N/A | V24: =VLOOKUP(E24,'FESTIVO 1'!D:AB,7,0) -> #N/A | W24: =VLOOKUP(E24,'FESTIVO 1'!D:AB,11,0) -> #N/A
F25: =VLOOKUP(E25,'ASIGNACION RANKING'!D:AB,7,0) -> #N/A | G25: =VLOOKUP(E25,'ASIGNACION RANKING'!D:AB,6,0) -> #N/A | H25: =VLOOKUP(E25,'ASIGNACION RANKING'!D:AB,11,0) -> #N/A | I25: 4.12 | J25: =H25/F25 -> #N/A | K25: 21 | N25: =F25*J24-H25 -> #N/A | O25: 50000 | P25: =VLOOKUP(E25,'DOMINGO 1'!D:AB,7,0) -> #N/A | Q25: =VLOOKUP(E25,'DOMINGO 2'!D:AB,7,0) -> #N/A | R25: =VLOOKUP(E25,'DOMINGO 3'!D:AB,7,0) -> #N/A | S25: =VLOOKUP(E25,'DOMINGO 1'!D:AB,11,0) -> #N/A | T25: =VLOOKUP(E25,'DOMINGO 2'!D:AB,11,0) -> #N/A | U25: =VLOOKUP(E25,'DOMINGO 3'!D:AB,11,0) -> #N/A | V25: =VLOOKUP(E25,'FESTIVO 1'!D:AB,7,0) -> #N/A | W25: =VLOOKUP(E25,'FESTIVO 1'!D:AB,11,0) -> #N/A
F26: =VLOOKUP(E26,'ASIGNACION RANKING'!D:AB,7,0) -> #N/A | G26: =VLOOKUP(E26,'ASIGNACION RANKING'!D:AB,6,0) -> #N/A | H26: =VLOOKUP(E26,'ASIGNACION RANKING'!D:AB,11,0) -> #N/A | I26: 5.12 | J26: =H26/F26 -> #N/A | K26: 22 | N26: =F26*J25-H26 -> #N/A | O26: 40000 | P26: =VLOOKUP(E26,'DOMINGO 1'!D:AB,7,0) -> #N/A | Q26: =VLOOKUP(E26,'DOMINGO 2'!D:AB,7,0) -> #N/A | R26: =VLOOKUP(E26,'DOMINGO 3'!D:AB,7,0) -> #N/A | S26: =VLOOKUP(E26,'DOMINGO 1'!D:AB,11,0) -> #N/A | T26: =VLOOKUP(E26,'DOMINGO 2'!D:AB,11,0) -> #N/A | U26: =VLOOKUP(E26,'DOMINGO 3'!D:AB,11,0) -> #N/A | V26: =VLOOKUP(E26,'FESTIVO 1'!D:AB,7,0) -> #N/A | W26: =VLOOKUP(E26,'FESTIVO 1'!D:AB,11,0) -> #N/A
K27: 23 | N27: =F27*J26-H27 -> #N/A | O27: 40000 | P27: =VLOOKUP(E27,'DOMINGO 1'!D:AB,7,0) -> #N/A | Q27: =VLOOKUP(E27,'DOMINGO 2'!D:AB,7,0) -> #N/A | R27: 0 | S27: =VLOOKUP(E27,'DOMINGO 1'!D:AB,11,0) -> #N/A | T27: =VLOOKUP(E27,'DOMINGO 2'!D:AB,11,0) -> #N/A | V27: =VLOOKUP(E27,'FESTIVO 1'!D:AB,7,0) -> #N/A | W27: =VLOOKUP(E27,'FESTIVO 1'!D:AB,11,0) -> #N/A
AB28: OK S1 BERENICE HERNANDEZ | AF28: OK S1 SANTIAGO | AJ28: OK S1 DONOVAN
E29: Fecha | F29: =NOW() -> 46324.461 | G29: Grupo | H29: S1 OK DINERO | J29: TLJ | K29: KATHERINE PARDO | L29: TOTAL PERSONAS EN RANKING | N29: % DEVOLUCIÓN | O29: %FALTA META | Q29: https://cs.exprescredito.com/indexBack | AB29: ASESOR | AC29: ASIGNACION | AD29: RECAUDO | AF29: ASESOR | AG29: ASIGNACION | AH29: RECAUDO | AJ29: ASESOR | AK29: ASIGNACION | AL29: RECAUDO
E30: RANKING COMISION | G30: ASIGNACIÓN | H30: =SUM(F32:F53) -> 28381941 | I30: RECUADO | J30: RECAUDO | K30: =SUM(H32:H53) -> 3038910 | L30: 92 | N30: ='COMISION STAFF'!M70 -> 0.08564428 | O30: ='COMISION STAFF'!N70 -> 205903.5 | AB30: M0011(A CHACON) | AC30: =VLOOKUP(AB30,E:O,2,0) -> 1415840 | AD30: =VLOOKUP(AB30,E:O,4,0) -> 128804 | AF30: M0121(A ERANDY) | AG30: =VLOOKUP(AF30,E:O,2,0) -> 1236037 | AH30: =VLOOKUP(AF30,E:O,4,0) -> 134290 | AJ30: M0054(A CATALINA) | AK30: =VLOOKUP(AJ30,E:O,2,0) -> 1279043 | AL30: =VLOOKUP(AJ30,E:O,4,0) -> 129892
E31: ASESOR | F31: Asignacion | G31: Cuentas | H31: Recaudo | I31: %_Meta | J31: % RECUPERADO | K31: TOP | L31: %TASA | M31: CLASIFICACION | N31: SIGUIENTE PISO | O31: BONO | P31: DOMINGO 1 | Q31: DOMINGO 2 | R31: DOMINGO 3 | S31: R DOMINGO 1 | T31: R DOMINGO 2 | U31: R DOMINGO 3 | V31: FESTIVO 1 | W31: R FESTIVO 1 | X31: DOMINGO 3 | AB31: M0402(A CIANNI) | AC31: =VLOOKUP(AB31,E:O,2,0) -> 1604646 | AD31: =VLOOKUP(AB31,E:O,4,0) -> 107756 | AF31: M0259(A KARINA) | AG31: =VLOOKUP(AF31,E:O,2,0) -> 1539387 | AH31: =VLOOKUP(AF31,E:O,4,0) -> 128925 | AJ31: M0077(A DONOVAN) | AK31: =VLOOKUP(AJ31,E:O,2,0) -> 1344459 | AL31: =VLOOKUP(AJ31,E:O,4,0) -> 103734
E32: A0125(YULI LEON) | F32: =VLOOKUP(E32,'ASIGNACION RANKING'!D:AB,7,0)-P32-Q32 -> 1328516 | G32: =VLOOKUP(E32,'ASIGNACION RANKING'!D:AB,6,0) -> 871 | H32: =VLOOKUP(E32,'ASIGNACION RANKING'!D:AB,11,0)-S32-T32 -> 180893 | J32: =H32/F32 -> 0.1361617 | K32: 1 | L32: =K32/$L$30 -> 0.010869565 | M32: =IF(L32<=0.02,"A1",IF(L32<=0.04,"A2",IF(L32<=0.06,"A3",IF(L32<=0.08,"A4",IF(L32<=0.1,"A5",IF(L32<=0.16,"B1",IF(L32<=0.22,"B2",IF(L32<=0.28,"B3",IF(L32<=0.34,"B4",IF(L32<=0.4,"B5",IF(L32<=0.46,"B6",IF(L32<=0.52,"B7",IF(L32<=0.58,"B8",IF(L32<=0.64,"B9",IF(L32<=0.7,"B10",IF(L32<=1.1,"C0")))))))))))))))) -> A1 | N32: =(H109+(H109*10%))-H109 -> 11667.9 | O32: =IF(M32="A1",1650000,IF(M32="A2",1290000,IF(M32="A3",1020000,IF(M32="A4",810000,IF(M32="A5",650000,IF(M32="B1",520000,IF(M32="B2",420000,IF(M32="B3",330000,IF(M32="B4",270000,IF(M32="B5",210000,IF(M32="B6",170000,IF(M32="B7",150000,IF(M32="B8",130000,IF(M32="B9",100000,IF(M32="B10",60000,IF(M32="C0",0)))))))))))))))) -> 1650000 | P32: =VLOOKUP(E32,'DOMINGO 1'!D:AB,7,0) -> 114965 | Q32: =VLOOKUP(E32,'DOMINGO 2'!D:AB,7,0) -> 124713 | S32: =VLOOKUP(E32,'DOMINGO 1'!D:AB,11,0) -> 13414 | T32: =VLOOKUP(E32,'DOMINGO 2'!D:AB,11,0) -> 8038 | AB32: M0057(A DANI) | AC32: =VLOOKUP(AB32,E:O,2,0) -> 1405189 | AD32: =VLOOKUP(AB32,E:O,4,0) -> 107558 | AF32: M0115(A KRISTIN) | AG32: =VLOOKUP(AF32,E:O,2,0) -> 1317832 | AH32: =VLOOKUP(AF32,E:O,4,0) -> 90122 | AJ32: M0384(A EMILY) | AK32: =VLOOKUP(AJ32,E:O,2,0) -> 1558271 | AL32: =VLOOKUP(AJ32,E:O,4,0) -> 118723
E33: M0310(A YEREMI) | F33: =VLOOKUP(E33,'ASIGNACION RANKING'!D:AB,7,0)-P33-Q33 -> 1187176 | G33: =VLOOKUP(E33,'ASIGNACION RANKING'!D:AB,6,0) -> 813 | H33: =VLOOKUP(E33,'ASIGNACION RANKING'!D:AB,11,0)-S33-T33 -> 160126 | J33: =H33/F33 -> 0.13487975 | K33: 2 | L33: =K33/$L$30 -> 0.02173913 | M33: =IF(L33<=0.02,"A1",IF(L33<=0.04,"A2",IF(L33<=0.06,"A3",IF(L33<=0.08,"A4",IF(L33<=0.1,"A5",IF(L33<=0.16,"B1",IF(L33<=0.22,"B2",IF(L33<=0.28,"B3",IF(L33<=0.34,"B4",IF(L33<=0.4,"B5",IF(L33<=0.46,"B6",IF(L33<=0.52,"B7",IF(L33<=0.58,"B8",IF(L33<=0.64,"B9",IF(L33<=0.7,"B10",IF(L33<=1.1,"C0")))))))))))))))) -> A2 | N33: =F33*J32-H33 -> 1521.905 | O33: =IF(M33="A1",1650000,IF(M33="A2",1290000,IF(M33="A3",1020000,IF(M33="A4",810000,IF(M33="A5",650000,IF(M33="B1",520000,IF(M33="B2",420000,IF(M33="B3",330000,IF(M33="B4",270000,IF(M33="B5",210000,IF(M33="B6",170000,IF(M33="B7",150000,IF(M33="B8",130000,IF(M33="B9",100000,IF(M33="B10",60000,IF(M33="C0",0)))))))))))))))) -> 1290000 | P33: =VLOOKUP(E33,'DOMINGO 1'!D:AB,7,0) -> 116987 | Q33: =VLOOKUP(E33,'DOMINGO 2'!D:AB,7,0) -> 88825 | R33: =VLOOKUP(E33,'DOMINGO 3'!D:AB,7,0) -> #N/A | S33: =VLOOKUP(E33,'DOMINGO 1'!D:AB,11,0) -> 4728 | T33: =VLOOKUP(E33,'DOMINGO 2'!D:AB,11,0) -> 6336 | U33: =VLOOKUP(E33,'DOMINGO 3'!D:AB,11,0) -> #N/A | V33: =VLOOKUP(E33,'FESTIVO 1'!D:AB,7,0) -> 123782 | W33: =VLOOKUP(E33,'FESTIVO 1'!D:AB,11,0) -> 38605 | AB33: M0399(A EFREN) | AC33: =VLOOKUP(AB33,E:O,2,0) -> 1430170 | AD33: =VLOOKUP(AB33,E:O,4,0) -> 128829 | AF33: M0360(A YEDANY) | AG33: =VLOOKUP(AF33,E:O,2,0) -> 1501590 | AH33: =VLOOKUP(AF33,E:O,4,0) -> 115208 | AJ33: M0140(A JAQUE) | AK33: =VLOOKUP(AJ33,E:O,2,0) -> 1605756 | AL33: =VLOOKUP(AJ33,E:O,4,0) -> 109437
E34: A0119(WILL) | F34: =VLOOKUP(E34,'ASIGNACION RANKING'!D:AB,7,0)-P34-Q34 -> 1146747 | G34: =VLOOKUP(E34,'ASIGNACION RANKING'!D:AB,6,0) -> 903 | H34: =VLOOKUP(E34,'ASIGNACION RANKING'!D:AB,11,0)-S34-T34 -> 147681 | J34: =H34/F34 -> 0.12878255 | K34: 3 | L34: =K34/$L$30 -> 0.032608696 | M34: =IF(L34<=0.02,"A1",IF(L34<=0.04,"A2",IF(L34<=0.06,"A3",IF(L34<=0.08,"A4",IF(L34<=0.1,"A5",IF(L34<=0.16,"B1",IF(L34<=0.22,"B2",IF(L34<=0.28,"B3",IF(L34<=0.34,"B4",IF(L34<=0.4,"B5",IF(L34<=0.46,"B6",IF(L34<=0.52,"B7",IF(L34<=0.58,"B8",IF(L34<=0.64,"B9",IF(L34<=0.7,"B10",IF(L34<=1.1,"C0")))))))))))))))) -> A2 | N34: =F34*J33-H34 -> 6991.9467 | O34: =IF(M34="A1",1650000,IF(M34="A2",1290000,IF(M34="A3",1020000,IF(M34="A4",810000,IF(M34="A5",650000,IF(M34="B1",520000,IF(M34="B2",420000,IF(M34="B3",330000,IF(M34="B4",270000,IF(M34="B5",210000,IF(M34="B6",170000,IF(M34="B7",150000,IF(M34="B8",130000,IF(M34="B9",100000,IF(M34="B10",60000,IF(M34="C0",0)))))))))))))))) -> 1290000 | P34: =VLOOKUP(E34,'DOMINGO 1'!D:AB,7,0) -> 104658 | Q34: =VLOOKUP(E34,'DOMINGO 2'!D:AB,7,0) -> 82610 | R34: =VLOOKUP(E34,'DOMINGO 3'!D:AB,7,0) -> #N/A | S34: =VLOOKUP(E34,'DOMINGO 1'!D:AB,11,0) -> 1847 | T34: =VLOOKUP(E34,'DOMINGO 2'!D:AB,11,0) -> 6305 | U34: =VLOOKUP(E34,'DOMINGO 3'!D:AB,11,0) -> #N/A | V34: =VLOOKUP(E34,'FESTIVO 1'!D:AB,7,0) -> 114771 | W34: =VLOOKUP(E34,'FESTIVO 1'!D:AB,11,0) -> 4722 | AB34: M0387(A IRAZEMA) | AC34: =VLOOKUP(AB34,E:O,2,0) -> 1465637 | AD34: =VLOOKUP(AB34,E:O,4,0) -> 145975 | AF34: M0434(P ARTURO) | AG34: =VLOOKUP(AF34,E:O,2,0) -> 1455678 | AH34: =VLOOKUP(AF34,E:O,4,0) -> 123103 | AJ34: M0385(A JAQUELIN) | AK34: =VLOOKUP(AJ34,E:O,2,0) -> 1372429 | AL34: =VLOOKUP(AJ34,E:O,4,0) -> 126189
E35: M0346(A JOVANI) | F35: =VLOOKUP(E35,'ASIGNACION RANKING'!D:AB,7,0)-P35-Q35 -> 1236203 | G35: =VLOOKUP(E35,'ASIGNACION RANKING'!D:AB,6,0) -> 835 | H35: =VLOOKUP(E35,'ASIGNACION RANKING'!D:AB,11,0)-S35-T35 -> 143184 | J35: =H35/F35 -> 0.11582564 | K35: 4 | L35: =K35/$L$30 -> 0.043478261 | M35: =IF(L35<=0.02,"A1",IF(L35<=0.04,"A2",IF(L35<=0.06,"A3",IF(L35<=0.08,"A4",IF(L35<=0.1,"A5",IF(L35<=0.16,"B1",IF(L35<=0.22,"B2",IF(L35<=0.28,"B3",IF(L35<=0.34,"B4",IF(L35<=0.4,"B5",IF(L35<=0.46,"B6",IF(L35<=0.52,"B7",IF(L35<=0.58,"B8",IF(L35<=0.64,"B9",IF(L35<=0.7,"B10",IF(L35<=1.1,"C0")))))))))))))))) -> A3 | N35: =F35*J34-H35 -> 16017.372 | O35: =IF(M35="A1",1650000,IF(M35="A2",1290000,IF(M35="A3",1020000,IF(M35="A4",810000,IF(M35="A5",650000,IF(M35="B1",520000,IF(M35="B2",420000,IF(M35="B3",330000,IF(M35="B4",270000,IF(M35="B5",210000,IF(M35="B6",170000,IF(M35="B7",150000,IF(M35="B8",130000,IF(M35="B9",100000,IF(M35="B10",60000,IF(M35="C0",0)))))))))))))))) -> 1020000 | P35: =VLOOKUP(E35,'DOMINGO 1'!D:AB,7,0) -> 106583 | Q35: =VLOOKUP(E35,'DOMINGO 2'!D:AB,7,0) -> 111110 | R35: =VLOOKUP(E35,'DOMINGO 3'!D:AB,7,0) -> #N/A | S35: =VLOOKUP(E35,'DOMINGO 1'!D:AB,11,0) -> 9186 | T35: =VLOOKUP(E35,'DOMINGO 2'!D:AB,11,0) -> 2672 | U35: =VLOOKUP(E35,'DOMINGO 3'!D:AB,11,0) -> #N/A | V35: =VLOOKUP(E35,'FESTIVO 1'!D:AB,7,0) -> 118840 | W35: =VLOOKUP(E35,'FESTIVO 1'!D:AB,11,0) -> 16576 | AB35: M0390(A OLIVER) | AC35: =VLOOKUP(AB35,E:O,2,0) -> 1640079 | AD35: =VLOOKUP(AB35,E:O,4,0) -> 85940 | AF35: M0222(P AZUL) | AG35: =VLOOKUP(AF35,E:O,2,0) -> 1448862 | AH35: =VLOOKUP(AF35,E:O,4,0) -> 105706 | AJ35: M0300(A JOCELYN) | AK35: =VLOOKUP(AJ35,E:O,2,0) -> 1264864 | AL35: =VLOOKUP(AJ35,E:O,4,0) -> 124588
E36: A0072(MIGUEL GARCIA) | F36: =VLOOKUP(E36,'ASIGNACION RANKING'!D:AB,7,0)-P36-Q36 -> 1266014 | G36: =VLOOKUP(E36,'ASIGNACION RANKING'!D:AB,6,0) -> 914 | H36: =VLOOKUP(E36,'ASIGNACION RANKING'!D:AB,11,0)-S36-T36 -> 144388 | I36: 14.12 | J36: =H36/F36 -> 0.11404929 | K36: 5 | L36: =K36/$L$30 -> 0.054347826 | M36: =IF(L36<=0.02,"A1",IF(L36<=0.04,"A2",IF(L36<=0.06,"A3",IF(L36<=0.08,"A4",IF(L36<=0.1,"A5",IF(L36<=0.16,"B1",IF(L36<=0.22,"B2",IF(L36<=0.28,"B3",IF(L36<=0.34,"B4",IF(L36<=0.4,"B5",IF(L36<=0.46,"B6",IF(L36<=0.52,"B7",IF(L36<=0.58,"B8",IF(L36<=0.64,"B9",IF(L36<=0.7,"B10",IF(L36<=1.1,"C0")))))))))))))))) -> A3 | N36: =F36*J35-H36 -> 2248.8781 | O36: =IF(M36="A1",1650000,IF(M36="A2",1290000,IF(M36="A3",1020000,IF(M36="A4",810000,IF(M36="A5",650000,IF(M36="B1",520000,IF(M36="B2",420000,IF(M36="B3",330000,IF(M36="B4",270000,IF(M36="B5",210000,IF(M36="B6",170000,IF(M36="B7",150000,IF(M36="B8",130000,IF(M36="B9",100000,IF(M36="B10",60000,IF(M36="C0",0)))))))))))))))) -> 1020000 | P36: =VLOOKUP(E36,'DOMINGO 1'!D:AB,7,0) -> 126229 | Q36: =VLOOKUP(E36,'DOMINGO 2'!D:AB,7,0) -> 97375 | R36: =VLOOKUP(E36,'DOMINGO 3'!D:AB,7,0) -> #N/A | S36: =VLOOKUP(E36,'DOMINGO 1'!D:AB,11,0) -> 890 | T36: =VLOOKUP(E36,'DOMINGO 2'!D:AB,11,0) -> 4445 | U36: =VLOOKUP(E36,'DOMINGO 3'!D:AB,11,0) -> #N/A | V36: =VLOOKUP(E36,'FESTIVO 1'!D:AB,7,0) -> 114427 | W36: =VLOOKUP(E36,'FESTIVO 1'!D:AB,11,0) -> 10362 | AB36: M0376(A OSWALDO) | AC36: =VLOOKUP(AB36,E:O,2,0) -> 1325989 | AD36: =VLOOKUP(AB36,E:O,4,0) -> 109228 | AF36: M0092(P DANIELA) | AG36: =VLOOKUP(AF36,E:O,2,0) -> 1538337 | AH36: =VLOOKUP(AF36,E:O,4,0) -> 94382 | AJ36: M0086(A JOHANA GUADALUPE) | AK36: =VLOOKUP(AJ36,E:O,2,0) -> 1479796 | AL36: =VLOOKUP(AJ36,E:O,4,0) -> 94237
E37: A0363(Kevin Martinez) | F37: =VLOOKUP(E37,'ASIGNACION RANKING'!D:AB,7,0)-P37-Q37 -> 1132129 | G37: =VLOOKUP(E37,'ASIGNACION RANKING'!D:AB,6,0) -> 721 | H37: =VLOOKUP(E37,'ASIGNACION RANKING'!D:AB,11,0)-S37-T37 -> 126847 | J37: =H37/F37 -> 0.11204289 | K37: 6 | L37: =K37/$L$30 -> 0.065217391 | M37: =IF(L37<=0.02,"A1",IF(L37<=0.04,"A2",IF(L37<=0.06,"A3",IF(L37<=0.08,"A4",IF(L37<=0.1,"A5",IF(L37<=0.16,"B1",IF(L37<=0.22,"B2",IF(L37<=0.28,"B3",IF(L37<=0.34,"B4",IF(L37<=0.4,"B5",IF(L37<=0.46,"B6",IF(L37<=0.52,"B7",IF(L37<=0.58,"B8",IF(L37<=0.64,"B9",IF(L37<=0.7,"B10",IF(L37<=1.1,"C0")))))))))))))))) -> A4 | N37: =F37*J36-H37 -> 2271.5106 | O37: =IF(M37="A1",1650000,IF(M37="A2",1290000,IF(M37="A3",1020000,IF(M37="A4",810000,IF(M37="A5",650000,IF(M37="B1",520000,IF(M37="B2",420000,IF(M37="B3",330000,IF(M37="B4",270000,IF(M37="B5",210000,IF(M37="B6",170000,IF(M37="B7",150000,IF(M37="B8",130000,IF(M37="B9",100000,IF(M37="B10",60000,IF(M37="C0",0)))))))))))))))) -> 810000 | P37: =VLOOKUP(E37,'DOMINGO 1'!D:AB,7,0) -> 59027 | Q37: =VLOOKUP(E37,'DOMINGO 2'!D:AB,7,0) -> 110348 | R37: =VLOOKUP(E37,'DOMINGO 3'!D:AB,7,0) -> #N/A | S37: =VLOOKUP(E37,'DOMINGO 1'!D:AB,11,0) -> 4548 | T37: =VLOOKUP(E37,'DOMINGO 2'!D:AB,11,0) -> 926 | U37: =VLOOKUP(E37,'DOMINGO 3'!D:AB,11,0) -> #N/A | V37: =VLOOKUP(E37,'FESTIVO 1'!D:AB,7,0) -> 158552 | W37: =VLOOKUP(E37,'FESTIVO 1'!D:AB,11,0) -> 7240 | AB37: M0448(A SUHEYL) | AC37: =VLOOKUP(AB37,E:O,2,0) -> 1484037 | AD37: =VLOOKUP(AB37,E:O,4,0) -> 112977 | AF37: M0177(P ELIUD) | AG37: =VLOOKUP(AF37,E:O,2,0) -> 1612952 | AH37: =VLOOKUP(AF37,E:O,4,0) -> 103122 | AJ37: M0346(A JOVANI) | AK37: =VLOOKUP(AJ37,E:O,2,0) -> 1236203 | AL37: =VLOOKUP(AJ37,E:O,4,0) -> 143184
E38: A0383(ALISSON MACIAS) | F38: =VLOOKUP(E38,'ASIGNACION RANKING'!D:AB,7,0)-P38-Q38 -> 1375082 | G38: =VLOOKUP(E38,'ASIGNACION RANKING'!D:AB,6,0) -> 858 | H38: =VLOOKUP(E38,'ASIGNACION RANKING'!D:AB,11,0)-S38-T38 -> 153894 | J38: =H38/F38 -> 0.11191623 | K38: 7 | L38: =K38/$L$30 -> 0.076086957 | M38: =IF(L38<=0.02,"A1",IF(L38<=0.04,"A2",IF(L38<=0.06,"A3",IF(L38<=0.08,"A4",IF(L38<=0.1,"A5",IF(L38<=0.16,"B1",IF(L38<=0.22,"B2",IF(L38<=0.28,"B3",IF(L38<=0.34,"B4",IF(L38<=0.4,"B5",IF(L38<=0.46,"B6",IF(L38<=0.52,"B7",IF(L38<=0.58,"B8",IF(L38<=0.64,"B9",IF(L38<=0.7,"B10",IF(L38<=1.1,"C0")))))))))))))))) -> A4 | N38: =F38*J37-H38 -> 174.15518 | O38: =IF(M38="A1",1650000,IF(M38="A2",1290000,IF(M38="A3",1020000,IF(M38="A4",810000,IF(M38="A5",650000,IF(M38="B1",520000,IF(M38="B2",420000,IF(M38="B3",330000,IF(M38="B4",270000,IF(M38="B5",210000,IF(M38="B6",170000,IF(M38="B7",150000,IF(M38="B8",130000,IF(M38="B9",100000,IF(M38="B10",60000,IF(M38="C0",0)))))))))))))))) -> 810000 | P38: =VLOOKUP(E38,'DOMINGO 1'!D:AB,7,0) -> 136249 | Q38: =VLOOKUP(E38,'DOMINGO 2'!D:AB,7,0) -> 109958 | R38: =VLOOKUP(E38,'DOMINGO 3'!D:AB,7,0) -> #N/A | S38: =VLOOKUP(E38,'DOMINGO 1'!D:AB,11,0) -> 16733 | T38: =VLOOKUP(E38,'DOMINGO 2'!D:AB,11,0) -> 4847 | U38: =VLOOKUP(E38,'DOMINGO 3'!D:AB,11,0) -> #N/A | V38: 0 | W38: =VLOOKUP(E38,'FESTIVO 1'!D:AB,11,0) -> 13401 | AB38: M0299(P ALDANA) | AC38: =VLOOKUP(AB38,E:O,2,0) -> 1432415 | AD38: =VLOOKUP(AB38,E:O,4,0) -> 103598 | AF38: M0449(P FATIMA) | AG38: =VLOOKUP(AF38,E:O,2,0) -> 1406995 | AH38: =VLOOKUP(AF38,E:O,4,0) -> 124045 | AJ38: M0176(A LILIANA) | AK38: =VLOOKUP(AJ38,E:O,2,0) -> 1306058 | AL38: =VLOOKUP(AJ38,E:O,4,0) -> 118254
E39: A0444(NICOL AMEZQUITA) | F39: =VLOOKUP(E39,'ASIGNACION RANKING'!D:AB,7,0)-P39-Q39 -> 1284679 | G39: =VLOOKUP(E39,'ASIGNACION RANKING'!D:AB,6,0) -> 844 | H39: =VLOOKUP(E39,'ASIGNACION RANKING'!D:AB,11,0)-S39-T39 -> 140635 | J39: =H39/F39 -> 0.10947093 | K39: 8 | L39: =K39/$L$30 -> 0.086956522 | M39: =IF(L39<=0.02,"A1",IF(L39<=0.04,"A2",IF(L39<=0.06,"A3",IF(L39<=0.08,"A4",IF(L39<=0.1,"A5",IF(L39<=0.16,"B1",IF(L39<=0.22,"B2",IF(L39<=0.28,"B3",IF(L39<=0.34,"B4",IF(L39<=0.4,"B5",IF(L39<=0.46,"B6",IF(L39<=0.52,"B7",IF(L39<=0.58,"B8",IF(L39<=0.64,"B9",IF(L39<=0.7,"B10",IF(L39<=1.1,"C0")))))))))))))))) -> A5 | N39: =F39*J38-H39 -> 3141.4366 | O39: =IF(M39="A1",1650000,IF(M39="A2",1290000,IF(M39="A3",1020000,IF(M39="A4",810000,IF(M39="A5",650000,IF(M39="B1",520000,IF(M39="B2",420000,IF(M39="B3",330000,IF(M39="B4",270000,IF(M39="B5",210000,IF(M39="B6",170000,IF(M39="B7",150000,IF(M39="B8",130000,IF(M39="B9",100000,IF(M39="B10",60000,IF(M39="C0",0)))))))))))))))) -> 650000 | P39: =VLOOKUP(E39,'DOMINGO 1'!D:AB,7,0) -> 124629 | Q39: =VLOOKUP(E39,'DOMINGO 2'!D:AB,7,0) -> 106613 | R39: =VLOOKUP(E39,'DOMINGO 3'!D:AB,7,0) -> #N/A | S39: =VLOOKUP(E39,'DOMINGO 1'!D:AB,11,0) -> 9235 | T39: =VLOOKUP(E39,'DOMINGO 2'!D:AB,11,0) -> 2655 | U39: =VLOOKUP(E39,'DOMINGO 3'!D:AB,11,0) -> #N/A | V39: =VLOOKUP(E39,'FESTIVO 1'!D:AB,7,0) -> 164651 | W39: =VLOOKUP(E39,'FESTIVO 1'!D:AB,11,0) -> 28384 | AB39: M0301(P ARTURO VALENCIA) | AC39: =VLOOKUP(AB39,E:O,2,0) -> 1602681 | AD39: =VLOOKUP(AB39,E:O,4,0) -> 119089 | AF39: M0014(P GAEL) | AG39: =VLOOKUP(AF39,E:O,2,0) -> 1319541 | AH39: =VLOOKUP(AF39,E:O,4,0) -> 122534 | AJ39: M0308(A SADIT) | AK39: =VLOOKUP(AJ39,E:O,2,0) -> 1091152 | AL39: =VLOOKUP(AJ39,E:O,4,0) -> 116977
E40: M0121(A ERANDY) | F40: =VLOOKUP(E40,'ASIGNACION RANKING'!D:AB,7,0)-P40-Q40 -> 1236037 | G40: =VLOOKUP(E40,'ASIGNACION RANKING'!D:AB,6,0) -> 816 | H40: =VLOOKUP(E40,'ASIGNACION RANKING'!D:AB,11,0)-S40-T40 -> 134290 | J40: =H40/F40 -> 0.10864561 | K40: 9 | L40: =K40/$L$30 -> 0.097826087 | M40: =IF(L40<=0.02,"A1",IF(L40<=0.04,"A2",IF(L40<=0.06,"A3",IF(L40<=0.08,"A4",IF(L40<=0.1,"A5",IF(L40<=0.16,"B1",IF(L40<=0.22,"B2",IF(L40<=0.28,"B3",IF(L40<=0.34,"B4",IF(L40<=0.4,"B5",IF(L40<=0.46,"B6",IF(L40<=0.52,"B7",IF(L40<=0.58,"B8",IF(L40<=0.64,"B9",IF(L40<=0.7,"B10",IF(L40<=1.1,"C0")))))))))))))))) -> A5 | N40: =F40*J39-H40 -> 1020.1152 | O40: =IF(M40="A1",1650000,IF(M40="A2",1290000,IF(M40="A3",1020000,IF(M40="A4",810000,IF(M40="A5",650000,IF(M40="B1",520000,IF(M40="B2",420000,IF(M40="B3",330000,IF(M40="B4",270000,IF(M40="B5",210000,IF(M40="B6",170000,IF(M40="B7",150000,IF(M40="B8",130000,IF(M40="B9",100000,IF(M40="B10",60000,IF(M40="C0",0)))))))))))))))) -> 650000 | P40: =VLOOKUP(E40,'DOMINGO 1'!D:AB,7,0) -> 122727 | Q40: =VLOOKUP(E40,'DOMINGO 2'!D:AB,7,0) -> 125240 | R40: =VLOOKUP(E40,'DOMINGO 3'!D:AB,7,0) -> #N/A | S40: =VLOOKUP(E40,'DOMINGO 1'!D:AB,11,0) -> 13567 | T40: =VLOOKUP(E40,'DOMINGO 2'!D:AB,11,0) -> 6737 | U40: =VLOOKUP(E40,'DOMINGO 3'!D:AB,11,0) -> #N/A | V40: =VLOOKUP(E40,'FESTIVO 1'!D:AB,7,0) -> 134612 | W40: =VLOOKUP(E40,'FESTIVO 1'!D:AB,11,0) -> 18549 | AB40: M0368(P JULIO) | AC40: =VLOOKUP(AB40,E:O,2,0) -> 1255949 | AD40: =VLOOKUP(AB40,E:O,4,0) -> 112111 | AF40: M0412(P GISELLE) | AG40: =VLOOKUP(AF40,E:O,2,0) -> 1288386 | AH40: =VLOOKUP(AF40,E:O,4,0) -> 92346 | AJ40: M0432(A TOLEDO) | AK40: =VLOOKUP(AJ40,E:O,2,0) -> 1423611 | AL40: =VLOOKUP(AJ40,E:O,4,0) -> 119242
E41: M0308(A SADIT) | F41: =VLOOKUP(E41,'ASIGNACION RANKING'!D:AB,7,0)-P41-Q41 -> 1091152 | G41: =VLOOKUP(E41,'ASIGNACION RANKING'!D:AB,6,0) -> 740 | H41: =VLOOKUP(E41,'ASIGNACION RANKING'!D:AB,11,0)-S41-T41 -> 116977 | J41: =H41/F41 -> 0.10720505 | K41: 10 | L41: =K41/$L$30 -> 0.10869565 | M41: =IF(L41<=0.02,"A1",IF(L41<=0.04,"A2",IF(L41<=0.06,"A3",IF(L41<=0.08,"A4",IF(L41<=0.1,"A5",IF(L41<=0.16,"B1",IF(L41<=0.22,"B2",IF(L41<=0.28,"B3",IF(L41<=0.34,"B4",IF(L41<=0.4,"B5",IF(L41<=0.46,"B6",IF(L41<=0.52,"B7",IF(L41<=0.58,"B8",IF(L41<=0.64,"B9",IF(L41<=0.7,"B10",IF(L41<=1.1,"C0")))))))))))))))) -> B1 | N41: =F41*J40-H41 -> 1571.8801 | O41: =IF(M41="A1",1650000,IF(M41="A2",1290000,IF(M41="A3",1020000,IF(M41="A4",810000,IF(M41="A5",650000,IF(M41="B1",520000,IF(M41="B2",420000,IF(M41="B3",330000,IF(M41="B4",270000,IF(M41="B5",210000,IF(M41="B6",170000,IF(M41="B7",150000,IF(M41="B8",130000,IF(M41="B9",100000,IF(M41="B10",60000,IF(M41="C0",0)))))))))))))))) -> 520000 | P41: =VLOOKUP(E41,'DOMINGO 1'!D:AB,7,0) -> 48709 | Q41: =VLOOKUP(E41,'DOMINGO 2'!D:AB,7,0) -> 130738 | R41: =VLOOKUP(E41,'DOMINGO 3'!D:AB,7,0) -> #N/A | S41: =VLOOKUP(E41,'DOMINGO 1'!D:AB,11,0) -> 5603 | T41: =VLOOKUP(E41,'DOMINGO 2'!D:AB,11,0) -> 10108 | U41: =VLOOKUP(E41,'DOMINGO 3'!D:AB,11,0) -> #N/A | V41: =VLOOKUP(E41,'FESTIVO 1'!D:AB,7,0) -> #N/A | W41: =VLOOKUP(E41,'FESTIVO 1'!D:AB,11,0) -> #N/A | AB41: M0332(P KAREN) | AC41: =VLOOKUP(AB41,E:O,2,0) -> 1404335 | AD41: =VLOOKUP(AB41,E:O,4,0) -> 119365 | AF41: M0119(P JESUS) | AG41: =VLOOKUP(AF41,E:O,2,0) -> 1629255 | AH41: =VLOOKUP(AF41,E:O,4,0) -> 141994 | AJ41: M0441(A YAZMIN) | AK41: =VLOOKUP(AJ41,E:O,2,0) -> 1594937 | AL41: =VLOOKUP(AJ41,E:O,4,0) -> 107323
E42: A0346(CATA TAMARA) | F42: =VLOOKUP(E42,'ASIGNACION RANKING'!D:AB,7,0)-P42-Q42 -> 1235282 | G42: =VLOOKUP(E42,'ASIGNACION RANKING'!D:AB,6,0) -> 947 | H42: =VLOOKUP(E42,'ASIGNACION RANKING'!D:AB,11,0)-S42-T42 -> 130801 | J42: =H42/F42 -> 0.10588756 | K42: 11 | L42: =K42/$L$30 -> 0.11956522 | M42: =IF(L42<=0.02,"A1",IF(L42<=0.04,"A2",IF(L42<=0.06,"A3",IF(L42<=0.08,"A4",IF(L42<=0.1,"A5",IF(L42<=0.16,"B1",IF(L42<=0.22,"B2",IF(L42<=0.28,"B3",IF(L42<=0.34,"B4",IF(L42<=0.4,"B5",IF(L42<=0.46,"B6",IF(L42<=0.52,"B7",IF(L42<=0.58,"B8",IF(L42<=0.64,"B9",IF(L42<=0.7,"B10",IF(L42<=1.1,"C0")))))))))))))))) -> B1 | N42: =F42*J41-H42 -> 1627.4632 | O42: =IF(M42="A1",1650000,IF(M42="A2",1290000,IF(M42="A3",1020000,IF(M42="A4",810000,IF(M42="A5",650000,IF(M42="B1",520000,IF(M42="B2",420000,IF(M42="B3",330000,IF(M42="B4",270000,IF(M42="B5",210000,IF(M42="B6",170000,IF(M42="B7",150000,IF(M42="B8",130000,IF(M42="B9",100000,IF(M42="B10",60000,IF(M42="C0",0)))))))))))))))) -> 520000 | P42: =VLOOKUP(E42,'DOMINGO 1'!D:AB,7,0) -> 115674 | Q42: =VLOOKUP(E42,'DOMINGO 2'!D:AB,7,0) -> 93601 | R42: =VLOOKUP(E42,'DOMINGO 3'!D:AB,7,0) -> #N/A | S42: =VLOOKUP(E42,'DOMINGO 1'!D:AB,11,0) -> 2162 | T42: =VLOOKUP(E42,'DOMINGO 2'!D:AB,11,0) -> 3511 | U42: =VLOOKUP(E42,'DOMINGO 3'!D:AB,11,0) -> #N/A | V42: =VLOOKUP(E42,'FESTIVO 1'!D:AB,7,0) -> #N/A | W42: =VLOOKUP(E42,'FESTIVO 1'!D:AB,11,0) -> #N/A | AB42: M0333(P MARITZA) | AC42: =VLOOKUP(AB42,E:O,2,0) -> 1415586 | AD42: =VLOOKUP(AB42,E:O,4,0) -> 130094 | AF42: M0124(P LIZET) | AG42: =VLOOKUP(AF42,E:O,2,0) -> 1296138 | AH42: =VLOOKUP(AF42,E:O,4,0) -> 111726 | AJ42: M0310(A YEREMI) | AK42: =VLOOKUP(AJ42,E:O,2,0) -> 1187176 | AL42: =VLOOKUP(AJ42,E:O,4,0) -> 160126
E43: A0201(SHARON PRIETO) | F43: =VLOOKUP(E43,'ASIGNACION RANKING'!D:AB,7,0)-P43-Q43 -> 1253367 | G43: =VLOOKUP(E43,'ASIGNACION RANKING'!D:AB,6,0) -> 812 | H43: =VLOOKUP(E43,'ASIGNACION RANKING'!D:AB,11,0)-S43-T43 -> 129007 | J43: =H43/F43 -> 0.10292835 | K43: 12 | L43: =K43/$L$30 -> 0.13043478 | M43: =IF(L43<=0.02,"A1",IF(L43<=0.04,"A2",IF(L43<=0.06,"A3",IF(L43<=0.08,"A4",IF(L43<=0.1,"A5",IF(L43<=0.16,"B1",IF(L43<=0.22,"B2",IF(L43<=0.28,"B3",IF(L43<=0.34,"B4",IF(L43<=0.4,"B5",IF(L43<=0.46,"B6",IF(L43<=0.52,"B7",IF(L43<=0.58,"B8",IF(L43<=0.64,"B9",IF(L43<=0.7,"B10",IF(L43<=1.1,"C0")))))))))))))))) -> B1 | N43: =F43*J42-H43 -> 3708.9766 | O43: =IF(M43="A1",1650000,IF(M43="A2",1290000,IF(M43="A3",1020000,IF(M43="A4",810000,IF(M43="A5",650000,IF(M43="B1",520000,IF(M43="B2",420000,IF(M43="B3",330000,IF(M43="B4",270000,IF(M43="B5",210000,IF(M43="B6",170000,IF(M43="B7",150000,IF(M43="B8",130000,IF(M43="B9",100000,IF(M43="B10",60000,IF(M43="C0",0)))))))))))))))) -> 520000 | P43: =VLOOKUP(E43,'DOMINGO 1'!D:AB,7,0) -> 68753 | Q43: =VLOOKUP(E43,'DOMINGO 2'!D:AB,7,0) -> 138738 | R43: =VLOOKUP(E43,'DOMINGO 3'!D:AB,7,0) -> #N/A | S43: =VLOOKUP(E43,'DOMINGO 1'!D:AB,11,0) -> 1656 | T43: =VLOOKUP(E43,'DOMINGO 2'!D:AB,11,0) -> 4049 | U43: =VLOOKUP(E43,'DOMINGO 3'!D:AB,11,0) -> #N/A | V43: 0 | W43: =VLOOKUP(E43,'FESTIVO 1'!D:AB,11,0) -> #N/A | AB43: M0055(P MARYJO) | AC43: =VLOOKUP(AB43,E:O,2,0) -> 1479451 | AD43: =VLOOKUP(AB43,E:O,4,0) -> 121967 | AF43: M0134(P LORENA) | AG43: =VLOOKUP(AF43,E:O,2,0) -> 1127423 | AH43: =VLOOKUP(AF43,E:O,4,0) -> 107256 | AJ43: M0022(A YOLANDA) | AK43: =VLOOKUP(AJ43,E:O,2,0) -> 1335659 | AL43: =VLOOKUP(AJ43,E:O,4,0) -> 116994
E44: M0054(A CATALINA) | F44: =VLOOKUP(E44,'ASIGNACION RANKING'!D:AB,7,0)-P44-Q44 -> 1279043 | G44: =VLOOKUP(E44,'ASIGNACION RANKING'!D:AB,6,0) -> 935 | H44: =VLOOKUP(E44,'ASIGNACION RANKING'!D:AB,11,0)-S44-T44 -> 129892 | J44: =H44/F44 -> 0.10155405 | K44: 13 | L44: =K44/$L$30 -> 0.14130435 | M44: =IF(L44<=0.02,"A1",IF(L44<=0.04,"A2",IF(L44<=0.06,"A3",IF(L44<=0.08,"A4",IF(L44<=0.1,"A5",IF(L44<=0.16,"B1",IF(L44<=0.22,"B2",IF(L44<=0.28,"B3",IF(L44<=0.34,"B4",IF(L44<=0.4,"B5",IF(L44<=0.46,"B6",IF(L44<=0.52,"B7",IF(L44<=0.58,"B8",IF(L44<=0.64,"B9",IF(L44<=0.7,"B10",IF(L44<=1.1,"C0")))))))))))))))) -> B1 | N44: =F44*J43-H44 -> 1757.7884 | O44: =IF(M44="A1",1650000,IF(M44="A2",1290000,IF(M44="A3",1020000,IF(M44="A4",810000,IF(M44="A5",650000,IF(M44="B1",520000,IF(M44="B2",420000,IF(M44="B3",330000,IF(M44="B4",270000,IF(M44="B5",210000,IF(M44="B6",170000,IF(M44="B7",150000,IF(M44="B8",130000,IF(M44="B9",100000,IF(M44="B10",60000,IF(M44="C0",0)))))))))))))))) -> 520000 | P44: =VLOOKUP(E44,'DOMINGO 1'!D:AB,7,0) -> 126653 | Q44: =VLOOKUP(E44,'DOMINGO 2'!D:AB,7,0) -> 93059 | R44: =VLOOKUP(E44,'DOMINGO 3'!D:AB,7,0) -> #N/A | S44: =VLOOKUP(E44,'DOMINGO 1'!D:AB,11,0) -> 7818 | T44: =VLOOKUP(E44,'DOMINGO 2'!D:AB,11,0) -> 4234 | U44: =VLOOKUP(E44,'DOMINGO 3'!D:AB,11,0) -> #N/A | V44: 0 | W44: =VLOOKUP(E44,'FESTIVO 1'!D:AB,11,0) -> 14741 | AB44: M0262(P REGINA) | AC44: =VLOOKUP(AB44,E:O,2,0) -> 1643897 | AD44: =VLOOKUP(AB44,E:O,4,0) -> 121555 | AF44: M0352(P NICOLAS) | AG44: =VLOOKUP(AF44,E:O,2,0) -> 1484839 | AH44: =VLOOKUP(AF44,E:O,4,0) -> 114963 | AJ44: M0337(P MICHELL) | AK44: =VLOOKUP(AJ44,E:O,2,0) -> 1257092 | AL44: =VLOOKUP(AJ44,E:O,4,0) -> 100165
E45: A0263(NICOL MARQUEZ) | F45: =VLOOKUP(E45,'ASIGNACION RANKING'!D:AB,7,0)-P45-Q45 -> 1406761 | G45: =VLOOKUP(E45,'ASIGNACION RANKING'!D:AB,6,0) -> 886 | H45: =VLOOKUP(E45,'ASIGNACION RANKING'!D:AB,11,0)-S45-T45 -> 140428 | J45: =H45/F45 -> 0.099823637 | K45: 14 | L45: =K45/$L$30 -> 0.15217391 | M45: =IF(L45<=0.02,"A1",IF(L45<=0.04,"A2",IF(L45<=0.06,"A3",IF(L45<=0.08,"A4",IF(L45<=0.1,"A5",IF(L45<=0.16,"B1",IF(L45<=0.22,"B2",IF(L45<=0.28,"B3",IF(L45<=0.34,"B4",IF(L45<=0.4,"B5",IF(L45<=0.46,"B6",IF(L45<=0.52,"B7",IF(L45<=0.58,"B8",IF(L45<=0.64,"B9",IF(L45<=0.7,"B10",IF(L45<=1.1,"C0")))))))))))))))) -> B1 | N45: =F45*J44-H45 -> 2434.2805 | O45: =IF(M45="A1",1650000,IF(M45="A2",1290000,IF(M45="A3",1020000,IF(M45="A4",810000,IF(M45="A5",650000,IF(M45="B1",520000,IF(M45="B2",420000,IF(M45="B3",330000,IF(M45="B4",270000,IF(M45="B5",210000,IF(M45="B6",170000,IF(M45="B7",150000,IF(M45="B8",130000,IF(M45="B9",100000,IF(M45="B10",60000,IF(M45="C0",0)))))))))))))))) -> 520000 | P45: =VLOOKUP(E45,'DOMINGO 1'!D:AB,7,0) -> 178615 | Q45: =VLOOKUP(E45,'DOMINGO 2'!D:AB,7,0) -> 100554 | R45: =VLOOKUP(E45,'DOMINGO 3'!D:AB,7,0) -> #N/A | S45: =VLOOKUP(E45,'DOMINGO 1'!D:AB,11,0) -> 12697 | T45: =VLOOKUP(E45,'DOMINGO 2'!D:AB,11,0) -> 1956 | U45: =VLOOKUP(E45,'DOMINGO 3'!D:AB,11,0) -> #N/A | V45: 0 | W45: =VLOOKUP(E45,'FESTIVO 1'!D:AB,11,0) -> 3273 | AB45: TOTAL | AC45: =SUM(AC30:AC44) -> 22005901 | AD45: =SUM(AD30:AD44) -> 1754846 | AF45: M0336(P SARAHI) | AG45: =VLOOKUP(AF45,E:O,2,0) -> 1299430 | AH45: =VLOOKUP(AF45,E:O,4,0) -> 106064 | AJ45: M0351(P OMAR) | AK45: =VLOOKUP(AJ45,E:O,2,0) -> 1562775 | AL45: =VLOOKUP(AJ45,E:O,4,0) -> 112695
E46: M0387(A IRAZEMA) | F46: =VLOOKUP(E46,'ASIGNACION RANKING'!D:AB,7,0)-P46-Q46 -> 1465637 | G46: =VLOOKUP(E46,'ASIGNACION RANKING'!D:AB,6,0) -> 956 | H46: =VLOOKUP(E46,'ASIGNACION RANKING'!D:AB,11,0)-S46-T46 -> 145975 | J46: =H46/F46 -> 0.099598332 | K46: 15 | L46: =K46/$L$30 -> 0.16304348 | M46: =IF(L46<=0.02,"A1",IF(L46<=0.04,"A2",IF(L46<=0.06,"A3",IF(L46<=0.08,"A4",IF(L46<=0.1,"A5",IF(L46<=0.16,"B1",IF(L46<=0.22,"B2",IF(L46<=0.28,"B3",IF(L46<=0.34,"B4",IF(L46<=0.4,"B5",IF(L46<=0.46,"B6",IF(L46<=0.52,"B7",IF(L46<=0.58,"B8",IF(L46<=0.64,"B9",IF(L46<=0.7,"B10",IF(L46<=1.1,"C0")))))))))))))))) -> B2 | N46: =F46*J45-H46 -> 330.21648 | O46: =IF(M46="A1",1650000,IF(M46="A2",1290000,IF(M46="A3",1020000,IF(M46="A4",810000,IF(M46="A5",650000,IF(M46="B1",520000,IF(M46="B2",420000,IF(M46="B3",330000,IF(M46="B4",270000,IF(M46="B5",210000,IF(M46="B6",170000,IF(M46="B7",150000,IF(M46="B8",130000,IF(M46="B9",100000,IF(M46="B10",60000,IF(M46="C0",0)))))))))))))))) -> 420000 | P46: =VLOOKUP(E46,'DOMINGO 1'!D:AB,7,0) -> 122885 | Q46: =VLOOKUP(E46,'DOMINGO 2'!D:AB,7,0) -> 110584 | R46: =VLOOKUP(E46,'DOMINGO 3'!D:AB,7,0) -> #N/A | S46: =VLOOKUP(E46,'DOMINGO 1'!D:AB,11,0) -> 2558 | T46: =VLOOKUP(E46,'DOMINGO 2'!D:AB,11,0) -> 1714 | U46: =VLOOKUP(E46,'DOMINGO 3'!D:AB,11,0) -> #N/A | V46: 0 | W46: =VLOOKUP(E46,'FESTIVO 1'!D:AB,11,0) -> 8827 | AB46: =AD45/AC45 -> 0.079744338 | AF46: TOTAL | AG46: =SUM(AG30:AG45) -> 22502682 | AH46: =SUM(AH30:AH45) -> 1815786 | AJ46: TOTAL | AK46: =SUM(AK30:AK45) -> 21899281 | AL46: =SUM(AL30:AL45) -> 1901760
E47: A0221(DAVID GOMEZ) | F47: =VLOOKUP(E47,'ASIGNACION RANKING'!D:AB,7,0)-P47-Q47 -> 1452433 | G47: =VLOOKUP(E47,'ASIGNACION RANKING'!D:AB,6,0) -> 892 | H47: =VLOOKUP(E47,'ASIGNACION RANKING'!D:AB,11,0)-S47-T47 -> 144565 | J47: =H47/F47 -> 0.099532991 | K47: 16 | L47: =K47/$L$30 -> 0.17391304 | M47: =IF(L47<=0.02,"A1",IF(L47<=0.04,"A2",IF(L47<=0.06,"A3",IF(L47<=0.08,"A4",IF(L47<=0.1,"A5",IF(L47<=0.16,"B1",IF(L47<=0.22,"B2",IF(L47<=0.28,"B3",IF(L47<=0.34,"B4",IF(L47<=0.4,"B5",IF(L47<=0.46,"B6",IF(L47<=0.52,"B7",IF(L47<=0.58,"B8",IF(L47<=0.64,"B9",IF(L47<=0.7,"B10",IF(L47<=1.1,"C0")))))))))))))))) -> B2 | N47: =F47*J46-H47 -> 94.903629 | O47: =IF(M47="A1",1650000,IF(M47="A2",1290000,IF(M47="A3",1020000,IF(M47="A4",810000,IF(M47="A5",650000,IF(M47="B1",520000,IF(M47="B2",420000,IF(M47="B3",330000,IF(M47="B4",270000,IF(M47="B5",210000,IF(M47="B6",170000,IF(M47="B7",150000,IF(M47="B8",130000,IF(M47="B9",100000,IF(M47="B10",60000,IF(M47="C0",0)))))))))))))))) -> 420000 | P47: =VLOOKUP(E47,'DOMINGO 1'!D:AB,7,0) -> 130494 | Q47: =VLOOKUP(E47,'DOMINGO 2'!D:AB,7,0) -> 116669 | R47: =VLOOKUP(E47,'DOMINGO 3'!D:AB,7,0) -> #N/A | S47: =VLOOKUP(E47,'DOMINGO 1'!D:AB,11,0) -> 17387 | T47: =VLOOKUP(E47,'DOMINGO 2'!D:AB,11,0) -> 680 | U47: =VLOOKUP(E47,'DOMINGO 3'!D:AB,11,0) -> #N/A | V47: =VLOOKUP(E47,'FESTIVO 1'!D:AB,7,0) -> 118427 | W47: =VLOOKUP(E47,'FESTIVO 1'!D:AB,11,0) -> 12896 | AF47: =AH46/AG46 -> 0.080691982 | AJ47: =AL46/AK46 -> 0.086841207
E48: M0300(A JOCELYN) | F48: =VLOOKUP(E48,'ASIGNACION RANKING'!D:AB,7,0)-P48-Q48 -> 1264864 | G48: =VLOOKUP(E48,'ASIGNACION RANKING'!D:AB,6,0) -> 883 | H48: =VLOOKUP(E48,'ASIGNACION RANKING'!D:AB,11,0)-S48-T48 -> 124588 | J48: =H48/F48 -> 0.098499127 | K48: 17 | L48: =K48/$L$30 -> 0.18478261 | M48: =IF(L48<=0.02,"A1",IF(L48<=0.04,"A2",IF(L48<=0.06,"A3",IF(L48<=0.08,"A4",IF(L48<=0.1,"A5",IF(L48<=0.16,"B1",IF(L48<=0.22,"B2",IF(L48<=0.28,"B3",IF(L48<=0.34,"B4",IF(L48<=0.4,"B5",IF(L48<=0.46,"B6",IF(L48<=0.52,"B7",IF(L48<=0.58,"B8",IF(L48<=0.64,"B9",IF(L48<=0.7,"B10",IF(L48<=1.1,"C0")))))))))))))))) -> B2 | N48: =F48*J47-H48 -> 1307.6965 | O48: =IF(M48="A1",1650000,IF(M48="A2",1290000,IF(M48="A3",1020000,IF(M48="A4",810000,IF(M48="A5",650000,IF(M48="B1",520000,IF(M48="B2",420000,IF(M48="B3",330000,IF(M48="B4",270000,IF(M48="B5",210000,IF(M48="B6",170000,IF(M48="B7",150000,IF(M48="B8",130000,IF(M48="B9",100000,IF(M48="B10",60000,IF(M48="C0",0)))))))))))))))) -> 420000 | P48: =VLOOKUP(E48,'DOMINGO 1'!D:AB,7,0) -> 138652 | Q48: =VLOOKUP(E48,'DOMINGO 2'!D:AB,7,0) -> 104471 | R48: =VLOOKUP(E48,'DOMINGO 3'!D:AB,7,0) -> #N/A | S48: =VLOOKUP(E48,'DOMINGO 1'!D:AB,11,0) -> 15008 | T48: =VLOOKUP(E48,'DOMINGO 2'!D:AB,11,0) -> 3978 | U48: =VLOOKUP(E48,'DOMINGO 3'!D:AB,11,0) -> #N/A | V48: =VLOOKUP(E48,'FESTIVO 1'!D:AB,7,0) -> 134222 | W48: =VLOOKUP(E48,'FESTIVO 1'!D:AB,11,0) -> 7291
E49: A0197(ASLE PERLAZA) | F49: =VLOOKUP(E49,'ASIGNACION RANKING'!D:AB,7,0)-P49-Q49 -> 1437376 | G49: =VLOOKUP(E49,'ASIGNACION RANKING'!D:AB,6,0) -> 877 | H49: =VLOOKUP(E49,'ASIGNACION RANKING'!D:AB,11,0)-S49-T49 -> 140701 | J49: =H49/F49 -> 0.0978874 | K49: 18 | L49: =K49/$L$30 -> 0.19565217 | M49: =IF(L49<=0.02,"A1",IF(L49<=0.04,"A2",IF(L49<=0.06,"A3",IF(L49<=0.08,"A4",IF(L49<=0.1,"A5",IF(L49<=0.16,"B1",IF(L49<=0.22,"B2",IF(L49<=0.28,"B3",IF(L49<=0.34,"B4",IF(L49<=0.4,"B5",IF(L49<=0.46,"B6",IF(L49<=0.52,"B7",IF(L49<=0.58,"B8",IF(L49<=0.64,"B9",IF(L49<=0.7,"B10",IF(L49<=1.1,"C0")))))))))))))))) -> B2 | N49: =F49*J48-H49 -> 879.28143 | O49: =IF(M49="A1",1650000,IF(M49="A2",1290000,IF(M49="A3",1020000,IF(M49="A4",810000,IF(M49="A5",650000,IF(M49="B1",520000,IF(M49="B2",420000,IF(M49="B3",330000,IF(M49="B4",270000,IF(M49="B5",210000,IF(M49="B6",170000,IF(M49="B7",150000,IF(M49="B8",130000,IF(M49="B9",100000,IF(M49="B10",60000,IF(M49="C0",0)))))))))))))))) -> 420000 | P49: =VLOOKUP(E49,'DOMINGO 1'!D:AB,7,0) -> 148669 | Q49: =VLOOKUP(E49,'DOMINGO 2'!D:AB,7,0) -> 108675 | R49: =VLOOKUP(E49,'DOMINGO 3'!D:AB,7,0) -> #N/A | S49: =VLOOKUP(E49,'DOMINGO 1'!D:AB,11,0) -> 10159 | T49: =VLOOKUP(E49,'DOMINGO 2'!D:AB,11,0) -> 12717 | U49: =VLOOKUP(E49,'DOMINGO 3'!D:AB,11,0) -> #N/A | V49: 0 | W49: =VLOOKUP(E49,'FESTIVO 1'!D:AB,11,0) -> 6254
E50: A0044(JOHAN CASTILLO) | F50: =VLOOKUP(E50,'ASIGNACION RANKING'!D:AB,7,0)-P50-Q50 -> 1425071 | G50: =VLOOKUP(E50,'ASIGNACION RANKING'!D:AB,6,0) -> 910 | H50: =VLOOKUP(E50,'ASIGNACION RANKING'!D:AB,11,0)-S50-T50 -> 137147 | J50: =H50/F50 -> 0.096238714 | K50: 19 | L50: =K50/$L$30 -> 0.20652174 | M50: =IF(L50<=0.02,"A1",IF(L50<=0.04,"A2",IF(L50<=0.06,"A3",IF(L50<=0.08,"A4",IF(L50<=0.1,"A5",IF(L50<=0.16,"B1",IF(L50<=0.22,"B2",IF(L50<=0.28,"B3",IF(L50<=0.34,"B4",IF(L50<=0.4,"B5",IF(L50<=0.46,"B6",IF(L50<=0.52,"B7",IF(L50<=0.58,"B8",IF(L50<=0.64,"B9",IF(L50<=0.7,"B10",IF(L50<=1.1,"C0")))))))))))))))) -> B2 | N50: =F50*J49-H50 -> 2349.4955 | O50: =IF(M50="A1",1650000,IF(M50="A2",1290000,IF(M50="A3",1020000,IF(M50="A4",810000,IF(M50="A5",650000,IF(M50="B1",520000,IF(M50="B2",420000,IF(M50="B3",330000,IF(M50="B4",270000,IF(M50="B5",210000,IF(M50="B6",170000,IF(M50="B7",150000,IF(M50="B8",130000,IF(M50="B9",100000,IF(M50="B10",60000,IF(M50="C0",0)))))))))))))))) -> 420000 | P50: =VLOOKUP(E50,'DOMINGO 1'!D:AB,7,0) -> 159105 | Q50: =VLOOKUP(E50,'DOMINGO 2'!D:AB,7,0) -> 87972 | R50: =VLOOKUP(E50,'DOMINGO 3'!D:AB,7,0) -> #N/A | S50: =VLOOKUP(E50,'DOMINGO 1'!D:AB,11,0) -> 9076 | T50: =VLOOKUP(E50,'DOMINGO 2'!D:AB,11,0) -> 4528 | U50: =VLOOKUP(E50,'DOMINGO 3'!D:AB,11,0) -> #N/A | V50: 0 | W50: =VLOOKUP(E50,'FESTIVO 1'!D:AB,11,0) -> 8656
E51: A0288(FABIAN STIVEN) | F51: =VLOOKUP(E51,'ASIGNACION RANKING'!D:AB,7,0)-P51-Q51 -> 1435695 | G51: =VLOOKUP(E51,'ASIGNACION RANKING'!D:AB,6,0) -> 960 | H51: =VLOOKUP(E51,'ASIGNACION RANKING'!D:AB,11,0)-S51-T51 -> 136800 | J51: =H51/F51 -> 0.095284862 | K51: 20 | L51: =K51/$L$30 -> 0.2173913 | M51: =IF(L51<=0.02,"A1",IF(L51<=0.04,"A2",IF(L51<=0.06,"A3",IF(L51<=0.08,"A4",IF(L51<=0.1,"A5",IF(L51<=0.16,"B1",IF(L51<=0.22,"B2",IF(L51<=0.28,"B3",IF(L51<=0.34,"B4",IF(L51<=0.4,"B5",IF(L51<=0.46,"B6",IF(L51<=0.52,"B7",IF(L51<=0.58,"B8",IF(L51<=0.64,"B9",IF(L51<=0.7,"B10",IF(L51<=1.1,"C0")))))))))))))))) -> B2 | N51: =F51*J50-H51 -> 1369.4401 | O51: =IF(M51="A1",1650000,IF(M51="A2",1290000,IF(M51="A3",1020000,IF(M51="A4",810000,IF(M51="A5",650000,IF(M51="B1",520000,IF(M51="B2",420000,IF(M51="B3",330000,IF(M51="B4",270000,IF(M51="B5",210000,IF(M51="B6",170000,IF(M51="B7",150000,IF(M51="B8",130000,IF(M51="B9",100000,IF(M51="B10",60000,IF(M51="C0",0)))))))))))))))) -> 420000 | P51: =VLOOKUP(E51,'DOMINGO 1'!D:AB,7,0) -> 144616 | Q51: =VLOOKUP(E51,'DOMINGO 2'!D:AB,7,0) -> 104116 | R51: =VLOOKUP(E51,'DOMINGO 3'!D:AB,7,0) -> #N/A | S51: =VLOOKUP(E51,'DOMINGO 1'!D:AB,11,0) -> 5765 | T51: =VLOOKUP(E51,'DOMINGO 2'!D:AB,11,0) -> 3989 | U51: =VLOOKUP(E51,'DOMINGO 3'!D:AB,11,0) -> #N/A | V51: 0 | W51: =VLOOKUP(E51,'FESTIVO 1'!D:AB,11,0) -> 1715
E52: M0134(P LORENA) | F52: =VLOOKUP(E52,'ASIGNACION RANKING'!D:AB,7,0)-P52-Q52 -> 1127423 | G52: =VLOOKUP(E52,'ASIGNACION RANKING'!D:AB,6,0) -> 763 | H52: =VLOOKUP(E52,'ASIGNACION RANKING'!D:AB,11,0)-S52-T52 -> 107256 | J52: =H52/F52 -> 0.09513377 | K52: 21 | L52: =K52/$L$30 -> 0.22826087 | M52: =IF(L52<=0.02,"A1",IF(L52<=0.04,"A2",IF(L52<=0.06,"A3",IF(L52<=0.08,"A4",IF(L52<=0.1,"A5",IF(L52<=0.16,"B1",IF(L52<=0.22,"B2",IF(L52<=0.28,"B3",IF(L52<=0.34,"B4",IF(L52<=0.4,"B5",IF(L52<=0.46,"B6",IF(L52<=0.52,"B7",IF(L52<=0.58,"B8",IF(L52<=0.64,"B9",IF(L52<=0.7,"B10",IF(L52<=1.1,"C0")))))))))))))))) -> B3 | N52: =F52*J51-H52 -> 170.34501 | O52: =IF(M52="A1",1650000,IF(M52="A2",1290000,IF(M52="A3",1020000,IF(M52="A4",810000,IF(M52="A5",650000,IF(M52="B1",520000,IF(M52="B2",420000,IF(M52="B3",330000,IF(M52="B4",270000,IF(M52="B5",210000,IF(M52="B6",170000,IF(M52="B7",150000,IF(M52="B8",130000,IF(M52="B9",100000,IF(M52="B10",60000,IF(M52="C0",0)))))))))))))))) -> 330000 | P52: =VLOOKUP(E52,'DOMINGO 1'!D:AB,7,0) -> 57241 | Q52: =VLOOKUP(E52,'DOMINGO 2'!D:AB,7,0) -> 126766 | R52: =VLOOKUP(E52,'DOMINGO 3'!D:AB,7,0) -> #N/A | S52: =VLOOKUP(E52,'DOMINGO 1'!D:AB,11,0) -> 5377 | T52: =VLOOKUP(E52,'DOMINGO 2'!D:AB,11,0) -> 3752 | U52: =VLOOKUP(E52,'DOMINGO 3'!D:AB,11,0) -> #N/A | V52: 0 | W52: =VLOOKUP(E52,'FESTIVO 1'!D:AB,11,0) -> #N/A
E53: A0431(SEBASNTIAN PIRANQUIVE) | F53: =VLOOKUP(E53,'ASIGNACION RANKING'!D:AB,7,0)-P53-Q53 -> 1315254 | G53: =VLOOKUP(E53,'ASIGNACION RANKING'!D:AB,6,0) -> 945 | H53: =VLOOKUP(E53,'ASIGNACION RANKING'!D:AB,11,0)-S53-T53 -> 122835 | J53: =H53/F53 -> 0.093392607 | K53: 22 | L53: =K53/$L$30 -> 0.23913043 | M53: =IF(L53<=0.02,"A1",IF(L53<=0.04,"A2",IF(L53<=0.06,"A3",IF(L53<=0.08,"A4",IF(L53<=0.1,"A5",IF(L53<=0.16,"B1",IF(L53<=0.22,"B2",IF(L53<=0.28,"B3",IF(L53<=0.34,"B4",IF(L53<=0.4,"B5",IF(L53<=0.46,"B6",IF(L53<=0.52,"B7",IF(L53<=0.58,"B8",IF(L53<=0.64,"B9",IF(L53<=0.7,"B10",IF(L53<=1.1,"C0")))))))))))))))) -> B3 | N53: =F53*J52-H53 -> 2290.0711 | O53: =IF(M53="A1",1650000,IF(M53="A2",1290000,IF(M53="A3",1020000,IF(M53="A4",810000,IF(M53="A5",650000,IF(M53="B1",520000,IF(M53="B2",420000,IF(M53="B3",330000,IF(M53="B4",270000,IF(M53="B5",210000,IF(M53="B6",170000,IF(M53="B7",150000,IF(M53="B8",130000,IF(M53="B9",100000,IF(M53="B10",60000,IF(M53="C0",0)))))))))))))))) -> 330000 | P53: =VLOOKUP(E53,'DOMINGO 1'!D:AB,7,0) -> 121195 | Q53: =VLOOKUP(E53,'DOMINGO 2'!D:AB,7,0) -> 104991 | R53: =VLOOKUP(E53,'DOMINGO 3'!D:AB,7,0) -> #N/A | S53: =VLOOKUP(E53,'DOMINGO 1'!D:AB,11,0) -> 3816 | T53: =VLOOKUP(E53,'DOMINGO 2'!D:AB,11,0) -> 1494 | U53: =VLOOKUP(E53,'DOMINGO 3'!D:AB,11,0) -> #N/A | V53: 0 | W53: =VLOOKUP(E53,'FESTIVO 1'!D:AB,11,0) -> 2925
E54: A0401(HELLEN MARIN) | F54: =VLOOKUP(E54,'ASIGNACION RANKING'!D:AB,7,0)-P54-Q54 -> 1245278 | G54: =VLOOKUP(E54,'ASIGNACION RANKING'!D:AB,6,0) -> 909 | H54: =VLOOKUP(E54,'ASIGNACION RANKING'!D:AB,11,0)-S54-T54 -> 116256 | J54: =H54/F54 -> 0.093357467 | K54: 23 | L54: =K54/$L$30 -> 0.25 | M54: =IF(L54<=0.02,"A1",IF(L54<=0.04,"A2",IF(L54<=0.06,"A3",IF(L54<=0.08,"A4",IF(L54<=0.1,"A5",IF(L54<=0.16,"B1",IF(L54<=0.22,"B2",IF(L54<=0.28,"B3",IF(L54<=0.34,"B4",IF(L54<=0.4,"B5",IF(L54<=0.46,"B6",IF(L54<=0.52,"B7",IF(L54<=0.58,"B8",IF(L54<=0.64,"B9",IF(L54<=0.7,"B10",IF(L54<=1.1,"C0")))))))))))))))) -> B3 | N54: =F54*J53-H54 -> 43.758929 | O54: =IF(M54="A1",1650000,IF(M54="A2",1290000,IF(M54="A3",1020000,IF(M54="A4",810000,IF(M54="A5",650000,IF(M54="B1",520000,IF(M54="B2",420000,IF(M54="B3",330000,IF(M54="B4",270000,IF(M54="B5",210000,IF(M54="B6",170000,IF(M54="B7",150000,IF(M54="B8",130000,IF(M54="B9",100000,IF(M54="B10",60000,IF(M54="C0",0)))))))))))))))) -> 330000 | P54: =VLOOKUP(E54,'DOMINGO 1'!D:AB,7,0) -> 91824 | Q54: =VLOOKUP(E54,'DOMINGO 2'!D:AB,7,0) -> 127416 | R54: =VLOOKUP(E54,'DOMINGO 3'!D:AB,7,0) -> #N/A | S54: =VLOOKUP(E54,'DOMINGO 1'!D:AB,11,0) -> 4973 | T54: =VLOOKUP(E54,'DOMINGO 2'!D:AB,11,0) -> 12084 | U54: =VLOOKUP(E54,'DOMINGO 3'!D:AB,11,0) -> #N/A | V54: =VLOOKUP(E54,'FESTIVO 1'!D:AB,7,0) -> 135967 | W54: =VLOOKUP(E54,'FESTIVO 1'!D:AB,11,0) -> 7962
E55: A0258(CRIS URREGO) | F55: =VLOOKUP(E55,'ASIGNACION RANKING'!D:AB,7,0)-P55-Q55 -> 1500967 | G55: =VLOOKUP(E55,'ASIGNACION RANKING'!D:AB,6,0) -> 928 | H55: =VLOOKUP(E55,'ASIGNACION RANKING'!D:AB,11,0)-S55-T55 -> 139570 | J55: =H55/F55 -> 0.092986721 | K55: 24 | L55: =K55/$L$30 -> 0.26086957 | M55: =IF(L55<=0.02,"A1",IF(L55<=0.04,"A2",IF(L55<=0.06,"A3",IF(L55<=0.08,"A4",IF(L55<=0.1,"A5",IF(L55<=0.16,"B1",IF(L55<=0.22,"B2",IF(L55<=0.28,"B3",IF(L55<=0.34,"B4",IF(L55<=0.4,"B5",IF(L55<=0.46,"B6",IF(L55<=0.52,"B7",IF(L55<=0.58,"B8",IF(L55<=0.64,"B9",IF(L55<=0.7,"B10",IF(L55<=1.1,"C0")))))))))))))))) -> B3 | N55: =F55*J54-H55 -> 556.47742 | O55: =IF(M55="A1",1650000,IF(M55="A2",1290000,IF(M55="A3",1020000,IF(M55="A4",810000,IF(M55="A5",650000,IF(M55="B1",520000,IF(M55="B2",420000,IF(M55="B3",330000,IF(M55="B4",270000,IF(M55="B5",210000,IF(M55="B6",170000,IF(M55="B7",150000,IF(M55="B8",130000,IF(M55="B9",100000,IF(M55="B10",60000,IF(M55="C0",0)))))))))))))))) -> 330000 | P55: =VLOOKUP(E55,'DOMINGO 1'!D:AB,7,0) -> 148155 | Q55: =VLOOKUP(E55,'DOMINGO 2'!D:AB,7,0) -> 135241 | R55: =VLOOKUP(E55,'DOMINGO 3'!D:AB,7,0) -> #N/A | S55: =VLOOKUP(E55,'DOMINGO 1'!D:AB,11,0) -> 3898 | T55: =VLOOKUP(E55,'DOMINGO 2'!D:AB,11,0) -> 6698 | U55: =VLOOKUP(E55,'DOMINGO 3'!D:AB,11,0) -> #N/A | V55: 0 | W55: =VLOOKUP(E55,'FESTIVO 1'!D:AB,11,0) -> 6415
E56: M0014(P GAEL) | F56: =VLOOKUP(E56,'ASIGNACION RANKING'!D:AB,7,0)-P56-Q56 -> 1319541 | G56: =VLOOKUP(E56,'ASIGNACION RANKING'!D:AB,6,0) -> 862 | H56: =VLOOKUP(E56,'ASIGNACION RANKING'!D:AB,11,0)-S56-T56 -> 122534 | J56: =H56/F56 -> 0.092861078 | K56: 25 | L56: =K56/$L$30 -> 0.27173913 | M56: =IF(L56<=0.02,"A1",IF(L56<=0.04,"A2",IF(L56<=0.06,"A3",IF(L56<=0.08,"A4",IF(L56<=0.1,"A5",IF(L56<=0.16,"B1",IF(L56<=0.22,"B2",IF(L56<=0.28,"B3",IF(L56<=0.34,"B4",IF(L56<=0.4,"B5",IF(L56<=0.46,"B6",IF(L56<=0.52,"B7",IF(L56<=0.58,"B8",IF(L56<=0.64,"B9",IF(L56<=0.7,"B10",IF(L56<=1.1,"C0")))))))))))))))) -> B3 | N56: =F56*J55-H56 -> 165.79111 | O56: =IF(M56="A1",1650000,IF(M56="A2",1290000,IF(M56="A3",1020000,IF(M56="A4",810000,IF(M56="A5",650000,IF(M56="B1",520000,IF(M56="B2",420000,IF(M56="B3",330000,IF(M56="B4",270000,IF(M56="B5",210000,IF(M56="B6",170000,IF(M56="B7",150000,IF(M56="B8",130000,IF(M56="B9",100000,IF(M56="B10",60000,IF(M56="C0",0)))))))))))))))) -> 330000 | P56: =VLOOKUP(E56,'DOMINGO 1'!D:AB,7,0) -> 107134 | Q56: =VLOOKUP(E56,'DOMINGO 2'!D:AB,7,0) -> 151457 | R56: =VLOOKUP(E56,'DOMINGO 3'!D:AB,7,0) -> #N/A | S56: =VLOOKUP(E56,'DOMINGO 1'!D:AB,11,0) -> 16142 | T56: =VLOOKUP(E56,'DOMINGO 2'!D:AB,11,0) -> 3828 | U56: =VLOOKUP(E56,'DOMINGO 3'!D:AB,11,0) -> #N/A | V56: 0 | W56: =VLOOKUP(E56,'FESTIVO 1'!D:AB,11,0) -> 12111
E57: M0385(A JAQUELIN) | F57: =VLOOKUP(E57,'ASIGNACION RANKING'!D:AB,7,0)-P57-Q57 -> 1372429 | G57: =VLOOKUP(E57,'ASIGNACION RANKING'!D:AB,6,0) -> 935 | H57: =VLOOKUP(E57,'ASIGNACION RANKING'!D:AB,11,0)-S57-T57 -> 126189 | J57: =H57/F57 -> 0.09194574 | K57: 26 | L57: =K57/$L$30 -> 0.2826087 | M57: =IF(L57<=0.02,"A1",IF(L57<=0.04,"A2",IF(L57<=0.06,"A3",IF(L57<=0.08,"A4",IF(L57<=0.1,"A5",IF(L57<=0.16,"B1",IF(L57<=0.22,"B2",IF(L57<=0.28,"B3",IF(L57<=0.34,"B4",IF(L57<=0.4,"B5",IF(L57<=0.46,"B6",IF(L57<=0.52,"B7",IF(L57<=0.58,"B8",IF(L57<=0.64,"B9",IF(L57<=0.7,"B10",IF(L57<=1.1,"C0")))))))))))))))) -> B4 | N57: =F57*J56-H57 -> 1256.2367 | O57: =IF(M57="A1",1650000,IF(M57="A2",1290000,IF(M57="A3",1020000,IF(M57="A4",810000,IF(M57="A5",650000,IF(M57="B1",520000,IF(M57="B2",420000,IF(M57="B3",330000,IF(M57="B4",270000,IF(M57="B5",210000,IF(M57="B6",170000,IF(M57="B7",150000,IF(M57="B8",130000,IF(M57="B9",100000,IF(M57="B10",60000,IF(M57="C0",0)))))))))))))))) -> 270000 | P57: =VLOOKUP(E57,'DOMINGO 1'!D:AB,7,0) -> 128837 | Q57: =VLOOKUP(E57,'DOMINGO 2'!D:AB,7,0) -> 109030 | R57: =VLOOKUP(E57,'DOMINGO 3'!D:AB,7,0) -> #N/A | S57: =VLOOKUP(E57,'DOMINGO 1'!D:AB,11,0) -> 8303 | T57: =VLOOKUP(E57,'DOMINGO 2'!D:AB,11,0) -> 10128 | U57: =VLOOKUP(E57,'DOMINGO 3'!D:AB,11,0) -> #N/A | V57: 0 | W57: =VLOOKUP(E57,'FESTIVO 1'!D:AB,11,0) -> 6389
E58: M0333(P MARITZA) | F58: =VLOOKUP(E58,'ASIGNACION RANKING'!D:AB,7,0)-P58-Q58 -> 1415586 | G58: =VLOOKUP(E58,'ASIGNACION RANKING'!D:AB,6,0) -> 960 | H58: =VLOOKUP(E58,'ASIGNACION RANKING'!D:AB,11,0)-S58-T58 -> 130094 | J58: =H58/F58 -> 0.091901163 | K58: 27 | L58: =K58/$L$30 -> 0.29347826 | M58: =IF(L58<=0.02,"A1",IF(L58<=0.04,"A2",IF(L58<=0.06,"A3",IF(L58<=0.08,"A4",IF(L58<=0.1,"A5",IF(L58<=0.16,"B1",IF(L58<=0.22,"B2",IF(L58<=0.28,"B3",IF(L58<=0.34,"B4",IF(L58<=0.4,"B5",IF(L58<=0.46,"B6",IF(L58<=0.52,"B7",IF(L58<=0.58,"B8",IF(L58<=0.64,"B9",IF(L58<=0.7,"B10",IF(L58<=1.1,"C0")))))))))))))))) -> B4 | N58: =F58*J57-H58 -> 63.102301 | O58: =IF(M58="A1",1650000,IF(M58="A2",1290000,IF(M58="A3",1020000,IF(M58="A4",810000,IF(M58="A5",650000,IF(M58="B1",520000,IF(M58="B2",420000,IF(M58="B3",330000,IF(M58="B4",270000,IF(M58="B5",210000,IF(M58="B6",170000,IF(M58="B7",150000,IF(M58="B8",130000,IF(M58="B9",100000,IF(M58="B10",60000,IF(M58="C0",0)))))))))))))))) -> 270000 | P58: =VLOOKUP(E58,'DOMINGO 1'!D:AB,7,0) -> 160535 | Q58: =VLOOKUP(E58,'DOMINGO 2'!D:AB,7,0) -> 128050 | R58: =VLOOKUP(E58,'DOMINGO 3'!D:AB,7,0) -> #N/A | S58: =VLOOKUP(E58,'DOMINGO 1'!D:AB,11,0) -> 9531 | T58: =VLOOKUP(E58,'DOMINGO 2'!D:AB,11,0) -> 13347 | U58: =VLOOKUP(E58,'DOMINGO 3'!D:AB,11,0) -> #N/A | V58: 0 | W58: =VLOOKUP(E58,'FESTIVO 1'!D:AB,11,0) -> 11887
E59: A0222(PIPE GONZALEZ) | F59: =VLOOKUP(E59,'ASIGNACION RANKING'!D:AB,7,0)-P59-Q59 -> 1498819 | G59: =VLOOKUP(E59,'ASIGNACION RANKING'!D:AB,6,0) -> 965 | H59: =VLOOKUP(E59,'ASIGNACION RANKING'!D:AB,11,0)-S59-T59 -> 137211 | J59: =H59/F59 -> 0.091546077 | K59: 28 | L59: =K59/$L$30 -> 0.30434783 | M59: =IF(L59<=0.02,"A1",IF(L59<=0.04,"A2",IF(L59<=0.06,"A3",IF(L59<=0.08,"A4",IF(L59<=0.1,"A5",IF(L59<=0.16,"B1",IF(L59<=0.22,"B2",IF(L59<=0.28,"B3",IF(L59<=0.34,"B4",IF(L59<=0.4,"B5",IF(L59<=0.46,"B6",IF(L59<=0.52,"B7",IF(L59<=0.58,"B8",IF(L59<=0.64,"B9",IF(L59<=0.7,"B10",IF(L59<=1.1,"C0")))))))))))))))) -> B4 | N59: =F59*J58-H59 -> 532.20952 | O59: =IF(M59="A1",1650000,IF(M59="A2",1290000,IF(M59="A3",1020000,IF(M59="A4",810000,IF(M59="A5",650000,IF(M59="B1",520000,IF(M59="B2",420000,IF(M59="B3",330000,IF(M59="B4",270000,IF(M59="B5",210000,IF(M59="B6",170000,IF(M59="B7",150000,IF(M59="B8",130000,IF(M59="B9",100000,IF(M59="B10",60000,IF(M59="C0",0)))))))))))))))) -> 270000 | P59: =VLOOKUP(E59,'DOMINGO 1'!D:AB,7,0) -> 143787 | Q59: =VLOOKUP(E59,'DOMINGO 2'!D:AB,7,0) -> 128633 | R59: =VLOOKUP(E59,'DOMINGO 3'!D:AB,7,0) -> #N/A | S59: =VLOOKUP(E59,'DOMINGO 1'!D:AB,11,0) -> 7726 | T59: =VLOOKUP(E59,'DOMINGO 2'!D:AB,11,0) -> 2250 | U59: =VLOOKUP(E59,'DOMINGO 3'!D:AB,11,0) -> #N/A | V59: =VLOOKUP(E59,'FESTIVO 1'!D:AB,7,0) -> 143794 | W59: =VLOOKUP(E59,'FESTIVO 1'!D:AB,11,0) -> 11190
E60: M0011(A CHACON) | F60: =VLOOKUP(E60,'ASIGNACION RANKING'!D:AB,7,0)-P60-Q60 -> 1415840 | G60: =VLOOKUP(E60,'ASIGNACION RANKING'!D:AB,6,0) -> 871 | H60: =VLOOKUP(E60,'ASIGNACION RANKING'!D:AB,11,0)-S60-T60 -> 128804 | J60: =H60/F60 -> 0.090973556 | K60: 29 | L60: =K60/$L$30 -> 0.31521739 | M60: =IF(L60<=0.02,"A1",IF(L60<=0.04,"A2",IF(L60<=0.06,"A3",IF(L60<=0.08,"A4",IF(L60<=0.1,"A5",IF(L60<=0.16,"B1",IF(L60<=0.22,"B2",IF(L60<=0.28,"B3",IF(L60<=0.34,"B4",IF(L60<=0.4,"B5",IF(L60<=0.46,"B6",IF(L60<=0.52,"B7",IF(L60<=0.58,"B8",IF(L60<=0.64,"B9",IF(L60<=0.7,"B10",IF(L60<=1.1,"C0")))))))))))))))) -> B4 | N60: =F60*J59-H60 -> 810.59805 | O60: =IF(M60="A1",1650000,IF(M60="A2",1290000,IF(M60="A3",1020000,IF(M60="A4",810000,IF(M60="A5",650000,IF(M60="B1",520000,IF(M60="B2",420000,IF(M60="B3",330000,IF(M60="B4",270000,IF(M60="B5",210000,IF(M60="B6",170000,IF(M60="B7",150000,IF(M60="B8",130000,IF(M60="B9",100000,IF(M60="B10",60000,IF(M60="C0",0)))))))))))))))) -> 270000 | P60: =VLOOKUP(E60,'DOMINGO 1'!D:AB,7,0) -> 123804 | Q60: =VLOOKUP(E60,'DOMINGO 2'!D:AB,7,0) -> 116809 | R60: =VLOOKUP(E60,'DOMINGO 3'!D:AB,7,0) -> #N/A | S60: =VLOOKUP(E60,'DOMINGO 1'!D:AB,11,0) -> 4712 | T60: =VLOOKUP(E60,'DOMINGO 2'!D:AB,11,0) -> 4139 | U60: =VLOOKUP(E60,'DOMINGO 3'!D:AB,11,0) -> #N/A | V60: =VLOOKUP(E60,'FESTIVO 1'!D:AB,7,0) -> 145780 | W60: =VLOOKUP(E60,'FESTIVO 1'!D:AB,11,0) -> 10059
E61: M0176(A LILIANA) | F61: =VLOOKUP(E61,'ASIGNACION RANKING'!D:AB,7,0)-P61-Q61 -> 1306058 | G61: =VLOOKUP(E61,'ASIGNACION RANKING'!D:AB,6,0) -> 911 | H61: =VLOOKUP(E61,'ASIGNACION RANKING'!D:AB,11,0)-S61-T61 -> 118254 | J61: =H61/F61 -> 0.090542686 | K61: 30 | L61: =K61/$L$30 -> 0.32608696 | M61: =IF(L61<=0.02,"A1",IF(L61<=0.04,"A2",IF(L61<=0.06,"A3",IF(L61<=0.08,"A4",IF(L61<=0.1,"A5",IF(L61<=0.16,"B1",IF(L61<=0.22,"B2",IF(L61<=0.28,"B3",IF(L61<=0.34,"B4",IF(L61<=0.4,"B5",IF(L61<=0.46,"B6",IF(L61<=0.52,"B7",IF(L61<=0.58,"B8",IF(L61<=0.64,"B9",IF(L61<=0.7,"B10",IF(L61<=1.1,"C0")))))))))))))))) -> B4 | N61: =F61*J60-H61 -> 562.74104 | O61: =IF(M61="A1",1650000,IF(M61="A2",1290000,IF(M61="A3",1020000,IF(M61="A4",810000,IF(M61="A5",650000,IF(M61="B1",520000,IF(M61="B2",420000,IF(M61="B3",330000,IF(M61="B4",270000,IF(M61="B5",210000,IF(M61="B6",170000,IF(M61="B7",150000,IF(M61="B8",130000,IF(M61="B9",100000,IF(M61="B10",60000,IF(M61="C0",0)))))))))))))))) -> 270000 | P61: =VLOOKUP(E61,'DOMINGO 1'!D:AB,7,0) -> 121685 | Q61: =VLOOKUP(E61,'DOMINGO 2'!D:AB,7,0) -> 121805 | R61: =VLOOKUP(E61,'DOMINGO 3'!D:AB,7,0) -> #N/A | S61: =VLOOKUP(E61,'DOMINGO 1'!D:AB,11,0) -> 13717 | T61: =VLOOKUP(E61,'DOMINGO 2'!D:AB,11,0) -> 8032 | U61: =VLOOKUP(E61,'DOMINGO 3'!D:AB,11,0) -> #N/A | V61: =VLOOKUP(E61,'FESTIVO 1'!D:AB,7,0) -> 112943 | W61: =VLOOKUP(E61,'FESTIVO 1'!D:AB,11,0) -> 9845
E62: M0399(A EFREN) | F62: =VLOOKUP(E62,'ASIGNACION RANKING'!D:AB,7,0)-P62-Q62 -> 1430170 | G62: =VLOOKUP(E62,'ASIGNACION RANKING'!D:AB,6,0) -> 957 | H62: =VLOOKUP(E62,'ASIGNACION RANKING'!D:AB,11,0)-S62-T62 -> 128829 | I62: 12.12 | J62: =H62/F62 -> 0.090079501 | K62: 31 | L62: =K62/$L$30 -> 0.33695652 | M62: =IF(L62<=0.02,"A1",IF(L62<=0.04,"A2",IF(L62<=0.06,"A3",IF(L62<=0.08,"A4",IF(L62<=0.1,"A5",IF(L62<=0.16,"B1",IF(L62<=0.22,"B2",IF(L62<=0.28,"B3",IF(L62<=0.34,"B4",IF(L62<=0.4,"B5",IF(L62<=0.46,"B6",IF(L62<=0.52,"B7",IF(L62<=0.58,"B8",IF(L62<=0.64,"B9",IF(L62<=0.7,"B10",IF(L62<=1.1,"C0")))))))))))))))) -> B4 | N62: =F62*J61-H62 -> 662.4339 | O62: =IF(M62="A1",1650000,IF(M62="A2",1290000,IF(M62="A3",1020000,IF(M62="A4",810000,IF(M62="A5",650000,IF(M62="B1",520000,IF(M62="B2",420000,IF(M62="B3",330000,IF(M62="B4",270000,IF(M62="B5",210000,IF(M62="B6",170000,IF(M62="B7",150000,IF(M62="B8",130000,IF(M62="B9",100000,IF(M62="B10",60000,IF(M62="C0",0)))))))))))))))) -> 270000 | P62: =VLOOKUP(E62,'DOMINGO 1'!D:AB,7,0) -> 131393 | Q62: =VLOOKUP(E62,'DOMINGO 2'!D:AB,7,0) -> 125293 | R62: =VLOOKUP(E62,'DOMINGO 3'!D:AB,7,0) -> #N/A | S62: =VLOOKUP(E62,'DOMINGO 1'!D:AB,11,0) -> 960 | T62: =VLOOKUP(E62,'DOMINGO 2'!D:AB,11,0) -> 7811 | U62: =VLOOKUP(E62,'DOMINGO 3'!D:AB,11,0) -> #N/A | V62: =VLOOKUP(E62,'FESTIVO 1'!D:AB,7,0) -> 143323 | W62: =VLOOKUP(E62,'FESTIVO 1'!D:AB,11,0) -> 5933
E63: A0447(LORENA SALGADO) | F63: =VLOOKUP(E63,'ASIGNACION RANKING'!D:AB,7,0)-P63-Q63 -> 1479191 | G63: =VLOOKUP(E63,'ASIGNACION RANKING'!D:AB,6,0) -> 938 | H63: =VLOOKUP(E63,'ASIGNACION RANKING'!D:AB,11,0)-S63-T63 -> 132105 | J63: =H63/F63 -> 0.089308953 | K63: 32 | L63: =K63/$L$30 -> 0.34782609 | M63: =IF(L63<=0.02,"A1",IF(L63<=0.04,"A2",IF(L63<=0.06,"A3",IF(L63<=0.08,"A4",IF(L63<=0.1,"A5",IF(L63<=0.16,"B1",IF(L63<=0.22,"B2",IF(L63<=0.28,"B3",IF(L63<=0.34,"B4",IF(L63<=0.4,"B5",IF(L63<=0.46,"B6",IF(L63<=0.52,"B7",IF(L63<=0.58,"B8",IF(L63<=0.64,"B9",IF(L63<=0.7,"B10",IF(L63<=1.1,"C0")))))))))))))))) -> B5 | N63: =F63*J62-H63 -> 1139.7872 | O63: =IF(M63="A1",1650000,IF(M63="A2",1290000,IF(M63="A3",1020000,IF(M63="A4",810000,IF(M63="A5",650000,IF(M63="B1",520000,IF(M63="B2",420000,IF(M63="B3",330000,IF(M63="B4",270000,IF(M63="B5",210000,IF(M63="B6",170000,IF(M63="B7",150000,IF(M63="B8",130000,IF(M63="B9",100000,IF(M63="B10",60000,IF(M63="C0",0)))))))))))))))) -> 210000 | P63: =VLOOKUP(E63,'DOMINGO 1'!D:AB,7,0) -> 137639 | Q63: =VLOOKUP(E63,'DOMINGO 2'!D:AB,7,0) -> 121021 | R63: =VLOOKUP(E63,'DOMINGO 3'!D:AB,7,0) -> #N/A | S63: =VLOOKUP(E63,'DOMINGO 1'!D:AB,11,0) -> 7708 | T63: =VLOOKUP(E63,'DOMINGO 2'!D:AB,11,0) -> 5405 | U63: =VLOOKUP(E63,'DOMINGO 3'!D:AB,11,0) -> #N/A | V63: =VLOOKUP(E63,'FESTIVO 1'!D:AB,7,0) -> 152081 | W63: =VLOOKUP(E63,'FESTIVO 1'!D:AB,11,0) -> 9042
E64: M0368(P JULIO) | F64: =VLOOKUP(E64,'ASIGNACION RANKING'!D:AB,7,0)-P64-Q64 -> 1255949 | G64: =VLOOKUP(E64,'ASIGNACION RANKING'!D:AB,6,0) -> 895 | H64: =VLOOKUP(E64,'ASIGNACION RANKING'!D:AB,11,0)-S64-T64 -> 112111 | J64: =H64/F64 -> 0.089263975 | K64: 33 | L64: =K64/$L$30 -> 0.35869565 | M64: =IF(L64<=0.02,"A1",IF(L64<=0.04,"A2",IF(L64<=0.06,"A3",IF(L64<=0.08,"A4",IF(L64<=0.1,"A5",IF(L64<=0.16,"B1",IF(L64<=0.22,"B2",IF(L64<=0.28,"B3",IF(L64<=0.34,"B4",IF(L64<=0.4,"B5",IF(L64<=0.46,"B6",IF(L64<=0.52,"B7",IF(L64<=0.58,"B8",IF(L64<=0.64,"B9",IF(L64<=0.7,"B10",IF(L64<=1.1,"C0")))))))))))))))) -> B5 | N64: =F64*J63-H64 -> 56.490638 | O64: =IF(M64="A1",1650000,IF(M64="A2",1290000,IF(M64="A3",1020000,IF(M64="A4",810000,IF(M64="A5",650000,IF(M64="B1",520000,IF(M64="B2",420000,IF(M64="B3",330000,IF(M64="B4",270000,IF(M64="B5",210000,IF(M64="B6",170000,IF(M64="B7",150000,IF(M64="B8",130000,IF(M64="B9",100000,IF(M64="B10",60000,IF(M64="C0",0)))))))))))))))) -> 210000 | P64: =VLOOKUP(E64,'DOMINGO 1'!D:AB,7,0) -> 129382 | Q64: =VLOOKUP(E64,'DOMINGO 2'!D:AB,7,0) -> 97944 | R64: =VLOOKUP(E64,'DOMINGO 3'!D:AB,7,0) -> #N/A | S64: =VLOOKUP(E64,'DOMINGO 1'!D:AB,11,0) -> 6443 | T64: =VLOOKUP(E64,'DOMINGO 2'!D:AB,11,0) -> 5936 | U64: =VLOOKUP(E64,'DOMINGO 3'!D:AB,11,0) -> #N/A | V64: 0 | W64: =VLOOKUP(E64,'FESTIVO 1'!D:AB,11,0) -> 6395
E65: A0096(NATALYA PACHECO) | F65: =VLOOKUP(E65,'ASIGNACION RANKING'!D:AB,7,0)-P65-Q65 -> 1461424 | G65: =VLOOKUP(E65,'ASIGNACION RANKING'!D:AB,6,0) -> 922 | H65: =VLOOKUP(E65,'ASIGNACION RANKING'!D:AB,11,0)-S65-T65 -> 129461 | J65: =H65/F65 -> 0.088585517 | K65: 34 | L65: =K65/$L$30 -> 0.36956522 | M65: =IF(L65<=0.02,"A1",IF(L65<=0.04,"A2",IF(L65<=0.06,"A3",IF(L65<=0.08,"A4",IF(L65<=0.1,"A5",IF(L65<=0.16,"B1",IF(L65<=0.22,"B2",IF(L65<=0.28,"B3",IF(L65<=0.34,"B4",IF(L65<=0.4,"B5",IF(L65<=0.46,"B6",IF(L65<=0.52,"B7",IF(L65<=0.58,"B8",IF(L65<=0.64,"B9",IF(L65<=0.7,"B10",IF(L65<=1.1,"C0")))))))))))))))) -> B5 | N65: =F65*J64-H65 -> 991.51524 | O65: =IF(M65="A1",1650000,IF(M65="A2",1290000,IF(M65="A3",1020000,IF(M65="A4",810000,IF(M65="A5",650000,IF(M65="B1",520000,IF(M65="B2",420000,IF(M65="B3",330000,IF(M65="B4",270000,IF(M65="B5",210000,IF(M65="B6",170000,IF(M65="B7",150000,IF(M65="B8",130000,IF(M65="B9",100000,IF(M65="B10",60000,IF(M65="C0",0)))))))))))))))) -> 210000 | P65: =VLOOKUP(E65,'DOMINGO 1'!D:AB,7,0) -> 130446 | Q65: =VLOOKUP(E65,'DOMINGO 2'!D:AB,7,0) -> 105178 | R65: =VLOOKUP(E65,'DOMINGO 3'!D:AB,7,0) -> #N/A | S65: =VLOOKUP(E65,'DOMINGO 1'!D:AB,11,0) -> 7024 | T65: =VLOOKUP(E65,'DOMINGO 2'!D:AB,11,0) -> 7590 | U65: =VLOOKUP(E65,'DOMINGO 3'!D:AB,11,0) -> #N/A | V65: 0 | W65: =VLOOKUP(E65,'FESTIVO 1'!D:AB,11,0) -> 11900
E66: M0449(P FATIMA) | F66: =VLOOKUP(E66,'ASIGNACION RANKING'!D:AB,7,0)-P66-Q66 -> 1406995 | G66: =VLOOKUP(E66,'ASIGNACION RANKING'!D:AB,6,0) -> 964 | H66: =VLOOKUP(E66,'ASIGNACION RANKING'!D:AB,11,0)-S66-T66 -> 124045 | J66: =H66/F66 -> 0.088163071 | K66: 35 | L66: =K66/$L$30 -> 0.38043478 | M66: =IF(L66<=0.02,"A1",IF(L66<=0.04,"A2",IF(L66<=0.06,"A3",IF(L66<=0.08,"A4",IF(L66<=0.1,"A5",IF(L66<=0.16,"B1",IF(L66<=0.22,"B2",IF(L66<=0.28,"B3",IF(L66<=0.34,"B4",IF(L66<=0.4,"B5",IF(L66<=0.46,"B6",IF(L66<=0.52,"B7",IF(L66<=0.58,"B8",IF(L66<=0.64,"B9",IF(L66<=0.7,"B10",IF(L66<=1.1,"C0")))))))))))))))) -> B5 | N66: =F66*J65-H66 -> 594.37892 | O66: =IF(M66="A1",1650000,IF(M66="A2",1290000,IF(M66="A3",1020000,IF(M66="A4",810000,IF(M66="A5",650000,IF(M66="B1",520000,IF(M66="B2",420000,IF(M66="B3",330000,IF(M66="B4",270000,IF(M66="B5",210000,IF(M66="B6",170000,IF(M66="B7",150000,IF(M66="B8",130000,IF(M66="B9",100000,IF(M66="B10",60000,IF(M66="C0",0)))))))))))))))) -> 210000 | P66: =VLOOKUP(E66,'DOMINGO 1'!D:AB,7,0) -> 125107 | Q66: =VLOOKUP(E66,'DOMINGO 2'!D:AB,7,0) -> 133328 | R66: =VLOOKUP(E66,'DOMINGO 3'!D:AB,7,0) -> #N/A | S66: =VLOOKUP(E66,'DOMINGO 1'!D:AB,11,0) -> 7966 | T66: =VLOOKUP(E66,'DOMINGO 2'!D:AB,11,0) -> 1480 | U66: =VLOOKUP(E66,'DOMINGO 3'!D:AB,11,0) -> #N/A | V66: 0 | W66: =VLOOKUP(E66,'FESTIVO 1'!D:AB,11,0) -> 5665
E67: A0017(NICOLARY MONTES) | F67: =VLOOKUP(E67,'ASIGNACION RANKING'!D:AB,7,0)-P67-Q67 -> 1399846 | G67: =VLOOKUP(E67,'ASIGNACION RANKING'!D:AB,6,0) -> 978 | H67: =VLOOKUP(E67,'ASIGNACION RANKING'!D:AB,11,0)-S67-T67 -> 123297 | I67: 16.12 | J67: =H67/F67 -> 0.088078974 | K67: 36 | L67: =K67/$L$30 -> 0.39130435 | M67: =IF(L67<=0.02,"A1",IF(L67<=0.04,"A2",IF(L67<=0.06,"A3",IF(L67<=0.08,"A4",IF(L67<=0.1,"A5",IF(L67<=0.16,"B1",IF(L67<=0.22,"B2",IF(L67<=0.28,"B3",IF(L67<=0.34,"B4",IF(L67<=0.4,"B5",IF(L67<=0.46,"B6",IF(L67<=0.52,"B7",IF(L67<=0.58,"B8",IF(L67<=0.64,"B9",IF(L67<=0.7,"B10",IF(L67<=1.1,"C0")))))))))))))))) -> B5 | N67: =F67*J66-H67 -> 117.72221 | O67: =IF(M67="A1",1650000,IF(M67="A2",1290000,IF(M67="A3",1020000,IF(M67="A4",810000,IF(M67="A5",650000,IF(M67="B1",520000,IF(M67="B2",420000,IF(M67="B3",330000,IF(M67="B4",270000,IF(M67="B5",210000,IF(M67="B6",170000,IF(M67="B7",150000,IF(M67="B8",130000,IF(M67="B9",100000,IF(M67="B10",60000,IF(M67="C0",0)))))))))))))))) -> 210000 | P67: =VLOOKUP(E67,'DOMINGO 1'!D:AB,7,0) -> 114499 | Q67: =VLOOKUP(E67,'DOMINGO 2'!D:AB,7,0) -> 112857 | R67: =VLOOKUP(E67,'DOMINGO 3'!D:AB,7,0) -> #N/A | S67: =VLOOKUP(E67,'DOMINGO 1'!D:AB,11,0) -> 8430 | T67: =VLOOKUP(E67,'DOMINGO 2'!D:AB,11,0) -> 3007 | U67: =VLOOKUP(E67,'DOMINGO 3'!D:AB,11,0) -> #N/A | V67: =VLOOKUP(E67,'FESTIVO 1'!D:AB,7,0) -> 108939 | W67: =VLOOKUP(E67,'FESTIVO 1'!D:AB,11,0) -> 11047
E68: A0134(Jessica Fernanda Porras) | F68: =VLOOKUP(E68,'ASIGNACION RANKING'!D:AB,7,0)-P68-Q68 -> 1467542 | G68: =VLOOKUP(E68,'ASIGNACION RANKING'!D:AB,6,0) -> 964 | H68: =VLOOKUP(E68,'ASIGNACION RANKING'!D:AB,11,0)-S68-T68 -> 129009 | I68: 2.12 | J68: =H68/F68 -> 0.087908217 | K68: 37 | L68: =K68/$L$30 -> 0.40217391 | M68: =IF(L68<=0.02,"A1",IF(L68<=0.04,"A2",IF(L68<=0.06,"A3",IF(L68<=0.08,"A4",IF(L68<=0.1,"A5",IF(L68<=0.16,"B1",IF(L68<=0.22,"B2",IF(L68<=0.28,"B3",IF(L68<=0.34,"B4",IF(L68<=0.4,"B5",IF(L68<=0.46,"B6",IF(L68<=0.52,"B7",IF(L68<=0.58,"B8",IF(L68<=0.64,"B9",IF(L68<=0.7,"B10",IF(L68<=1.1,"C0")))))))))))))))) -> B6 | N68: =F68*J67-H68 -> 250.59425 | O68: =IF(M68="A1",1650000,IF(M68="A2",1290000,IF(M68="A3",1020000,IF(M68="A4",810000,IF(M68="A5",650000,IF(M68="B1",520000,IF(M68="B2",420000,IF(M68="B3",330000,IF(M68="B4",270000,IF(M68="B5",210000,IF(M68="B6",170000,IF(M68="B7",150000,IF(M68="B8",130000,IF(M68="B9",100000,IF(M68="B10",60000,IF(M68="C0",0)))))))))))))))) -> 170000 | P68: =VLOOKUP(E68,'DOMINGO 1'!D:AB,7,0) -> 107673 | Q68: =VLOOKUP(E68,'DOMINGO 2'!D:AB,7,0) -> 132189 | R68: =VLOOKUP(E68,'DOMINGO 3'!D:AB,7,0) -> #N/A | S68: =VLOOKUP(E68,'DOMINGO 1'!D:AB,11,0) -> 2291 | T68: =VLOOKUP(E68,'DOMINGO 2'!D:AB,11,0) -> 6895 | U68: =VLOOKUP(E68,'DOMINGO 3'!D:AB,11,0) -> #N/A | V68: =VLOOKUP(E68,'FESTIVO 1'!D:AB,7,0) -> 125928 | W68: =VLOOKUP(E68,'FESTIVO 1'!D:AB,11,0) -> 19669
E69: M0022(A YOLANDA) | F69: =VLOOKUP(E69,'ASIGNACION RANKING'!D:AB,7,0)-P69-Q69 -> 1335659 | G69: =VLOOKUP(E69,'ASIGNACION RANKING'!D:AB,6,0) -> 881 | H69: =VLOOKUP(E69,'ASIGNACION RANKING'!D:AB,11,0)-S69-T69 -> 116994 | J69: =H69/F69 -> 0.087592716 | K69: 38 | L69: =K69/$L$30 -> 0.41304348 | M69: =IF(L69<=0.02,"A1",IF(L69<=0.04,"A2",IF(L69<=0.06,"A3",IF(L69<=0.08,"A4",IF(L69<=0.1,"A5",IF(L69<=0.16,"B1",IF(L69<=0.22,"B2",IF(L69<=0.28,"B3",IF(L69<=0.34,"B4",IF(L69<=0.4,"B5",IF(L69<=0.46,"B6",IF(L69<=0.52,"B7",IF(L69<=0.58,"B8",IF(L69<=0.64,"B9",IF(L69<=0.7,"B10",IF(L69<=1.1,"C0")))))))))))))))) -> B6 | N69: =F69*J68-H69 -> 421.40067 | O69: =IF(M69="A1",1650000,IF(M69="A2",1290000,IF(M69="A3",1020000,IF(M69="A4",810000,IF(M69="A5",650000,IF(M69="B1",520000,IF(M69="B2",420000,IF(M69="B3",330000,IF(M69="B4",270000,IF(M69="B5",210000,IF(M69="B6",170000,IF(M69="B7",150000,IF(M69="B8",130000,IF(M69="B9",100000,IF(M69="B10",60000,IF(M69="C0",0)))))))))))))))) -> 170000 | P69: =VLOOKUP(E69,'DOMINGO 1'!D:AB,7,0) -> 117955 | Q69: =VLOOKUP(E69,'DOMINGO 2'!D:AB,7,0) -> 116470 | R69: =VLOOKUP(E69,'DOMINGO 3'!D:AB,7,0) -> #N/A | S69: =VLOOKUP(E69,'DOMINGO 1'!D:AB,11,0) -> 4915 | T69: =VLOOKUP(E69,'DOMINGO 2'!D:AB,11,0) -> 2735 | U69: =VLOOKUP(E69,'DOMINGO 3'!D:AB,11,0) -> #N/A | V69: 0 | W69: =VLOOKUP(E69,'FESTIVO 1'!D:AB,11,0) -> 16471
E70: A0249(DANIEL MAYORGA) | F70: =VLOOKUP(E70,'ASIGNACION RANKING'!D:AB,7,0)-P70-Q70 -> 1375501 | G70: =VLOOKUP(E70,'ASIGNACION RANKING'!D:AB,6,0) -> 934 | H70: =VLOOKUP(E70,'ASIGNACION RANKING'!D:AB,11,0)-S70-T70 -> 120001 | J70: =H70/F70 -> 0.087241667 | K70: 39 | L70: =K70/$L$30 -> 0.42391304 | M70: =IF(L70<=0.02,"A1",IF(L70<=0.04,"A2",IF(L70<=0.06,"A3",IF(L70<=0.08,"A4",IF(L70<=0.1,"A5",IF(L70<=0.16,"B1",IF(L70<=0.22,"B2",IF(L70<=0.28,"B3",IF(L70<=0.34,"B4",IF(L70<=0.4,"B5",IF(L70<=0.46,"B6",IF(L70<=0.52,"B7",IF(L70<=0.58,"B8",IF(L70<=0.64,"B9",IF(L70<=0.7,"B10",IF(L70<=1.1,"C0")))))))))))))))) -> B6 | N70: =F70*J69-H70 -> 482.86901 | O70: =IF(M70="A1",1650000,IF(M70="A2",1290000,IF(M70="A3",1020000,IF(M70="A4",810000,IF(M70="A5",650000,IF(M70="B1",520000,IF(M70="B2",420000,IF(M70="B3",330000,IF(M70="B4",270000,IF(M70="B5",210000,IF(M70="B6",170000,IF(M70="B7",150000,IF(M70="B8",130000,IF(M70="B9",100000,IF(M70="B10",60000,IF(M70="C0",0)))))))))))))))) -> 170000 | P70: =VLOOKUP(E70,'DOMINGO 1'!D:AB,7,0) -> 123239 | Q70: =VLOOKUP(E70,'DOMINGO 2'!D:AB,7,0) -> 126718 | R70: =VLOOKUP(E70,'DOMINGO 3'!D:AB,7,0) -> #N/A | S70: =VLOOKUP(E70,'DOMINGO 1'!D:AB,11,0) -> 5526 | T70: =VLOOKUP(E70,'DOMINGO 2'!D:AB,11,0) -> 6781 | U70: =VLOOKUP(E70,'DOMINGO 3'!D:AB,11,0) -> #N/A | V70: =VLOOKUP(E70,'FESTIVO 1'!D:AB,7,0) -> 130913 | W70: =VLOOKUP(E70,'FESTIVO 1'!D:AB,11,0) -> 13188
E71: M0119(P JESUS) | F71: =VLOOKUP(E71,'ASIGNACION RANKING'!D:AB,7,0)-P71-Q71 -> 1629255 | G71: =VLOOKUP(E71,'ASIGNACION RANKING'!D:AB,6,0) -> 948 | H71: =VLOOKUP(E71,'ASIGNACION RANKING'!D:AB,11,0)-S71-T71 -> 141994 | J71: =H71/F71 -> 0.087152717 | K71: 40 | L71: =K71/$L$30 -> 0.43478261 | M71: =IF(L71<=0.02,"A1",IF(L71<=0.04,"A2",IF(L71<=0.06,"A3",IF(L71<=0.08,"A4",IF(L71<=0.1,"A5",IF(L71<=0.16,"B1",IF(L71<=0.22,"B2",IF(L71<=0.28,"B3",IF(L71<=0.34,"B4",IF(L71<=0.4,"B5",IF(L71<=0.46,"B6",IF(L71<=0.52,"B7",IF(L71<=0.58,"B8",IF(L71<=0.64,"B9",IF(L71<=0.7,"B10",IF(L71<=1.1,"C0")))))))))))))))) -> B6 | N71: =F71*J70-H71 -> 144.92193 | O71: =IF(M71="A1",1650000,IF(M71="A2",1290000,IF(M71="A3",1020000,IF(M71="A4",810000,IF(M71="A5",650000,IF(M71="B1",520000,IF(M71="B2",420000,IF(M71="B3",330000,IF(M71="B4",270000,IF(M71="B5",210000,IF(M71="B6",170000,IF(M71="B7",150000,IF(M71="B8",130000,IF(M71="B9",100000,IF(M71="B10",60000,IF(M71="C0",0)))))))))))))))) -> 170000 | P71: =VLOOKUP(E71,'DOMINGO 1'!D:AB,7,0) -> 137128 | Q71: =VLOOKUP(E71,'DOMINGO 2'!D:AB,7,0) -> 137564 | R71: =VLOOKUP(E71,'DOMINGO 3'!D:AB,7,0) -> #N/A | S71: =VLOOKUP(E71,'DOMINGO 1'!D:AB,11,0) -> 3870 | T71: =VLOOKUP(E71,'DOMINGO 2'!D:AB,11,0) -> 3869 | U71: =VLOOKUP(E71,'DOMINGO 3'!D:AB,11,0) -> #N/A | V71: 0 | W71: =VLOOKUP(E71,'FESTIVO 1'!D:AB,11,0) -> 8527
E72: M0124(P LIZET) | F72: =VLOOKUP(E72,'ASIGNACION RANKING'!D:AB,7,0)-P72-Q72 -> 1296138 | G72: =VLOOKUP(E72,'ASIGNACION RANKING'!D:AB,6,0) -> 948 | H72: =VLOOKUP(E72,'ASIGNACION RANKING'!D:AB,11,0)-S72-T72 -> 111726 | J72: =H72/F72 -> 0.086199155 | K72: 41 | L72: =K72/$L$30 -> 0.44565217 | M72: =IF(L72<=0.02,"A1",IF(L72<=0.04,"A2",IF(L72<=0.06,"A3",IF(L72<=0.08,"A4",IF(L72<=0.1,"A5",IF(L72<=0.16,"B1",IF(L72<=0.22,"B2",IF(L72<=0.28,"B3",IF(L72<=0.34,"B4",IF(L72<=0.4,"B5",IF(L72<=0.46,"B6",IF(L72<=0.52,"B7",IF(L72<=0.58,"B8",IF(L72<=0.64,"B9",IF(L72<=0.7,"B10",IF(L72<=1.1,"C0")))))))))))))))) -> B6 | N72: =F72*J71-H72 -> 1235.9484 | O72: =IF(M72="A1",1650000,IF(M72="A2",1290000,IF(M72="A3",1020000,IF(M72="A4",810000,IF(M72="A5",650000,IF(M72="B1",520000,IF(M72="B2",420000,IF(M72="B3",330000,IF(M72="B4",270000,IF(M72="B5",210000,IF(M72="B6",170000,IF(M72="B7",150000,IF(M72="B8",130000,IF(M72="B9",100000,IF(M72="B10",60000,IF(M72="C0",0)))))))))))))))) -> 170000 | P72: =VLOOKUP(E72,'DOMINGO 1'!D:AB,7,0) -> 132542 | Q72: =VLOOKUP(E72,'DOMINGO 2'!D:AB,7,0) -> 107638 | R72: =VLOOKUP(E72,'DOMINGO 3'!D:AB,7,0) -> #N/A | S72: =VLOOKUP(E72,'DOMINGO 1'!D:AB,11,0) -> 6290 | T72: =VLOOKUP(E72,'DOMINGO 2'!D:AB,11,0) -> 9928 | U72: =VLOOKUP(E72,'DOMINGO 3'!D:AB,11,0) -> #N/A | V72: =VLOOKUP(E72,'FESTIVO 1'!D:AB,7,0) -> 106214 | W72: =VLOOKUP(E72,'FESTIVO 1'!D:AB,11,0) -> 11549
E73: A0144(DANIEL HERNANDEZ) | F73: =VLOOKUP(E73,'ASIGNACION RANKING'!D:AB,7,0)-P73-Q73 -> 1462441 | G73: =VLOOKUP(E73,'ASIGNACION RANKING'!D:AB,6,0) -> 950 | H73: =VLOOKUP(E73,'ASIGNACION RANKING'!D:AB,11,0)-S73-T73 -> 125888 | J73: =H73/F73 -> 0.086080738 | K73: 42 | L73: =K73/$L$30 -> 0.45652174 | M73: =IF(L73<=0.02,"A1",IF(L73<=0.04,"A2",IF(L73<=0.06,"A3",IF(L73<=0.08,"A4",IF(L73<=0.1,"A5",IF(L73<=0.16,"B1",IF(L73<=0.22,"B2",IF(L73<=0.28,"B3",IF(L73<=0.34,"B4",IF(L73<=0.4,"B5",IF(L73<=0.46,"B6",IF(L73<=0.52,"B7",IF(L73<=0.58,"B8",IF(L73<=0.64,"B9",IF(L73<=0.7,"B10",IF(L73<=1.1,"C0")))))))))))))))) -> B6 | N73: =F73*J72-H73 -> 173.17803 | O73: =IF(M73="A1",1650000,IF(M73="A2",1290000,IF(M73="A3",1020000,IF(M73="A4",810000,IF(M73="A5",650000,IF(M73="B1",520000,IF(M73="B2",420000,IF(M73="B3",330000,IF(M73="B4",270000,IF(M73="B5",210000,IF(M73="B6",170000,IF(M73="B7",150000,IF(M73="B8",130000,IF(M73="B9",100000,IF(M73="B10",60000,IF(M73="C0",0)))))))))))))))) -> 170000 | P73: =VLOOKUP(E73,'DOMINGO 1'!D:AB,7,0) -> 146973 | Q73: =VLOOKUP(E73,'DOMINGO 2'!D:AB,7,0) -> 126974 | R73: =VLOOKUP(E73,'DOMINGO 3'!D:AB,7,0) -> #N/A | S73: =VLOOKUP(E73,'DOMINGO 1'!D:AB,11,0) -> 6538 | T73: =VLOOKUP(E73,'DOMINGO 2'!D:AB,11,0) -> 11365 | U73: =VLOOKUP(E73,'DOMINGO 3'!D:AB,11,0) -> #N/A | V73: 0 | W73: =VLOOKUP(E73,'FESTIVO 1'!D:AB,11,0) -> 11677
E74: A0128(LEIDY TORRES) | F74: =VLOOKUP(E74,'ASIGNACION RANKING'!D:AB,7,0)-P74-Q74 -> 1472361 | G74: =VLOOKUP(E74,'ASIGNACION RANKING'!D:AB,6,0) -> 1002 | H74: =VLOOKUP(E74,'ASIGNACION RANKING'!D:AB,11,0)-S74-T74 -> 125496 | J74: =H74/F74 -> 0.085234531 | K74: 43 | L74: =K74/$L$30 -> 0.4673913 | M74: =IF(L74<=0.02,"A1",IF(L74<=0.04,"A2",IF(L74<=0.06,"A3",IF(L74<=0.08,"A4",IF(L74<=0.1,"A5",IF(L74<=0.16,"B1",IF(L74<=0.22,"B2",IF(L74<=0.28,"B3",IF(L74<=0.34,"B4",IF(L74<=0.4,"B5",IF(L74<=0.46,"B6",IF(L74<=0.52,"B7",IF(L74<=0.58,"B8",IF(L74<=0.64,"B9",IF(L74<=0.7,"B10",IF(L74<=1.1,"C0")))))))))))))))) -> B7 | N74: =F74*J73-H74 -> 1245.9209 | O74: =IF(M74="A1",1650000,IF(M74="A2",1290000,IF(M74="A3",1020000,IF(M74="A4",810000,IF(M74="A5",650000,IF(M74="B1",520000,IF(M74="B2",420000,IF(M74="B3",330000,IF(M74="B4",270000,IF(M74="B5",210000,IF(M74="B6",170000,IF(M74="B7",150000,IF(M74="B8",130000,IF(M74="B9",100000,IF(M74="B10",60000,IF(M74="C0",0)))))))))))))))) -> 150000 | P74: =VLOOKUP(E74,'DOMINGO 1'!D:AB,7,0) -> 125992 | Q74: =VLOOKUP(E74,'DOMINGO 2'!D:AB,7,0) -> 136031 | R74: =VLOOKUP(E74,'DOMINGO 3'!D:AB,7,0) -> #N/A | S74: =VLOOKUP(E74,'DOMINGO 1'!D:AB,11,0) -> 6647 | T74: =VLOOKUP(E74,'DOMINGO 2'!D:AB,11,0) -> 2252 | U74: =VLOOKUP(E74,'DOMINGO 3'!D:AB,11,0) -> #N/A | V74: =VLOOKUP(E74,'FESTIVO 1'!D:AB,7,0) -> 126710 | W74: =VLOOKUP(E74,'FESTIVO 1'!D:AB,11,0) -> 12760
E75: M0332(P KAREN) | F75: =VLOOKUP(E75,'ASIGNACION RANKING'!D:AB,7,0)-P75-Q75 -> 1404335 | G75: =VLOOKUP(E75,'ASIGNACION RANKING'!D:AB,6,0) -> 975 | H75: =VLOOKUP(E75,'ASIGNACION RANKING'!D:AB,11,0)-S75-T75 -> 119365 | J75: =H75/F75 -> 0.084997526 | K75: 44 | L75: =K75/$L$30 -> 0.47826087 | M75: =IF(L75<=0.02,"A1",IF(L75<=0.04,"A2",IF(L75<=0.06,"A3",IF(L75<=0.08,"A4",IF(L75<=0.1,"A5",IF(L75<=0.16,"B1",IF(L75<=0.22,"B2",IF(L75<=0.28,"B3",IF(L75<=0.34,"B4",IF(L75<=0.4,"B5",IF(L75<=0.46,"B6",IF(L75<=0.52,"B7",IF(L75<=0.58,"B8",IF(L75<=0.64,"B9",IF(L75<=0.7,"B10",IF(L75<=1.1,"C0")))))))))))))))) -> B7 | N75: =F75*J74-H75 -> 332.83576 | O75: =IF(M75="A1",1650000,IF(M75="A2",1290000,IF(M75="A3",1020000,IF(M75="A4",810000,IF(M75="A5",650000,IF(M75="B1",520000,IF(M75="B2",420000,IF(M75="B3",330000,IF(M75="B4",270000,IF(M75="B5",210000,IF(M75="B6",170000,IF(M75="B7",150000,IF(M75="B8",130000,IF(M75="B9",100000,IF(M75="B10",60000,IF(M75="C0",0)))))))))))))))) -> 150000 | P75: =VLOOKUP(E75,'DOMINGO 1'!D:AB,7,0) -> 160303 | Q75: =VLOOKUP(E75,'DOMINGO 2'!D:AB,7,0) -> 108455 | R75: =VLOOKUP(E75,'DOMINGO 3'!D:AB,7,0) -> #N/A | S75: =VLOOKUP(E75,'DOMINGO 1'!D:AB,11,0) -> 4478 | T75: =VLOOKUP(E75,'DOMINGO 2'!D:AB,11,0) -> 4307 | U75: =VLOOKUP(E75,'DOMINGO 3'!D:AB,11,0) -> #N/A | V75: =VLOOKUP(E75,'FESTIVO 1'!D:AB,7,0) -> 149897 | W75: =VLOOKUP(E75,'FESTIVO 1'!D:AB,11,0) -> 5752
E76: A0022(Lorena Portacio) | F76: =VLOOKUP(E76,'ASIGNACION RANKING'!D:AB,7,0)-P76-Q76 -> 1333664 | G76: =VLOOKUP(E76,'ASIGNACION RANKING'!D:AB,6,0) -> 951 | H76: =VLOOKUP(E76,'ASIGNACION RANKING'!D:AB,11,0)-S76-T76 -> 113219 | J76: =H76/F76 -> 0.084893196 | K76: 45 | L76: =K76/$L$30 -> 0.48913043 | M76: =IF(L76<=0.02,"A1",IF(L76<=0.04,"A2",IF(L76<=0.06,"A3",IF(L76<=0.08,"A4",IF(L76<=0.1,"A5",IF(L76<=0.16,"B1",IF(L76<=0.22,"B2",IF(L76<=0.28,"B3",IF(L76<=0.34,"B4",IF(L76<=0.4,"B5",IF(L76<=0.46,"B6",IF(L76<=0.52,"B7",IF(L76<=0.58,"B8",IF(L76<=0.64,"B9",IF(L76<=0.7,"B10",IF(L76<=1.1,"C0")))))))))))))))) -> B7 | N76: =F76*J75-H76 -> 139.13987 | O76: =IF(M76="A1",1650000,IF(M76="A2",1290000,IF(M76="A3",1020000,IF(M76="A4",810000,IF(M76="A5",650000,IF(M76="B1",520000,IF(M76="B2",420000,IF(M76="B3",330000,IF(M76="B4",270000,IF(M76="B5",210000,IF(M76="B6",170000,IF(M76="B7",150000,IF(M76="B8",130000,IF(M76="B9",100000,IF(M76="B10",60000,IF(M76="C0",0)))))))))))))))) -> 150000 | P76: =VLOOKUP(E76,'DOMINGO 1'!D:AB,7,0) -> 137208 | Q76: =VLOOKUP(E76,'DOMINGO 2'!D:AB,7,0) -> 108883 | R76: =VLOOKUP(E76,'DOMINGO 3'!D:AB,7,0) -> #N/A | S76: =VLOOKUP(E76,'DOMINGO 1'!D:AB,11,0) -> 9579 | T76: =VLOOKUP(E76,'DOMINGO 2'!D:AB,11,0) -> 4018 | U76: =VLOOKUP(E76,'DOMINGO 3'!D:AB,11,0) -> #N/A | V76: 0 | W76: =VLOOKUP(E76,'FESTIVO 1'!D:AB,11,0) -> 6504
E77: A0232(PAU ALDANA) | F77: =VLOOKUP(E77,'ASIGNACION RANKING'!D:AB,7,0)-P77-Q77 -> 1319544 | G77: =VLOOKUP(E77,'ASIGNACION RANKING'!D:AB,6,0) -> 956 | H77: =VLOOKUP(E77,'ASIGNACION RANKING'!D:AB,11,0)-S77-T77 -> 111853 | J77: =H77/F77 -> 0.084766404 | K77: 46 | L77: =K77/$L$30 -> 0.5 | M77: =IF(L77<=0.02,"A1",IF(L77<=0.04,"A2",IF(L77<=0.06,"A3",IF(L77<=0.08,"A4",IF(L77<=0.1,"A5",IF(L77<=0.16,"B1",IF(L77<=0.22,"B2",IF(L77<=0.28,"B3",IF(L77<=0.34,"B4",IF(L77<=0.4,"B5",IF(L77<=0.46,"B6",IF(L77<=0.52,"B7",IF(L77<=0.58,"B8",IF(L77<=0.64,"B9",IF(L77<=0.7,"B10",IF(L77<=1.1,"C0")))))))))))))))) -> B7 | N77: =F77*J76-H77 -> 167.30807 | O77: =IF(M77="A1",1650000,IF(M77="A2",1290000,IF(M77="A3",1020000,IF(M77="A4",810000,IF(M77="A5",650000,IF(M77="B1",520000,IF(M77="B2",420000,IF(M77="B3",330000,IF(M77="B4",270000,IF(M77="B5",210000,IF(M77="B6",170000,IF(M77="B7",150000,IF(M77="B8",130000,IF(M77="B9",100000,IF(M77="B10",60000,IF(M77="C0",0)))))))))))))))) -> 150000 | P77: =VLOOKUP(E77,'DOMINGO 1'!D:AB,7,0) -> 119412 | Q77: =VLOOKUP(E77,'DOMINGO 2'!D:AB,7,0) -> 116136 | R77: =VLOOKUP(E77,'DOMINGO 3'!D:AB,7,0) -> #N/A | S77: =VLOOKUP(E77,'DOMINGO 1'!D:AB,11,0) -> 3083 | T77: =VLOOKUP(E77,'DOMINGO 2'!D:AB,11,0) -> 8970 | U77: =VLOOKUP(E77,'DOMINGO 3'!D:AB,11,0) -> #N/A | V77: 0 | W77: =VLOOKUP(E77,'FESTIVO 1'!D:AB,11,0) -> 7256
E78: M0434(P ARTURO) | F78: =VLOOKUP(E78,'ASIGNACION RANKING'!D:AB,7,0)-P78-Q78 -> 1455678 | G78: =VLOOKUP(E78,'ASIGNACION RANKING'!D:AB,6,0) -> 957 | H78: =VLOOKUP(E78,'ASIGNACION RANKING'!D:AB,11,0)-S78-T78 -> 123103 | J78: =H78/F78 -> 0.084567466 | K78: 47 | L78: =K78/$L$30 -> 0.51086957 | M78: =IF(L78<=0.02,"A1",IF(L78<=0.04,"A2",IF(L78<=0.06,"A3",IF(L78<=0.08,"A4",IF(L78<=0.1,"A5",IF(L78<=0.16,"B1",IF(L78<=0.22,"B2",IF(L78<=0.28,"B3",IF(L78<=0.34,"B4",IF(L78<=0.4,"B5",IF(L78<=0.46,"B6",IF(L78<=0.52,"B7",IF(L78<=0.58,"B8",IF(L78<=0.64,"B9",IF(L78<=0.7,"B10",IF(L78<=1.1,"C0")))))))))))))))) -> B7 | N78: =F78*J77-H78 -> 289.58966 | O78: =IF(M78="A1",1650000,IF(M78="A2",1290000,IF(M78="A3",1020000,IF(M78="A4",810000,IF(M78="A5",650000,IF(M78="B1",520000,IF(M78="B2",420000,IF(M78="B3",330000,IF(M78="B4",270000,IF(M78="B5",210000,IF(M78="B6",170000,IF(M78="B7",150000,IF(M78="B8",130000,IF(M78="B9",100000,IF(M78="B10",60000,IF(M78="C0",0)))))))))))))))) -> 150000 | P78: =VLOOKUP(E78,'DOMINGO 1'!D:AB,7,0) -> 140496 | Q78: =VLOOKUP(E78,'DOMINGO 2'!D:AB,7,0) -> 135898 | R78: =VLOOKUP(E78,'DOMINGO 3'!D:AB,7,0) -> #N/A | S78: =VLOOKUP(E78,'DOMINGO 1'!D:AB,11,0) -> 690 | T78: =VLOOKUP(E78,'DOMINGO 2'!D:AB,11,0) -> 6683 | U78: =VLOOKUP(E78,'DOMINGO 3'!D:AB,11,0) -> #N/A | V78: =VLOOKUP(E78,'FESTIVO 1'!D:AB,7,0) -> 108261 | W78: =VLOOKUP(E78,'FESTIVO 1'!D:AB,11,0) -> 11614
E79: A0151(ALISSON CARRERO) | F79: =VLOOKUP(E79,'ASIGNACION RANKING'!D:AB,7,0)-P79-Q79 -> 1291435 | G79: =VLOOKUP(E79,'ASIGNACION RANKING'!D:AB,6,0) -> 925 | H79: =VLOOKUP(E79,'ASIGNACION RANKING'!D:AB,11,0)-S79-T79 -> 108491 | I79: 18.12 | J79: =H79/F79 -> 0.0840081 | K79: 48 | L79: =K79/$L$30 -> 0.52173913 | M79: =IF(L79<=0.02,"A1",IF(L79<=0.04,"A2",IF(L79<=0.06,"A3",IF(L79<=0.08,"A4",IF(L79<=0.1,"A5",IF(L79<=0.16,"B1",IF(L79<=0.22,"B2",IF(L79<=0.28,"B3",IF(L79<=0.34,"B4",IF(L79<=0.4,"B5",IF(L79<=0.46,"B6",IF(L79<=0.52,"B7",IF(L79<=0.58,"B8",IF(L79<=0.64,"B9",IF(L79<=0.7,"B10",IF(L79<=1.1,"C0")))))))))))))))) -> B8 | N79: =F79*J78-H79 -> 722.38566 | O79: =IF(M79="A1",1650000,IF(M79="A2",1290000,IF(M79="A3",1020000,IF(M79="A4",810000,IF(M79="A5",650000,IF(M79="B1",520000,IF(M79="B2",420000,IF(M79="B3",330000,IF(M79="B4",270000,IF(M79="B5",210000,IF(M79="B6",170000,IF(M79="B7",150000,IF(M79="B8",130000,IF(M79="B9",100000,IF(M79="B10",60000,IF(M79="C0",0)))))))))))))))) -> 130000 | P79: =VLOOKUP(E79,'DOMINGO 1'!D:AB,7,0) -> 101216 | Q79: =VLOOKUP(E79,'DOMINGO 2'!D:AB,7,0) -> 131174 | R79: =VLOOKUP(E79,'DOMINGO 3'!D:AB,7,0) -> #N/A | S79: =VLOOKUP(E79,'DOMINGO 1'!D:AB,11,0) -> 8430 | T79: =VLOOKUP(E79,'DOMINGO 2'!D:AB,11,0) -> 3160 | U79: =VLOOKUP(E79,'DOMINGO 3'!D:AB,11,0) -> #N/A | V79: =VLOOKUP(E79,'FESTIVO 1'!D:AB,7,0) -> 128850 | W79: =VLOOKUP(E79,'FESTIVO 1'!D:AB,11,0) -> 6094
E80: M0432(A TOLEDO) | F80: =VLOOKUP(E80,'ASIGNACION RANKING'!D:AB,7,0)-P80-Q80 -> 1423611 | G80: =VLOOKUP(E80,'ASIGNACION RANKING'!D:AB,6,0) -> 928 | H80: =VLOOKUP(E80,'ASIGNACION RANKING'!D:AB,11,0)-S80-T80 -> 119242 | J80: =H80/F80 -> 0.083760241 | K80: 49 | L80: =K80/$L$30 -> 0.5326087 | M80: =IF(L80<=0.02,"A1",IF(L80<=0.04,"A2",IF(L80<=0.06,"A3",IF(L80<=0.08,"A4",IF(L80<=0.1,"A5",IF(L80<=0.16,"B1",IF(L80<=0.22,"B2",IF(L80<=0.28,"B3",IF(L80<=0.34,"B4",IF(L80<=0.4,"B5",IF(L80<=0.46,"B6",IF(L80<=0.52,"B7",IF(L80<=0.58,"B8",IF(L80<=0.64,"B9",IF(L80<=0.7,"B10",IF(L80<=1.1,"C0")))))))))))))))) -> B8 | N80: =F80*J79-H80 -> 352.85456 | O80: =IF(M80="A1",1650000,IF(M80="A2",1290000,IF(M80="A3",1020000,IF(M80="A4",810000,IF(M80="A5",650000,IF(M80="B1",520000,IF(M80="B2",420000,IF(M80="B3",330000,IF(M80="B4",270000,IF(M80="B5",210000,IF(M80="B6",170000,IF(M80="B7",150000,IF(M80="B8",130000,IF(M80="B9",100000,IF(M80="B10",60000,IF(M80="C0",0)))))))))))))))) -> 130000 | P80: =VLOOKUP(E80,'DOMINGO 1'!D:AB,7,0) -> 118514 | Q80: =VLOOKUP(E80,'DOMINGO 2'!D:AB,7,0) -> 131537 | R80: =VLOOKUP(E80,'DOMINGO 3'!D:AB,7,0) -> #N/A | S80: =VLOOKUP(E80,'DOMINGO 1'!D:AB,11,0) -> 6961 | T80: =VLOOKUP(E80,'DOMINGO 2'!D:AB,11,0) -> 1190 | U80: =VLOOKUP(E80,'DOMINGO 3'!D:AB,11,0) -> #N/A | V80: 0 | W80: =VLOOKUP(E80,'FESTIVO 1'!D:AB,11,0) -> 10935
E81: M0259(A KARINA) | F81: =VLOOKUP(E81,'ASIGNACION RANKING'!D:AB,7,0)-P81-Q81 -> 1539387 | G81: =VLOOKUP(E81,'ASIGNACION RANKING'!D:AB,6,0) -> 1015 | H81: =VLOOKUP(E81,'ASIGNACION RANKING'!D:AB,11,0)-S81-T81 -> 128925 | J81: =H81/F81 -> 0.08375087 | K81: 50 | L81: =K81/$L$30 -> 0.54347826 | M81: =IF(L81<=0.02,"A1",IF(L81<=0.04,"A2",IF(L81<=0.06,"A3",IF(L81<=0.08,"A4",IF(L81<=0.1,"A5",IF(L81<=0.16,"B1",IF(L81<=0.22,"B2",IF(L81<=0.28,"B3",IF(L81<=0.34,"B4",IF(L81<=0.4,"B5",IF(L81<=0.46,"B6",IF(L81<=0.52,"B7",IF(L81<=0.58,"B8",IF(L81<=0.64,"B9",IF(L81<=0.7,"B10",IF(L81<=1.1,"C0")))))))))))))))) -> B8 | N81: =F81*J80-H81 -> 14.425625 | O81: =IF(M81="A1",1650000,IF(M81="A2",1290000,IF(M81="A3",1020000,IF(M81="A4",810000,IF(M81="A5",650000,IF(M81="B1",520000,IF(M81="B2",420000,IF(M81="B3",330000,IF(M81="B4",270000,IF(M81="B5",210000,IF(M81="B6",170000,IF(M81="B7",150000,IF(M81="B8",130000,IF(M81="B9",100000,IF(M81="B10",60000,IF(M81="C0",0)))))))))))))))) -> 130000 | P81: =VLOOKUP(E81,'DOMINGO 1'!D:AB,7,0) -> 140749 | Q81: =VLOOKUP(E81,'DOMINGO 2'!D:AB,7,0) -> 143446 | R81: =VLOOKUP(E81,'DOMINGO 3'!D:AB,7,0) -> #N/A | S81: =VLOOKUP(E81,'DOMINGO 1'!D:AB,11,0) -> 1950 | T81: =VLOOKUP(E81,'DOMINGO 2'!D:AB,11,0) -> 10132 | U81: =VLOOKUP(E81,'DOMINGO 3'!D:AB,11,0) -> #N/A | V81: 0 | W81: =VLOOKUP(E81,'FESTIVO 1'!D:AB,11,0) -> 6281
E82: A0161(E MACIAS) | F82: =VLOOKUP(E82,'ASIGNACION RANKING'!D:AB,7,0)-P82-Q82 -> 1383549 | G82: =VLOOKUP(E82,'ASIGNACION RANKING'!D:AB,6,0) -> 968 | H82: =VLOOKUP(E82,'ASIGNACION RANKING'!D:AB,11,0)-S82-T82 -> 115577 | J82: =H82/F82 -> 0.083536615 | K82: 51 | L82: =K82/$L$30 -> 0.55434783 | M82: =IF(L82<=0.02,"A1",IF(L82<=0.04,"A2",IF(L82<=0.06,"A3",IF(L82<=0.08,"A4",IF(L82<=0.1,"A5",IF(L82<=0.16,"B1",IF(L82<=0.22,"B2",IF(L82<=0.28,"B3",IF(L82<=0.34,"B4",IF(L82<=0.4,"B5",IF(L82<=0.46,"B6",IF(L82<=0.52,"B7",IF(L82<=0.58,"B8",IF(L82<=0.64,"B9",IF(L82<=0.7,"B10",IF(L82<=1.1,"C0")))))))))))))))) -> B8 | N82: =F82*J81-H82 -> 296.43197 | O82: =IF(M82="A1",1650000,IF(M82="A2",1290000,IF(M82="A3",1020000,IF(M82="A4",810000,IF(M82="A5",650000,IF(M82="B1",520000,IF(M82="B2",420000,IF(M82="B3",330000,IF(M82="B4",270000,IF(M82="B5",210000,IF(M82="B6",170000,IF(M82="B7",150000,IF(M82="B8",130000,IF(M82="B9",100000,IF(M82="B10",60000,IF(M82="C0",0)))))))))))))))) -> 130000 | P82: =VLOOKUP(E82,'DOMINGO 1'!D:AB,7,0) -> 144580 | Q82: =VLOOKUP(E82,'DOMINGO 2'!D:AB,7,0) -> 113633 | R82: =VLOOKUP(E82,'DOMINGO 3'!D:AB,7,0) -> #N/A | S82: =VLOOKUP(E82,'DOMINGO 1'!D:AB,11,0) -> 11166 | T82: =VLOOKUP(E82,'DOMINGO 2'!D:AB,11,0) -> 3723 | U82: =VLOOKUP(E82,'DOMINGO 3'!D:AB,11,0) -> #N/A | V82: 0 | W82: =VLOOKUP(E82,'FESTIVO 1'!D:AB,11,0) -> 8165
E83: M0055(P MARYJO) | F83: =VLOOKUP(E83,'ASIGNACION RANKING'!D:AB,7,0)-P83-Q83 -> 1479451 | G83: =VLOOKUP(E83,'ASIGNACION RANKING'!D:AB,6,0) -> 995 | H83: =VLOOKUP(E83,'ASIGNACION RANKING'!D:AB,11,0)-S83-T83 -> 121967 | J83: =H83/F83 -> 0.082440716 | K83: 52 | L83: =K83/$L$30 -> 0.56521739 | M83: =IF(L83<=0.02,"A1",IF(L83<=0.04,"A2",IF(L83<=0.06,"A3",IF(L83<=0.08,"A4",IF(L83<=0.1,"A5",IF(L83<=0.16,"B1",IF(L83<=0.22,"B2",IF(L83<=0.28,"B3",IF(L83<=0.34,"B4",IF(L83<=0.4,"B5",IF(L83<=0.46,"B6",IF(L83<=0.52,"B7",IF(L83<=0.58,"B8",IF(L83<=0.64,"B9",IF(L83<=0.7,"B10",IF(L83<=1.1,"C0")))))))))))))))) -> B8 | N83: =F83*J82-H83 -> 1621.3284 | O83: =IF(M83="A1",1650000,IF(M83="A2",1290000,IF(M83="A3",1020000,IF(M83="A4",810000,IF(M83="A5",650000,IF(M83="B1",520000,IF(M83="B2",420000,IF(M83="B3",330000,IF(M83="B4",270000,IF(M83="B5",210000,IF(M83="B6",170000,IF(M83="B7",150000,IF(M83="B8",130000,IF(M83="B9",100000,IF(M83="B10",60000,IF(M83="C0",0)))))))))))))))) -> 130000 | P83: =VLOOKUP(E83,'DOMINGO 1'!D:AB,7,0) -> 132520 | Q83: =VLOOKUP(E83,'DOMINGO 2'!D:AB,7,0) -> 124488 | R83: =VLOOKUP(E83,'DOMINGO 3'!D:AB,7,0) -> #N/A | S83: =VLOOKUP(E83,'DOMINGO 1'!D:AB,11,0) -> 7054 | T83: =VLOOKUP(E83,'DOMINGO 2'!D:AB,11,0) -> 4868 | U83: =VLOOKUP(E83,'DOMINGO 3'!D:AB,11,0) -> #N/A | V83: 0 | W83: =VLOOKUP(E83,'FESTIVO 1'!D:AB,11,0) -> 10359
E84: M0376(A OSWALDO) | F84: =VLOOKUP(E84,'ASIGNACION RANKING'!D:AB,7,0)-P84-Q84 -> 1325989 | G84: =VLOOKUP(E84,'ASIGNACION RANKING'!D:AB,6,0) -> 887 | H84: =VLOOKUP(E84,'ASIGNACION RANKING'!D:AB,11,0)-S84-T84 -> 109228 | J84: =H84/F84 -> 0.082374741 | K84: 53 | L84: =K84/$L$30 -> 0.57608696 | M84: =IF(L84<=0.02,"A1",IF(L84<=0.04,"A2",IF(L84<=0.06,"A3",IF(L84<=0.08,"A4",IF(L84<=0.1,"A5",IF(L84<=0.16,"B1",IF(L84<=0.22,"B2",IF(L84<=0.28,"B3",IF(L84<=0.34,"B4",IF(L84<=0.4,"B5",IF(L84<=0.46,"B6",IF(L84<=0.52,"B7",IF(L84<=0.58,"B8",IF(L84<=0.64,"B9",IF(L84<=0.7,"B10",IF(L84<=1.1,"C0")))))))))))))))) -> B8 | N84: =F84*J83-H84 -> 87.482813 | O84: =IF(M84="A1",1650000,IF(M84="A2",1290000,IF(M84="A3",1020000,IF(M84="A4",810000,IF(M84="A5",650000,IF(M84="B1",520000,IF(M84="B2",420000,IF(M84="B3",330000,IF(M84="B4",270000,IF(M84="B5",210000,IF(M84="B6",170000,IF(M84="B7",150000,IF(M84="B8",130000,IF(M84="B9",100000,IF(M84="B10",60000,IF(M84="C0",0)))))))))))))))) -> 130000 | P84: =VLOOKUP(E84,'DOMINGO 1'!D:AB,7,0) -> 135492 | Q84: =VLOOKUP(E84,'DOMINGO 2'!D:AB,7,0) -> 108647 | R84: =VLOOKUP(E84,'DOMINGO 3'!D:AB,7,0) -> #N/A | S84: =VLOOKUP(E84,'DOMINGO 1'!D:AB,11,0) -> 5820 | T84: =VLOOKUP(E84,'DOMINGO 2'!D:AB,11,0) -> 10231 | U84: =VLOOKUP(E84,'DOMINGO 3'!D:AB,11,0) -> #N/A | V84: 0 | W84: =VLOOKUP(E84,'FESTIVO 1'!D:AB,11,0) -> 7944
